Workbook

Sheet README
A1: Health IBNR model: 2026-09 valuation (live formulas)
A3: How to use
A4: 1. Each category has Triangle (data), Ratios, Factors and Reserve sheets.
A5: 2. Type a link ratio into a yellow Override cell on a Factors sheet. Completion factors, ultimates, IBNR and the Summary recalculate.
A6: 3. Margin, CAE, the PMPM/B-F cut-off and backlog gross-up ratios are yellow cells on the Assumptions sheet.
A7: 4. Grey ratios on the Ratios sheets are excluded from the averages (see the Selections log in the exhibits workbook).
A8: 5. Expected PMPM (blue) comes from the Python trend fit: log-linear trend with calendar-month seasonality.
A10: Colour key: blue font = data input; yellow fill = judgment input; black = formula; grey fill = excluded ratio.
A11: Summary column 'Python engine' shows the model of record. 'Difference' should be zero until you change an input.

Sheet Summary
A1: Category | B1: Paid to date | C1: IBNR | D1: Margin | E1: CAE | F1: Total liability | G1: Python engine IBNR | H1: Difference
A2: Inpatient (ex. large) | B2: ='IP Reserve'!D47 | C2: ='IP Reserve'!L47 | D2: =C2*Assumptions!$B$4 | E2: =(C2+D2)*Assumptions!$B$5 | F2: =C2+D2+E2 | G2: 65138744 | H2: =C2-G2
A3: Outpatient | B3: ='OP Reserve'!D47 | C3: ='OP Reserve'!L47 | D3: =C3*Assumptions!$B$4 | E3: =(C3+D3)*Assumptions!$B$5 | F3: =C3+D3+E3 | G3: 71888260 | H3: =C3-G3
A4: Professional | B4: ='Prof Reserve'!D47 | C4: ='Prof Reserve'!L47 | D4: =C4*Assumptions!$B$4 | E4: =(C4+D4)*Assumptions!$B$5 | F4: =C4+D4+E4 | G4: 45653039 | H4: =C4-G4
A5: Large claims (>$250k) | B5: ='LC Reserve'!D47 | C5: ='LC Reserve'!L47 | D5: =C5*Assumptions!$B$4 | E5: =(C5+D5)*Assumptions!$B$5 | F5: =C5+D5+E5 | G5: 43566758 | H5: =C5-G5
A6: Total | B6: =SUM(B2:B5) | C6: =SUM(C2:C5) | D6: =SUM(D2:D5) | E6: =SUM(E2:E5) | F6: =SUM(F2:F5) | G6: =SUM(G2:G5) | H6: =SUM(H2:H5)

Sheet Assumptions
A1: Assumption | B1: Value | C1: Note
A2: Valuation month | B2: 2026-09 | C2: Paid-through month
A3: PMPM / B-F months | B3: 3 | C3: Incurred months younger than this lag use B-F on the PMPM expected
A4: Margin % | B4: 0.075 | C4: Provision for adverse deviation on IBNR
A5: CAE % | B5: 0.025 | C5: Claim adjustment expense on IBNR + margin
A6: Backlog gross-up ratio: IP | B6: 1 | C6: Paid in valuation month / (paid + excess pended). 1.0 = no backlog
A7: Backlog gross-up ratio: OP | B7: 1 | C7: Paid in valuation month / (paid + excess pended). 1.0 = no backlog
A8: Backlog gross-up ratio: Prof | B8: 1 | C8: Paid in valuation month / (paid + excess pended). 1.0 = no backlog
A9: Backlog gross-up ratio: LC | B9: 1 | C9: Paid in valuation month / (paid + excess pended). 1.0 = no backlog

Sheet IP Triangle
A1: Incurred | B1: Lag 0 | C1: Lag 1 | D1: Lag 2 | E1: Lag 3 | F1: Lag 4 | G1: Lag 5 | H1: Lag 6 | I1: Lag 7 | J1: Lag 8 | K1: Lag 9 | L1: Lag 10 | M1: Lag 11 | N1: Lag 12 | O1: Lag 13 | P1: Lag 14 | Q1: Lag 15 | R1: Lag 16 | S1: Lag 17 | T1: Lag 18 | U1: Lag 19 | V1: Lag 20 | W1: Lag 21 | X1: Lag 22 | Y1: Lag 23 | Z1: Lag 24 | AA1: Lag 25 | AB1: Lag 26 | AC1: Lag 27 | AD1: Lag 28 | AE1: Lag 29 | AF1: Lag 30 | AG1: Lag 31 | AH1: Lag 32 | AI1: Lag 33 | AJ1: Lag 34 | AK1: Lag 35 | AL1: Lag 36 | AM1: Lag 37 | AN1: Lag 38 | AO1: Lag 39 | AP1: Lag 40 | AQ1: Lag 41 | AR1: Lag 42 | AS1: Lag 43 | AT1: Lag 44
A2: 2023-01 | B2: 2223686.8 | C2: 5991719.2 | D2: 9146020.4 | E2: 11433879 | F2: 13078776 | G2: 14116374 | H2: 14882654 | I2: 15365672 | J2: 15680081 | K2: 15909958 | L2: 16066729 | M2: 16163140 | N2: 16225892 | O2: 16265585 | P2: 16293209 | Q2: 16311612 | R2: 16322833 | S2: 16330220 | T2: 16335166 | U2: 16338309 | V2: 16340339 | W2: 16341645 | X2: 16342513 | Y2: 16343082 | Z2: 16343450 | AA2: 16343677 | AB2: 16343837 | AC2: 16343938 | AD2: 16344001 | AE2: 16344041 | AF2: 16344069 | AG2: 16344086 | AH2: 16344098 | AI2: 16344105 | AJ2: 16344110 | AK2: 16344113 | AL2: 16344115 | AM2: 16344115 | AN2: 16344115 | AO2: 16344115 | AP2: 16344115 | AQ2: 16344115 | AR2: 16344115 | AS2: 16344115 | AT2: 16344115
A3: 2023-02 | B3: 2294770.3 | C3: 6313241.1 | D3: 9617771.7 | E3: 11964281 | F3: 13599746 | G3: 14666615 | H3: 15428321 | I3: 15941453 | J3: 16277440 | K3: 16485326 | L3: 16623272 | M3: 16724738 | N3: 16789299 | O3: 16829593 | P3: 16854904 | Q3: 16872264 | R3: 16884021 | S3: 16891619 | T3: 16896559 | U3: 16899797 | V3: 16901892 | W3: 16903236 | X3: 16904144 | Y3: 16904695 | Z3: 16905043 | AA3: 16905267 | AB3: 16905419 | AC3: 16905515 | AD3: 16905580 | AE3: 16905621 | AF3: 16905646 | AG3: 16905662 | AH3: 16905674 | AI3: 16905681 | AJ3: 16905685 | AK3: 16905688 | AL3: 16905690 | AM3: 16905690 | AN3: 16905690 | AO3: 16905690 | AP3: 16905690 | AQ3: 16905690 | AR3: 16905690 | AS3: 16905690
A4: 2023-03 | B4: 2368953.5 | C4: 6658129.5 | D4: 9946001.7 | E4: 12324762 | F4: 14083626 | G4: 15138009 | H4: 15908506 | I4: 16432138 | J4: 16782346 | K4: 17015599 | L4: 17169823 | M4: 17269910 | N4: 17334685 | O4: 17377833 | P4: 17407385 | Q4: 17426039 | R4: 17438342 | S4: 17445760 | T4: 17450587 | U4: 17453859 | V4: 17456012 | W4: 17457429 | X4: 17458358 | Y4: 17458913 | Z4: 17459277 | AA4: 17459514 | AB4: 17459665 | AC4: 17459764 | AD4: 17459828 | AE4: 17459871 | AF4: 17459899 | AG4: 17459916 | AH4: 17459927 | AI4: 17459935 | AJ4: 17459939 | AK4: 17459942 | AL4: 17459944 | AM4: 17459944 | AN4: 17459944 | AO4: 17459944 | AP4: 17459944 | AQ4: 17459944 | AR4: 17459944
A5: 2023-04 | B5: 2643028.1 | C5: 7482429.9 | D5: 11171610 | E5: 13870489 | F5: 15789694 | G5: 17103903 | H5: 17929679 | I5: 18561550 | J5: 18959715 | K5: 19209218 | L5: 19381907 | M5: 19493398 | N5: 19563454 | O5: 19611364 | P5: 19641902 | Q5: 19661937 | R5: 19674532 | S5: 19683092 | T5: 19688657 | U5: 19692185 | V5: 19694612 | W5: 19696090 | X5: 19697065 | Y5: 19697691 | Z5: 19698105 | AA5: 19698363 | AB5: 19698532 | AC5: 19698641 | AD5: 19698713 | AE5: 19698756 | AF5: 19698786 | AG5: 19698807 | AH5: 19698819 | AI5: 19698827 | AJ5: 19698831 | AK5: 19698835 | AL5: 19698837 | AM5: 19698837 | AN5: 19698837 | AO5: 19698837 | AP5: 19698837 | AQ5: 19698837
A6: 2023-05 | B6: 2424616 | C6: 7317241.1 | D6: 10733832 | E6: 13169383 | F6: 14867488 | G6: 16038729 | H6: 16849514 | I6: 17362566 | J6: 17695552 | K6: 17928174 | L6: 18077216 | M6: 18178841 | N6: 18251113 | O6: 18295009 | P6: 18322227 | Q6: 18340430 | R6: 18352384 | S6: 18359838 | T6: 18364937 | U6: 18368146 | V6: 18370294 | W6: 18371666 | X6: 18372471 | Y6: 18373035 | Z6: 18373385 | AA6: 18373613 | AB6: 18373759 | AC6: 18373856 | AD6: 18373916 | AE6: 18373956 | AF6: 18373981 | AG6: 18373997 | AH6: 18374007 | AI6: 18374014 | AJ6: 18374018 | AK6: 18374021 | AL6: 18374023 | AM6: 18374023 | AN6: 18374023 | AO6: 18374023 | AP6: 18374023
A7: 2023-06 | B7: 2342849.5 | C7: 6620503.3 | D7: 10120072 | E7: 12563985 | F7: 14219875 | G7: 15401418 | H7: 16167807 | I7: 16679337 | J7: 17002780 | K7: 17226281 | L7: 17379300 | M7: 17476356 | N7: 17539938 | O7: 17579934 | P7: 17606580 | Q7: 17623068 | R7: 17634419 | S7: 17641607 | T7: 17646383 | U7: 17649278 | V7: 17651360 | W7: 17652672 | X7: 17653532 | Y7: 17654077 | Z7: 17654428 | AA7: 17654662 | AB7: 17654805 | AC7: 17654900 | AD7: 17654957 | AE7: 17654995 | AF7: 17655018 | AG7: 17655034 | AH7: 17655044 | AI7: 17655051 | AJ7: 17655055 | AK7: 17655058 | AL7: 17655059 | AM7: 17655059 | AN7: 17655059 | AO7: 17655059
A8: 2023-07 | B8: 2455059.7 | C8: 7031679.7 | D8: 10375866 | E8: 12804400 | F8: 14473942 | G8: 15683641 | H8: 16493146 | I8: 17054698 | J8: 17401961 | K8: 17629648 | L8: 17773857 | M8: 17871292 | N8: 17937391 | O8: 17979599 | P8: 18007120 | Q8: 18025150 | R8: 18036454 | S8: 18043731 | T8: 18048604 | U8: 18051675 | V8: 18053634 | W8: 18054985 | X8: 18055832 | Y8: 18056361 | Z8: 18056698 | AA8: 18056906 | AB8: 18057051 | AC8: 18057141 | AD8: 18057201 | AE8: 18057238 | AF8: 18057262 | AG8: 18057278 | AH8: 18057288 | AI8: 18057294 | AJ8: 18057298 | AK8: 18057301 | AL8: 18057303 | AM8: 18057303 | AN8: 18057303
A9: 2023-08 | B9: 2486264.4 | C9: 7358804.5 | D9: 10960525 | E9: 13491504 | F9: 15278002 | G9: 16534196 | H9: 17338812 | I9: 17869202 | J9: 18229554 | K9: 18465629 | L9: 18613564 | M9: 18710873 | N9: 18776648 | O9: 18819936 | P9: 18848639 | Q9: 18866692 | R9: 18878251 | S9: 18885430 | T9: 18890393 | U9: 18893623 | V9: 18895616 | W9: 18896910 | X9: 18897715 | Y9: 18898251 | Z9: 18898602 | AA9: 18898830 | AB9: 18898964 | AC9: 18899053 | AD9: 18899109 | AE9: 18899147 | AF9: 18899171 | AG9: 18899186 | AH9: 18899195 | AI9: 18899201 | AJ9: 18899205 | AK9: 18899208 | AL9: 18899210 | AM9: 18899210
A10: 2023-09 | B10: 2434282.7 | C10: 6939321.2 | D10: 10441862 | E10: 12854952 | F10: 14570694 | G10: 15715482 | H10: 16474994 | I10: 16968907 | J10: 17304059 | K10: 17517592 | L10: 17659742 | M10: 17755057 | N10: 17817610 | O10: 17856852 | P10: 17882032 | Q10: 17898196 | R10: 17909142 | S10: 17916191 | T10: 17920774 | U10: 17923553 | V10: 17925440 | W10: 17926612 | X10: 17927410 | Y10: 17927926 | Z10: 17928245 | AA10: 17928441 | AB10: 17928569 | AC10: 17928652 | AD10: 17928707 | AE10: 17928740 | AF10: 17928763 | AG10: 17928778 | AH10: 17928787 | AI10: 17928793 | AJ10: 17928797 | AK10: 17928799 | AL10: 17928801
A11: 2023-10 | B11: 2612330.9 | C11: 7331311.5 | D11: 10995055 | E11: 13705527 | F11: 15467140 | G11: 16707348 | H11: 17556030 | I11: 18095482 | J11: 18452606 | K11: 18688516 | L11: 18842168 | M11: 18942327 | N11: 19004480 | O11: 19045813 | P11: 19072885 | Q11: 19090481 | R11: 19101410 | S11: 19108690 | T11: 19113652 | U11: 19116735 | V11: 19118654 | W11: 19119901 | X11: 19120721 | Y11: 19121242 | Z11: 19121578 | AA11: 19121808 | AB11: 19121946 | AC11: 19122033 | AD11: 19122089 | AE11: 19122124 | AF11: 19122148 | AG11: 19122163 | AH11: 19122170 | AI11: 19122177 | AJ11: 19122181 | AK11: 19122184
A12: 2023-11 | B12: 2476255.6 | C12: 7067072.7 | D12: 10778528 | E12: 13412667 | F12: 15232059 | G12: 16451105 | H12: 17292566 | I12: 17822223 | J12: 18168628 | K12: 18395348 | L12: 18543373 | M12: 18639623 | N12: 18704591 | O12: 18744374 | P12: 18769843 | Q12: 18787236 | R12: 18797706 | S12: 18804712 | T12: 18809216 | U12: 18812116 | V12: 18814028 | W12: 18815215 | X12: 18815965 | Y12: 18816450 | Z12: 18816770 | AA12: 18816985 | AB12: 18817110 | AC12: 18817193 | AD12: 18817247 | AE12: 18817280 | AF12: 18817302 | AG12: 18817314 | AH12: 18817324 | AI12: 18817330 | AJ12: 18817333
A13: 2023-12 | B13: 3016686.1 | C13: 8502841.5 | D13: 12752657 | E13: 15841933 | F13: 17985060 | G13: 19366547 | H13: 20299795 | I13: 20921321 | J13: 21302646 | K13: 21567625 | L13: 21739366 | M13: 21854954 | N13: 21927195 | O13: 21975957 | P13: 22006759 | Q13: 22027084 | R13: 22040276 | S13: 22048028 | T13: 22053107 | U13: 22056366 | V13: 22058564 | W13: 22059934 | X13: 22060797 | Y13: 22061364 | Z13: 22061726 | AA13: 22061970 | AB13: 22062116 | AC13: 22062215 | AD13: 22062274 | AE13: 22062316 | AF13: 22062338 | AG13: 22062356 | AH13: 22062366 | AI13: 22062372
A14: 2024-01 | B14: 2918876.3 | C14: 8030524.1 | D14: 11818589 | E14: 14629218 | F14: 16613604 | G14: 17911515 | H14: 18760078 | I14: 19313479 | J14: 19683619 | K14: 19938132 | L14: 20088484 | M14: 20195357 | N14: 20262998 | O14: 20306140 | P14: 20333113 | Q14: 20351035 | R14: 20362797 | S14: 20370166 | T14: 20374804 | U14: 20377769 | V14: 20379694 | W14: 20380951 | X14: 20381777 | Y14: 20382287 | Z14: 20382611 | AA14: 20382823 | AB14: 20382952 | AC14: 20383038 | AD14: 20383091 | AE14: 20383120 | AF14: 20383147 | AG14: 20383161 | AH14: 20383169
A15: 2024-02 | B15: 2708480.4 | C15: 7914023.9 | D15: 11613089 | E15: 14207421 | F15: 15897064 | G15: 17107858 | H15: 17895099 | I15: 18419271 | J15: 18754605 | K15: 18982874 | L15: 19133729 | M15: 19232004 | N15: 19294029 | O15: 19331936 | P15: 19357926 | Q15: 19374760 | R15: 19385286 | S15: 19391576 | T15: 19395703 | U15: 19398489 | V15: 19400235 | W15: 19401463 | X15: 19402160 | Y15: 19402622 | Z15: 19402932 | AA15: 19403118 | AB15: 19403242 | AC15: 19403315 | AD15: 19403359 | AE15: 19403395 | AF15: 19403415 | AG15: 19403427
A16: 2024-03 | B16: 2642112.8 | C16: 7532822.5 | D16: 11554169 | E16: 14212668 | F16: 16192306 | G16: 17516320 | H16: 18324778 | I16: 18895029 | J16: 19242518 | K16: 19485679 | L16: 19635856 | M16: 19736392 | N16: 19798307 | O16: 19841068 | P16: 19868222 | Q16: 19885515 | R16: 19896805 | S16: 19903623 | T16: 19908004 | U16: 19910950 | V16: 19912744 | W16: 19913904 | X16: 19914675 | Y16: 19915138 | Z16: 19915438 | AA16: 19915622 | AB16: 19915741 | AC16: 19915809 | AD16: 19915867 | AE16: 19915899 | AF16: 19915920
A17: 2024-04 | B17: 2864228.9 | C17: 8200510.1 | D17: 12390556 | E17: 15436815 | F17: 17393873 | G17: 18798316 | H17: 19718729 | I17: 20301645 | J17: 20698993 | K17: 20958795 | L17: 21114444 | M17: 21220008 | N17: 21289621 | O17: 21334615 | P17: 21363198 | Q17: 21380764 | R17: 21392169 | S17: 21399568 | T17: 21404167 | U17: 21407327 | V17: 21409294 | W17: 21410497 | X17: 21411280 | Y17: 21411781 | Z17: 21412104 | AA17: 21412301 | AB17: 21412412 | AC17: 21412510 | AD17: 21412561 | AE17: 21412595
A18: 2024-05 | B18: 2878060.9 | C18: 8291529.6 | D18: 12645848 | E18: 15729412 | F18: 17796838 | G18: 19194100 | H18: 20102427 | I18: 20731641 | J18: 21129840 | K18: 21384385 | L18: 21556446 | M18: 21666511 | N18: 21735871 | O18: 21780503 | P18: 21808956 | Q18: 21827610 | R18: 21839567 | S18: 21847178 | T18: 21851900 | U18: 21854837 | V18: 21856803 | W18: 21858054 | X18: 21858840 | Y18: 21859333 | Z18: 21859652 | AA18: 21859841 | AB18: 21859993 | AC18: 21860077 | AD18: 21860130
A19: 2024-06 | B19: 2843018.6 | C19: 8208312.3 | D19: 12222789 | E19: 15056763 | F19: 17002160 | G19: 18283703 | H19: 19177112 | I19: 19739417 | J19: 20112970 | K19: 20344615 | L19: 20493280 | M19: 20595674 | N19: 20659553 | O19: 20698486 | P19: 20725479 | Q19: 20742048 | R19: 20753048 | S19: 20759784 | T19: 20763997 | U19: 20766670 | V19: 20768405 | W19: 20769581 | X19: 20770303 | Y19: 20770737 | Z19: 20770974 | AA19: 20771183 | AB19: 20771291 | AC19: 20771358
A20: 2024-07 | B20: 2705308.4 | C20: 7935499 | D20: 12013299 | E20: 14731646 | F20: 16571050 | G20: 17791115 | H20: 18648782 | I20: 19184111 | J20: 19564720 | K20: 19794947 | L20: 19952473 | M20: 20053224 | N20: 20113827 | O20: 20153306 | P20: 20178837 | Q20: 20194765 | R20: 20204913 | S20: 20211714 | T20: 20215979 | U20: 20218753 | V20: 20220481 | W20: 20221593 | X20: 20222274 | Y20: 20222667 | Z20: 20222990 | AA20: 20223165 | AB20: 20223278
A21: 2024-08 | B21: 3151649.3 | C21: 8248249 | D21: 12281399 | E21: 15261588 | F21: 17282585 | G21: 18695152 | H21: 19594409 | I21: 20194232 | J21: 20572661 | K21: 20808033 | L21: 20962469 | M21: 21070088 | N21: 21135512 | O21: 21177349 | P21: 21204211 | Q21: 21221079 | R21: 21232021 | S21: 21238628 | T21: 21243036 | U21: 21245765 | V21: 21247531 | W21: 21248638 | X21: 21249264 | Y21: 21249796 | Z21: 21250087 | AA21: 21250258
A22: 2024-09 | B22: 2921301.6 | C22: 8284699.8 | D22: 12421179 | E22: 15221395 | F22: 17118539 | G22: 18429811 | H22: 19264388 | I22: 19838820 | J22: 20191635 | K22: 20427470 | L22: 20574078 | M22: 20668628 | N22: 20729941 | O22: 20769621 | P22: 20793330 | Q22: 20809398 | R22: 20819367 | S22: 20825715 | T22: 20829853 | U22: 20832442 | V22: 20834049 | W22: 20834962 | X22: 20835736 | Y22: 20836147 | Z22: 20836402
A23: 2024-10 | B23: 3291786.1 | C23: 9208576.7 | D23: 13706672 | E23: 16875447 | F23: 18979375 | G23: 20385471 | H23: 21276019 | I23: 21879977 | J23: 22289863 | K23: 22542519 | L23: 22710128 | M23: 22817528 | N23: 22885694 | O23: 22928270 | P23: 22956287 | Q23: 22972799 | R23: 22983833 | S23: 22990538 | T23: 22994862 | U23: 22997569 | V23: 22999135 | W23: 23000436 | X23: 23001195 | Y23: 23001650
A24: 2024-11 | B24: 3237868.6 | C24: 8900497.7 | D24: 13321459 | E24: 16496883 | F24: 18574340 | G24: 19959925 | H24: 20863975 | I24: 21453420 | J24: 21838020 | K24: 22089920 | L24: 22245356 | M24: 22346962 | N24: 22415921 | O24: 22455644 | P24: 22482804 | Q24: 22499286 | R24: 22509905 | S24: 22516604 | T24: 22520810 | U24: 22523262 | V24: 22525341 | W24: 22526431 | X24: 22527149
A25: 2024-12 | B25: 3473698 | C25: 9626924.6 | D25: 14185378 | E25: 17440838 | F25: 19779385 | G25: 21278426 | H25: 22251458 | I25: 22884693 | J25: 23284994 | K25: 23545909 | L25: 23708147 | M25: 23816917 | N25: 23884317 | O25: 23929991 | P25: 23956561 | Q25: 23974153 | R25: 23984847 | S25: 23992078 | T25: 23995980 | U25: 23999320 | V25: 24001056 | W25: 24002178
A26: 2025-01 | B26: 3227119.6 | C26: 9079173.6 | D26: 13335349 | E26: 16449771 | F26: 18692097 | G26: 20048582 | H26: 21006752 | I26: 21587602 | J26: 21957498 | K26: 22192544 | L26: 22346362 | M26: 22442380 | N26: 22506753 | O26: 22547045 | P26: 22572698 | Q26: 22589575 | R26: 22600074 | S26: 22605784 | T26: 22610646 | U26: 22613196 | V26: 22614794
A27: 2025-02 | B27: 2969490.7 | C27: 8688017.8 | D27: 12674290 | E27: 15636116 | F27: 17515323 | G27: 18824044 | H27: 19714970 | I27: 20281723 | J27: 20648523 | K27: 20874874 | L27: 21018149 | M27: 21110924 | N27: 21170040 | O27: 21207328 | P27: 21231282 | Q27: 21245806 | R27: 21254121 | S27: 21261223 | T27: 21264994 | U27: 21267310
A28: 2025-03 | B28: 3019875.6 | C28: 8344612.5 | D28: 12575652 | E28: 15634406 | F28: 17594444 | G28: 18953808 | H28: 19844793 | I28: 20374177 | J28: 20732292 | K28: 20977759 | L28: 21119114 | M28: 21211247 | N28: 21270776 | O28: 21309669 | P28: 21333405 | Q28: 21346723 | R28: 21358227 | S28: 21364276 | T28: 21368088
A29: 2025-04 | B29: 3528729.5 | C29: 9328168.5 | D29: 13809156 | E29: 17066464 | F29: 19158586 | G29: 20535847 | H29: 21461068 | I29: 22022485 | J29: 22405804 | K29: 22657820 | L29: 22817064 | M29: 22910578 | N29: 22970975 | O29: 23011096 | P29: 23032838 | Q29: 23051867 | R29: 23062309 | S29: 23068652
A30: 2025-05 | B30: 3275776.9 | C30: 9253777.1 | D30: 13701090 | E30: 16941084 | F30: 19063974 | G30: 20470184 | H30: 21401098 | I30: 22002551 | J30: 22371444 | K30: 22623592 | L30: 22778324 | M30: 22876143 | N30: 22939205 | O30: 22973306 | P30: 23001214 | Q30: 23016030 | R30: 23026182
A31: 2025-06 | B31: 3517443.9 | C31: 9920730.4 | D31: 14314060 | E31: 17501467 | F31: 19549387 | G31: 21007382 | H31: 21946286 | I31: 22557094 | J31: 22965556 | K31: 23212981 | L31: 23363545 | M31: 23463727 | N31: 23519468 | O31: 23566596 | P31: 23590300 | Q31: 23605034
A32: 2025-07 | B32: 3356398.2 | C32: 9393397.3 | D32: 13786555 | E32: 16786351 | F32: 18847537 | G32: 20340118 | H32: 21214887 | I32: 21795223 | J32: 22192546 | K32: 22425910 | L32: 22578459 | M32: 22661568 | N32: 22735787 | O32: 22774371 | P32: 22797932
A33: 2025-08 | B33: 3141229.6 | C33: 8813975.1 | D33: 13205570 | E33: 16330444 | F33: 18287202 | G33: 19633209 | H33: 20502647 | I33: 21012780 | J33: 21360619 | K33: 21590674 | L33: 21716376 | M33: 21826043 | N33: 21882254 | O33: 21918180
A34: 2025-09 | B34: 3412715.4 | C34: 10059927 | D34: 14571999 | E34: 17791379 | F34: 19948525 | G34: 21372245 | H34: 22290308 | I34: 22881516 | J34: 23249983 | K34: 23452087 | L34: 23625427 | M34: 23717346 | N34: 23777837
A35: 2025-10 | B35: 3830933.8 | C35: 10614910 | D35: 15586167 | E35: 18972141 | F35: 21405304 | G35: 22894622 | H35: 23883568 | I35: 24521337 | J35: 24851096 | K35: 25143650 | L35: 25310532 | M35: 25410117
A36: 2025-11 | B36: 3868183.5 | C36: 10995690 | D36: 16000478 | E36: 19255825 | F36: 21529367 | G36: 23053046 | H36: 24035263 | I36: 24578330 | J36: 25042423 | K36: 25295194 | L36: 25449717
A37: 2025-12 | B37: 4082932.6 | C37: 11258057 | D37: 16391566 | E37: 20002411 | F37: 22579644 | G37: 24196386 | H37: 25106293 | I37: 25906603 | J37: 26331105 | K37: 26592485
A38: 2026-01 | B38: 3551488.8 | C38: 9742748.7 | D38: 14225638 | E38: 17333405 | F38: 19491103 | G38: 20639483 | H38: 21688923 | I38: 22242263 | J38: 22605863
A39: 2026-02 | B39: 3832070.7 | C39: 10502602 | D39: 15340847 | E39: 18769410 | F39: 20820174 | G39: 22515091 | H39: 23485931 | I39: 24061764
A40: 2026-03 | B40: 3702489.9 | C40: 10162880 | D40: 14908747 | E40: 17992734 | F40: 20598786 | G40: 22119629 | H40: 23041091
A41: 2026-04 | B41: 3838325.4 | C41: 10835504 | D41: 15477125 | E41: 19787944 | F41: 22126013 | G41: 23607892
A42: 2026-05 | B42: 3970160 | C42: 9681927.2 | D42: 15637619 | E42: 19018236 | F42: 21410489
A43: 2026-06 | B43: 3402671.7 | C43: 10465420 | D43: 15419053 | E43: 18745121
A44: 2026-07 | B44: 3941533 | C44: 10626126 | D44: 15698560
A45: 2026-08 | B45: 4301101.6 | C45: 12076534
A46: 2026-09 | B46: 3880709.6

Sheet IP Ratios
A1: Incurred | B1: 0-1 | C1: 1-2 | D1: 2-3 | E1: 3-4 | F1: 4-5 | G1: 5-6 | H1: 6-7 | I1: 7-8 | J1: 8-9 | K1: 9-10 | L1: 10-11 | M1: 11-12 | N1: 12-13 | O1: 13-14 | P1: 14-15 | Q1: 15-16 | R1: 16-17 | S1: 17-18 | T1: 18-19 | U1: 19-20 | V1: 20-21 | W1: 21-22 | X1: 22-23 | Y1: 23-24 | Z1: 24-25 | AA1: 25-26 | AB1: 26-27 | AC1: 27-28 | AD1: 28-29 | AE1: 29-30 | AF1: 30-31 | AG1: 31-32 | AH1: 32-33 | AI1: 33-34 | AJ1: 34-35 | AK1: 35-36 | AL1: 36-37 | AM1: 37-38 | AN1: 38-39 | AO1: 39-40 | AP1: 40-41 | AQ1: 41-42 | AR1: 42-43 | AS1: 43-44
A2: 2023-01 | B2: =IF('IP Triangle'!B2>0,'IP Triangle'!C2/'IP Triangle'!B2,"") | C2: =IF('IP Triangle'!C2>0,'IP Triangle'!D2/'IP Triangle'!C2,"") | D2: =IF('IP Triangle'!D2>0,'IP Triangle'!E2/'IP Triangle'!D2,"") | E2: =IF('IP Triangle'!E2>0,'IP Triangle'!F2/'IP Triangle'!E2,"") | F2: =IF('IP Triangle'!F2>0,'IP Triangle'!G2/'IP Triangle'!F2,"") | G2: =IF('IP Triangle'!G2>0,'IP Triangle'!H2/'IP Triangle'!G2,"") | H2: =IF('IP Triangle'!H2>0,'IP Triangle'!I2/'IP Triangle'!H2,"") | I2: =IF('IP Triangle'!I2>0,'IP Triangle'!J2/'IP Triangle'!I2,"") | ... AS2: =IF('IP Triangle'!AS2>0,'IP Triangle'!AT2/'IP Triangle'!AS2,"")
A3: 2023-02 | B3: =IF('IP Triangle'!B3>0,'IP Triangle'!C3/'IP Triangle'!B3,"") | C3: =IF('IP Triangle'!C3>0,'IP Triangle'!D3/'IP Triangle'!C3,"") | D3: =IF('IP Triangle'!D3>0,'IP Triangle'!E3/'IP Triangle'!D3,"") | E3: =IF('IP Triangle'!E3>0,'IP Triangle'!F3/'IP Triangle'!E3,"") | F3: =IF('IP Triangle'!F3>0,'IP Triangle'!G3/'IP Triangle'!F3,"") | G3: =IF('IP Triangle'!G3>0,'IP Triangle'!H3/'IP Triangle'!G3,"") | H3: =IF('IP Triangle'!H3>0,'IP Triangle'!I3/'IP Triangle'!H3,"") | I3: =IF('IP Triangle'!I3>0,'IP Triangle'!J3/'IP Triangle'!I3,"") | ... AR3: =IF('IP Triangle'!AR3>0,'IP Triangle'!AS3/'IP Triangle'!AR3,"")
A4: 2023-03 | B4: =IF('IP Triangle'!B4>0,'IP Triangle'!C4/'IP Triangle'!B4,"") | C4: =IF('IP Triangle'!C4>0,'IP Triangle'!D4/'IP Triangle'!C4,"") | D4: =IF('IP Triangle'!D4>0,'IP Triangle'!E4/'IP Triangle'!D4,"") | E4: =IF('IP Triangle'!E4>0,'IP Triangle'!F4/'IP Triangle'!E4,"") | F4: =IF('IP Triangle'!F4>0,'IP Triangle'!G4/'IP Triangle'!F4,"") | G4: =IF('IP Triangle'!G4>0,'IP Triangle'!H4/'IP Triangle'!G4,"") | H4: =IF('IP Triangle'!H4>0,'IP Triangle'!I4/'IP Triangle'!H4,"") | I4: =IF('IP Triangle'!I4>0,'IP Triangle'!J4/'IP Triangle'!I4,"") | ... AQ4: =IF('IP Triangle'!AQ4>0,'IP Triangle'!AR4/'IP Triangle'!AQ4,"")
A5: 2023-04 | B5: =IF('IP Triangle'!B5>0,'IP Triangle'!C5/'IP Triangle'!B5,"") | C5: =IF('IP Triangle'!C5>0,'IP Triangle'!D5/'IP Triangle'!C5,"") | D5: =IF('IP Triangle'!D5>0,'IP Triangle'!E5/'IP Triangle'!D5,"") | E5: =IF('IP Triangle'!E5>0,'IP Triangle'!F5/'IP Triangle'!E5,"") | F5: =IF('IP Triangle'!F5>0,'IP Triangle'!G5/'IP Triangle'!F5,"") | G5: =IF('IP Triangle'!G5>0,'IP Triangle'!H5/'IP Triangle'!G5,"") | H5: =IF('IP Triangle'!H5>0,'IP Triangle'!I5/'IP Triangle'!H5,"") | I5: =IF('IP Triangle'!I5>0,'IP Triangle'!J5/'IP Triangle'!I5,"") | ... AP5: =IF('IP Triangle'!AP5>0,'IP Triangle'!AQ5/'IP Triangle'!AP5,"")
A6: 2023-05 | B6: =IF('IP Triangle'!B6>0,'IP Triangle'!C6/'IP Triangle'!B6,"") | C6: =IF('IP Triangle'!C6>0,'IP Triangle'!D6/'IP Triangle'!C6,"") | D6: =IF('IP Triangle'!D6>0,'IP Triangle'!E6/'IP Triangle'!D6,"") | E6: =IF('IP Triangle'!E6>0,'IP Triangle'!F6/'IP Triangle'!E6,"") | F6: =IF('IP Triangle'!F6>0,'IP Triangle'!G6/'IP Triangle'!F6,"") | G6: =IF('IP Triangle'!G6>0,'IP Triangle'!H6/'IP Triangle'!G6,"") | H6: =IF('IP Triangle'!H6>0,'IP Triangle'!I6/'IP Triangle'!H6,"") | I6: =IF('IP Triangle'!I6>0,'IP Triangle'!J6/'IP Triangle'!I6,"") | ... AO6: =IF('IP Triangle'!AO6>0,'IP Triangle'!AP6/'IP Triangle'!AO6,"")
A7: 2023-06 | B7: =IF('IP Triangle'!B7>0,'IP Triangle'!C7/'IP Triangle'!B7,"") | C7: =IF('IP Triangle'!C7>0,'IP Triangle'!D7/'IP Triangle'!C7,"") | D7: =IF('IP Triangle'!D7>0,'IP Triangle'!E7/'IP Triangle'!D7,"") | E7: =IF('IP Triangle'!E7>0,'IP Triangle'!F7/'IP Triangle'!E7,"") | F7: =IF('IP Triangle'!F7>0,'IP Triangle'!G7/'IP Triangle'!F7,"") | G7: =IF('IP Triangle'!G7>0,'IP Triangle'!H7/'IP Triangle'!G7,"") | H7: =IF('IP Triangle'!H7>0,'IP Triangle'!I7/'IP Triangle'!H7,"") | I7: =IF('IP Triangle'!I7>0,'IP Triangle'!J7/'IP Triangle'!I7,"") | ... AN7: =IF('IP Triangle'!AN7>0,'IP Triangle'!AO7/'IP Triangle'!AN7,"")
A8: 2023-07 | B8: =IF('IP Triangle'!B8>0,'IP Triangle'!C8/'IP Triangle'!B8,"") | C8: =IF('IP Triangle'!C8>0,'IP Triangle'!D8/'IP Triangle'!C8,"") | D8: =IF('IP Triangle'!D8>0,'IP Triangle'!E8/'IP Triangle'!D8,"") | E8: =IF('IP Triangle'!E8>0,'IP Triangle'!F8/'IP Triangle'!E8,"") | F8: =IF('IP Triangle'!F8>0,'IP Triangle'!G8/'IP Triangle'!F8,"") | G8: =IF('IP Triangle'!G8>0,'IP Triangle'!H8/'IP Triangle'!G8,"") | H8: =IF('IP Triangle'!H8>0,'IP Triangle'!I8/'IP Triangle'!H8,"") | I8: =IF('IP Triangle'!I8>0,'IP Triangle'!J8/'IP Triangle'!I8,"") | ... AM8: =IF('IP Triangle'!AM8>0,'IP Triangle'!AN8/'IP Triangle'!AM8,"")
A9: 2023-08 | B9: =IF('IP Triangle'!B9>0,'IP Triangle'!C9/'IP Triangle'!B9,"") | C9: =IF('IP Triangle'!C9>0,'IP Triangle'!D9/'IP Triangle'!C9,"") | D9: =IF('IP Triangle'!D9>0,'IP Triangle'!E9/'IP Triangle'!D9,"") | E9: =IF('IP Triangle'!E9>0,'IP Triangle'!F9/'IP Triangle'!E9,"") | F9: =IF('IP Triangle'!F9>0,'IP Triangle'!G9/'IP Triangle'!F9,"") | G9: =IF('IP Triangle'!G9>0,'IP Triangle'!H9/'IP Triangle'!G9,"") | H9: =IF('IP Triangle'!H9>0,'IP Triangle'!I9/'IP Triangle'!H9,"") | I9: =IF('IP Triangle'!I9>0,'IP Triangle'!J9/'IP Triangle'!I9,"") | ... AL9: =IF('IP Triangle'!AL9>0,'IP Triangle'!AM9/'IP Triangle'!AL9,"")
A10: 2023-09 | B10: =IF('IP Triangle'!B10>0,'IP Triangle'!C10/'IP Triangle'!B10,"") | C10: =IF('IP Triangle'!C10>0,'IP Triangle'!D10/'IP Triangle'!C10,"") | D10: =IF('IP Triangle'!D10>0,'IP Triangle'!E10/'IP Triangle'!D10,"") | E10: =IF('IP Triangle'!E10>0,'IP Triangle'!F10/'IP Triangle'!E10,"") | F10: =IF('IP Triangle'!F10>0,'IP Triangle'!G10/'IP Triangle'!F10,"") | G10: =IF('IP Triangle'!G10>0,'IP Triangle'!H10/'IP Triangle'!G10,"") | H10: =IF('IP Triangle'!H10>0,'IP Triangle'!I10/'IP Triangle'!H10,"") | I10: =IF('IP Triangle'!I10>0,'IP Triangle'!J10/'IP Triangle'!I10,"") | ... AK10: =IF('IP Triangle'!AK10>0,'IP Triangle'!AL10/'IP Triangle'!AK10,"")
A11: 2023-10 | B11: =IF('IP Triangle'!B11>0,'IP Triangle'!C11/'IP Triangle'!B11,"") | C11: =IF('IP Triangle'!C11>0,'IP Triangle'!D11/'IP Triangle'!C11,"") | D11: =IF('IP Triangle'!D11>0,'IP Triangle'!E11/'IP Triangle'!D11,"") | E11: =IF('IP Triangle'!E11>0,'IP Triangle'!F11/'IP Triangle'!E11,"") | F11: =IF('IP Triangle'!F11>0,'IP Triangle'!G11/'IP Triangle'!F11,"") | G11: =IF('IP Triangle'!G11>0,'IP Triangle'!H11/'IP Triangle'!G11,"") | H11: =IF('IP Triangle'!H11>0,'IP Triangle'!I11/'IP Triangle'!H11,"") | I11: =IF('IP Triangle'!I11>0,'IP Triangle'!J11/'IP Triangle'!I11,"") | ... AJ11: =IF('IP Triangle'!AJ11>0,'IP Triangle'!AK11/'IP Triangle'!AJ11,"")
A12: 2023-11 | B12: =IF('IP Triangle'!B12>0,'IP Triangle'!C12/'IP Triangle'!B12,"") | C12: =IF('IP Triangle'!C12>0,'IP Triangle'!D12/'IP Triangle'!C12,"") | D12: =IF('IP Triangle'!D12>0,'IP Triangle'!E12/'IP Triangle'!D12,"") | E12: =IF('IP Triangle'!E12>0,'IP Triangle'!F12/'IP Triangle'!E12,"") | F12: =IF('IP Triangle'!F12>0,'IP Triangle'!G12/'IP Triangle'!F12,"") | G12: =IF('IP Triangle'!G12>0,'IP Triangle'!H12/'IP Triangle'!G12,"") | H12: =IF('IP Triangle'!H12>0,'IP Triangle'!I12/'IP Triangle'!H12,"") | I12: =IF('IP Triangle'!I12>0,'IP Triangle'!J12/'IP Triangle'!I12,"") | ... AI12: =IF('IP Triangle'!AI12>0,'IP Triangle'!AJ12/'IP Triangle'!AI12,"")
A13: 2023-12 | B13: =IF('IP Triangle'!B13>0,'IP Triangle'!C13/'IP Triangle'!B13,"") | C13: =IF('IP Triangle'!C13>0,'IP Triangle'!D13/'IP Triangle'!C13,"") | D13: =IF('IP Triangle'!D13>0,'IP Triangle'!E13/'IP Triangle'!D13,"") | E13: =IF('IP Triangle'!E13>0,'IP Triangle'!F13/'IP Triangle'!E13,"") | F13: =IF('IP Triangle'!F13>0,'IP Triangle'!G13/'IP Triangle'!F13,"") | G13: =IF('IP Triangle'!G13>0,'IP Triangle'!H13/'IP Triangle'!G13,"") | H13: =IF('IP Triangle'!H13>0,'IP Triangle'!I13/'IP Triangle'!H13,"") | I13: =IF('IP Triangle'!I13>0,'IP Triangle'!J13/'IP Triangle'!I13,"") | ... AH13: =IF('IP Triangle'!AH13>0,'IP Triangle'!AI13/'IP Triangle'!AH13,"")
A14: 2024-01 | B14: =IF('IP Triangle'!B14>0,'IP Triangle'!C14/'IP Triangle'!B14,"") | C14: =IF('IP Triangle'!C14>0,'IP Triangle'!D14/'IP Triangle'!C14,"") | D14: =IF('IP Triangle'!D14>0,'IP Triangle'!E14/'IP Triangle'!D14,"") | E14: =IF('IP Triangle'!E14>0,'IP Triangle'!F14/'IP Triangle'!E14,"") | F14: =IF('IP Triangle'!F14>0,'IP Triangle'!G14/'IP Triangle'!F14,"") | G14: =IF('IP Triangle'!G14>0,'IP Triangle'!H14/'IP Triangle'!G14,"") | H14: =IF('IP Triangle'!H14>0,'IP Triangle'!I14/'IP Triangle'!H14,"") | I14: =IF('IP Triangle'!I14>0,'IP Triangle'!J14/'IP Triangle'!I14,"") | ... AG14: =IF('IP Triangle'!AG14>0,'IP Triangle'!AH14/'IP Triangle'!AG14,"")
A15: 2024-02 | B15: =IF('IP Triangle'!B15>0,'IP Triangle'!C15/'IP Triangle'!B15,"") | C15: =IF('IP Triangle'!C15>0,'IP Triangle'!D15/'IP Triangle'!C15,"") | D15: =IF('IP Triangle'!D15>0,'IP Triangle'!E15/'IP Triangle'!D15,"") | E15: =IF('IP Triangle'!E15>0,'IP Triangle'!F15/'IP Triangle'!E15,"") | F15: =IF('IP Triangle'!F15>0,'IP Triangle'!G15/'IP Triangle'!F15,"") | G15: =IF('IP Triangle'!G15>0,'IP Triangle'!H15/'IP Triangle'!G15,"") | H15: =IF('IP Triangle'!H15>0,'IP Triangle'!I15/'IP Triangle'!H15,"") | I15: =IF('IP Triangle'!I15>0,'IP Triangle'!J15/'IP Triangle'!I15,"") | ... AF15: =IF('IP Triangle'!AF15>0,'IP Triangle'!AG15/'IP Triangle'!AF15,"")
A16: 2024-03 | B16: =IF('IP Triangle'!B16>0,'IP Triangle'!C16/'IP Triangle'!B16,"") | C16: =IF('IP Triangle'!C16>0,'IP Triangle'!D16/'IP Triangle'!C16,"") | D16: =IF('IP Triangle'!D16>0,'IP Triangle'!E16/'IP Triangle'!D16,"") | E16: =IF('IP Triangle'!E16>0,'IP Triangle'!F16/'IP Triangle'!E16,"") | F16: =IF('IP Triangle'!F16>0,'IP Triangle'!G16/'IP Triangle'!F16,"") | G16: =IF('IP Triangle'!G16>0,'IP Triangle'!H16/'IP Triangle'!G16,"") | H16: =IF('IP Triangle'!H16>0,'IP Triangle'!I16/'IP Triangle'!H16,"") | I16: =IF('IP Triangle'!I16>0,'IP Triangle'!J16/'IP Triangle'!I16,"") | ... AE16: =IF('IP Triangle'!AE16>0,'IP Triangle'!AF16/'IP Triangle'!AE16,"")
A17: 2024-04 | B17: =IF('IP Triangle'!B17>0,'IP Triangle'!C17/'IP Triangle'!B17,"") | C17: =IF('IP Triangle'!C17>0,'IP Triangle'!D17/'IP Triangle'!C17,"") | D17: =IF('IP Triangle'!D17>0,'IP Triangle'!E17/'IP Triangle'!D17,"") | E17: =IF('IP Triangle'!E17>0,'IP Triangle'!F17/'IP Triangle'!E17,"") | F17: =IF('IP Triangle'!F17>0,'IP Triangle'!G17/'IP Triangle'!F17,"") | G17: =IF('IP Triangle'!G17>0,'IP Triangle'!H17/'IP Triangle'!G17,"") | H17: =IF('IP Triangle'!H17>0,'IP Triangle'!I17/'IP Triangle'!H17,"") | I17: =IF('IP Triangle'!I17>0,'IP Triangle'!J17/'IP Triangle'!I17,"") | ... AD17: =IF('IP Triangle'!AD17>0,'IP Triangle'!AE17/'IP Triangle'!AD17,"")
A18: 2024-05 | B18: =IF('IP Triangle'!B18>0,'IP Triangle'!C18/'IP Triangle'!B18,"") | C18: =IF('IP Triangle'!C18>0,'IP Triangle'!D18/'IP Triangle'!C18,"") | D18: =IF('IP Triangle'!D18>0,'IP Triangle'!E18/'IP Triangle'!D18,"") | E18: =IF('IP Triangle'!E18>0,'IP Triangle'!F18/'IP Triangle'!E18,"") | F18: =IF('IP Triangle'!F18>0,'IP Triangle'!G18/'IP Triangle'!F18,"") | G18: =IF('IP Triangle'!G18>0,'IP Triangle'!H18/'IP Triangle'!G18,"") | H18: =IF('IP Triangle'!H18>0,'IP Triangle'!I18/'IP Triangle'!H18,"") | I18: =IF('IP Triangle'!I18>0,'IP Triangle'!J18/'IP Triangle'!I18,"") | ... AC18: =IF('IP Triangle'!AC18>0,'IP Triangle'!AD18/'IP Triangle'!AC18,"")
A19: 2024-06 | B19: =IF('IP Triangle'!B19>0,'IP Triangle'!C19/'IP Triangle'!B19,"") | C19: =IF('IP Triangle'!C19>0,'IP Triangle'!D19/'IP Triangle'!C19,"") | D19: =IF('IP Triangle'!D19>0,'IP Triangle'!E19/'IP Triangle'!D19,"") | E19: =IF('IP Triangle'!E19>0,'IP Triangle'!F19/'IP Triangle'!E19,"") | F19: =IF('IP Triangle'!F19>0,'IP Triangle'!G19/'IP Triangle'!F19,"") | G19: =IF('IP Triangle'!G19>0,'IP Triangle'!H19/'IP Triangle'!G19,"") | H19: =IF('IP Triangle'!H19>0,'IP Triangle'!I19/'IP Triangle'!H19,"") | I19: =IF('IP Triangle'!I19>0,'IP Triangle'!J19/'IP Triangle'!I19,"") | ... AB19: =IF('IP Triangle'!AB19>0,'IP Triangle'!AC19/'IP Triangle'!AB19,"")
A20: 2024-07 | B20: =IF('IP Triangle'!B20>0,'IP Triangle'!C20/'IP Triangle'!B20,"") | C20: =IF('IP Triangle'!C20>0,'IP Triangle'!D20/'IP Triangle'!C20,"") | D20: =IF('IP Triangle'!D20>0,'IP Triangle'!E20/'IP Triangle'!D20,"") | E20: =IF('IP Triangle'!E20>0,'IP Triangle'!F20/'IP Triangle'!E20,"") | F20: =IF('IP Triangle'!F20>0,'IP Triangle'!G20/'IP Triangle'!F20,"") | G20: =IF('IP Triangle'!G20>0,'IP Triangle'!H20/'IP Triangle'!G20,"") | H20: =IF('IP Triangle'!H20>0,'IP Triangle'!I20/'IP Triangle'!H20,"") | I20: =IF('IP Triangle'!I20>0,'IP Triangle'!J20/'IP Triangle'!I20,"") | ... AA20: =IF('IP Triangle'!AA20>0,'IP Triangle'!AB20/'IP Triangle'!AA20,"")
A21: 2024-08 | B21: =IF('IP Triangle'!B21>0,'IP Triangle'!C21/'IP Triangle'!B21,"") | C21: =IF('IP Triangle'!C21>0,'IP Triangle'!D21/'IP Triangle'!C21,"") | D21: =IF('IP Triangle'!D21>0,'IP Triangle'!E21/'IP Triangle'!D21,"") | E21: =IF('IP Triangle'!E21>0,'IP Triangle'!F21/'IP Triangle'!E21,"") | F21: =IF('IP Triangle'!F21>0,'IP Triangle'!G21/'IP Triangle'!F21,"") | G21: =IF('IP Triangle'!G21>0,'IP Triangle'!H21/'IP Triangle'!G21,"") | H21: =IF('IP Triangle'!H21>0,'IP Triangle'!I21/'IP Triangle'!H21,"") | I21: =IF('IP Triangle'!I21>0,'IP Triangle'!J21/'IP Triangle'!I21,"") | ... Z21: =IF('IP Triangle'!Z21>0,'IP Triangle'!AA21/'IP Triangle'!Z21,"")
A22: 2024-09 | B22: =IF('IP Triangle'!B22>0,'IP Triangle'!C22/'IP Triangle'!B22,"") | C22: =IF('IP Triangle'!C22>0,'IP Triangle'!D22/'IP Triangle'!C22,"") | D22: =IF('IP Triangle'!D22>0,'IP Triangle'!E22/'IP Triangle'!D22,"") | E22: =IF('IP Triangle'!E22>0,'IP Triangle'!F22/'IP Triangle'!E22,"") | F22: =IF('IP Triangle'!F22>0,'IP Triangle'!G22/'IP Triangle'!F22,"") | G22: =IF('IP Triangle'!G22>0,'IP Triangle'!H22/'IP Triangle'!G22,"") | H22: =IF('IP Triangle'!H22>0,'IP Triangle'!I22/'IP Triangle'!H22,"") | I22: =IF('IP Triangle'!I22>0,'IP Triangle'!J22/'IP Triangle'!I22,"") | ... Y22: =IF('IP Triangle'!Y22>0,'IP Triangle'!Z22/'IP Triangle'!Y22,"")
A23: 2024-10 | B23: =IF('IP Triangle'!B23>0,'IP Triangle'!C23/'IP Triangle'!B23,"") | C23: =IF('IP Triangle'!C23>0,'IP Triangle'!D23/'IP Triangle'!C23,"") | D23: =IF('IP Triangle'!D23>0,'IP Triangle'!E23/'IP Triangle'!D23,"") | E23: =IF('IP Triangle'!E23>0,'IP Triangle'!F23/'IP Triangle'!E23,"") | F23: =IF('IP Triangle'!F23>0,'IP Triangle'!G23/'IP Triangle'!F23,"") | G23: =IF('IP Triangle'!G23>0,'IP Triangle'!H23/'IP Triangle'!G23,"") | H23: =IF('IP Triangle'!H23>0,'IP Triangle'!I23/'IP Triangle'!H23,"") | I23: =IF('IP Triangle'!I23>0,'IP Triangle'!J23/'IP Triangle'!I23,"") | ... X23: =IF('IP Triangle'!X23>0,'IP Triangle'!Y23/'IP Triangle'!X23,"")
A24: 2024-11 | B24: =IF('IP Triangle'!B24>0,'IP Triangle'!C24/'IP Triangle'!B24,"") | C24: =IF('IP Triangle'!C24>0,'IP Triangle'!D24/'IP Triangle'!C24,"") | D24: =IF('IP Triangle'!D24>0,'IP Triangle'!E24/'IP Triangle'!D24,"") | E24: =IF('IP Triangle'!E24>0,'IP Triangle'!F24/'IP Triangle'!E24,"") | F24: =IF('IP Triangle'!F24>0,'IP Triangle'!G24/'IP Triangle'!F24,"") | G24: =IF('IP Triangle'!G24>0,'IP Triangle'!H24/'IP Triangle'!G24,"") | H24: =IF('IP Triangle'!H24>0,'IP Triangle'!I24/'IP Triangle'!H24,"") | I24: =IF('IP Triangle'!I24>0,'IP Triangle'!J24/'IP Triangle'!I24,"") | ... W24: =IF('IP Triangle'!W24>0,'IP Triangle'!X24/'IP Triangle'!W24,"")
A25: 2024-12 | B25: =IF('IP Triangle'!B25>0,'IP Triangle'!C25/'IP Triangle'!B25,"") | C25: =IF('IP Triangle'!C25>0,'IP Triangle'!D25/'IP Triangle'!C25,"") | D25: =IF('IP Triangle'!D25>0,'IP Triangle'!E25/'IP Triangle'!D25,"") | E25: =IF('IP Triangle'!E25>0,'IP Triangle'!F25/'IP Triangle'!E25,"") | F25: =IF('IP Triangle'!F25>0,'IP Triangle'!G25/'IP Triangle'!F25,"") | G25: =IF('IP Triangle'!G25>0,'IP Triangle'!H25/'IP Triangle'!G25,"") | H25: =IF('IP Triangle'!H25>0,'IP Triangle'!I25/'IP Triangle'!H25,"") | I25: =IF('IP Triangle'!I25>0,'IP Triangle'!J25/'IP Triangle'!I25,"") | ... V25: =IF('IP Triangle'!V25>0,'IP Triangle'!W25/'IP Triangle'!V25,"")
A26: 2025-01 | B26: =IF('IP Triangle'!B26>0,'IP Triangle'!C26/'IP Triangle'!B26,"") | C26: =IF('IP Triangle'!C26>0,'IP Triangle'!D26/'IP Triangle'!C26,"") | D26: =IF('IP Triangle'!D26>0,'IP Triangle'!E26/'IP Triangle'!D26,"") | E26: =IF('IP Triangle'!E26>0,'IP Triangle'!F26/'IP Triangle'!E26,"") | F26: =IF('IP Triangle'!F26>0,'IP Triangle'!G26/'IP Triangle'!F26,"") | G26: =IF('IP Triangle'!G26>0,'IP Triangle'!H26/'IP Triangle'!G26,"") | H26: =IF('IP Triangle'!H26>0,'IP Triangle'!I26/'IP Triangle'!H26,"") | I26: =IF('IP Triangle'!I26>0,'IP Triangle'!J26/'IP Triangle'!I26,"") | ... U26: =IF('IP Triangle'!U26>0,'IP Triangle'!V26/'IP Triangle'!U26,"")
A27: 2025-02 | B27: =IF('IP Triangle'!B27>0,'IP Triangle'!C27/'IP Triangle'!B27,"") | C27: =IF('IP Triangle'!C27>0,'IP Triangle'!D27/'IP Triangle'!C27,"") | D27: =IF('IP Triangle'!D27>0,'IP Triangle'!E27/'IP Triangle'!D27,"") | E27: =IF('IP Triangle'!E27>0,'IP Triangle'!F27/'IP Triangle'!E27,"") | F27: =IF('IP Triangle'!F27>0,'IP Triangle'!G27/'IP Triangle'!F27,"") | G27: =IF('IP Triangle'!G27>0,'IP Triangle'!H27/'IP Triangle'!G27,"") | H27: =IF('IP Triangle'!H27>0,'IP Triangle'!I27/'IP Triangle'!H27,"") | I27: =IF('IP Triangle'!I27>0,'IP Triangle'!J27/'IP Triangle'!I27,"") | ... T27: =IF('IP Triangle'!T27>0,'IP Triangle'!U27/'IP Triangle'!T27,"")
A28: 2025-03 | B28: =IF('IP Triangle'!B28>0,'IP Triangle'!C28/'IP Triangle'!B28,"") | C28: =IF('IP Triangle'!C28>0,'IP Triangle'!D28/'IP Triangle'!C28,"") | D28: =IF('IP Triangle'!D28>0,'IP Triangle'!E28/'IP Triangle'!D28,"") | E28: =IF('IP Triangle'!E28>0,'IP Triangle'!F28/'IP Triangle'!E28,"") | F28: =IF('IP Triangle'!F28>0,'IP Triangle'!G28/'IP Triangle'!F28,"") | G28: =IF('IP Triangle'!G28>0,'IP Triangle'!H28/'IP Triangle'!G28,"") | H28: =IF('IP Triangle'!H28>0,'IP Triangle'!I28/'IP Triangle'!H28,"") | I28: =IF('IP Triangle'!I28>0,'IP Triangle'!J28/'IP Triangle'!I28,"") | ... S28: =IF('IP Triangle'!S28>0,'IP Triangle'!T28/'IP Triangle'!S28,"")
A29: 2025-04 | B29: =IF('IP Triangle'!B29>0,'IP Triangle'!C29/'IP Triangle'!B29,"") | C29: =IF('IP Triangle'!C29>0,'IP Triangle'!D29/'IP Triangle'!C29,"") | D29: =IF('IP Triangle'!D29>0,'IP Triangle'!E29/'IP Triangle'!D29,"") | E29: =IF('IP Triangle'!E29>0,'IP Triangle'!F29/'IP Triangle'!E29,"") | F29: =IF('IP Triangle'!F29>0,'IP Triangle'!G29/'IP Triangle'!F29,"") | G29: =IF('IP Triangle'!G29>0,'IP Triangle'!H29/'IP Triangle'!G29,"") | H29: =IF('IP Triangle'!H29>0,'IP Triangle'!I29/'IP Triangle'!H29,"") | I29: =IF('IP Triangle'!I29>0,'IP Triangle'!J29/'IP Triangle'!I29,"") | ... R29: =IF('IP Triangle'!R29>0,'IP Triangle'!S29/'IP Triangle'!R29,"")
A30: 2025-05 | B30: =IF('IP Triangle'!B30>0,'IP Triangle'!C30/'IP Triangle'!B30,"") | C30: =IF('IP Triangle'!C30>0,'IP Triangle'!D30/'IP Triangle'!C30,"") | D30: =IF('IP Triangle'!D30>0,'IP Triangle'!E30/'IP Triangle'!D30,"") | E30: =IF('IP Triangle'!E30>0,'IP Triangle'!F30/'IP Triangle'!E30,"") | F30: =IF('IP Triangle'!F30>0,'IP Triangle'!G30/'IP Triangle'!F30,"") | G30: =IF('IP Triangle'!G30>0,'IP Triangle'!H30/'IP Triangle'!G30,"") | H30: =IF('IP Triangle'!H30>0,'IP Triangle'!I30/'IP Triangle'!H30,"") | I30: =IF('IP Triangle'!I30>0,'IP Triangle'!J30/'IP Triangle'!I30,"") | ... Q30: =IF('IP Triangle'!Q30>0,'IP Triangle'!R30/'IP Triangle'!Q30,"")
A31: 2025-06 | B31: =IF('IP Triangle'!B31>0,'IP Triangle'!C31/'IP Triangle'!B31,"") | C31: =IF('IP Triangle'!C31>0,'IP Triangle'!D31/'IP Triangle'!C31,"") | D31: =IF('IP Triangle'!D31>0,'IP Triangle'!E31/'IP Triangle'!D31,"") | E31: =IF('IP Triangle'!E31>0,'IP Triangle'!F31/'IP Triangle'!E31,"") | F31: =IF('IP Triangle'!F31>0,'IP Triangle'!G31/'IP Triangle'!F31,"") | G31: =IF('IP Triangle'!G31>0,'IP Triangle'!H31/'IP Triangle'!G31,"") | H31: =IF('IP Triangle'!H31>0,'IP Triangle'!I31/'IP Triangle'!H31,"") | I31: =IF('IP Triangle'!I31>0,'IP Triangle'!J31/'IP Triangle'!I31,"") | ... P31: =IF('IP Triangle'!P31>0,'IP Triangle'!Q31/'IP Triangle'!P31,"")
A32: 2025-07 | B32: =IF('IP Triangle'!B32>0,'IP Triangle'!C32/'IP Triangle'!B32,"") | C32: =IF('IP Triangle'!C32>0,'IP Triangle'!D32/'IP Triangle'!C32,"") | D32: =IF('IP Triangle'!D32>0,'IP Triangle'!E32/'IP Triangle'!D32,"") | E32: =IF('IP Triangle'!E32>0,'IP Triangle'!F32/'IP Triangle'!E32,"") | F32: =IF('IP Triangle'!F32>0,'IP Triangle'!G32/'IP Triangle'!F32,"") | G32: =IF('IP Triangle'!G32>0,'IP Triangle'!H32/'IP Triangle'!G32,"") | H32: =IF('IP Triangle'!H32>0,'IP Triangle'!I32/'IP Triangle'!H32,"") | I32: =IF('IP Triangle'!I32>0,'IP Triangle'!J32/'IP Triangle'!I32,"") | ... O32: =IF('IP Triangle'!O32>0,'IP Triangle'!P32/'IP Triangle'!O32,"")
A33: 2025-08 | B33: =IF('IP Triangle'!B33>0,'IP Triangle'!C33/'IP Triangle'!B33,"") | C33: =IF('IP Triangle'!C33>0,'IP Triangle'!D33/'IP Triangle'!C33,"") | D33: =IF('IP Triangle'!D33>0,'IP Triangle'!E33/'IP Triangle'!D33,"") | E33: =IF('IP Triangle'!E33>0,'IP Triangle'!F33/'IP Triangle'!E33,"") | F33: =IF('IP Triangle'!F33>0,'IP Triangle'!G33/'IP Triangle'!F33,"") | G33: =IF('IP Triangle'!G33>0,'IP Triangle'!H33/'IP Triangle'!G33,"") | H33: =IF('IP Triangle'!H33>0,'IP Triangle'!I33/'IP Triangle'!H33,"") | I33: =IF('IP Triangle'!I33>0,'IP Triangle'!J33/'IP Triangle'!I33,"") | ... N33: =IF('IP Triangle'!N33>0,'IP Triangle'!O33/'IP Triangle'!N33,"")
A34: 2025-09 | B34: =IF('IP Triangle'!B34>0,'IP Triangle'!C34/'IP Triangle'!B34,"") | C34: =IF('IP Triangle'!C34>0,'IP Triangle'!D34/'IP Triangle'!C34,"") | D34: =IF('IP Triangle'!D34>0,'IP Triangle'!E34/'IP Triangle'!D34,"") | E34: =IF('IP Triangle'!E34>0,'IP Triangle'!F34/'IP Triangle'!E34,"") | F34: =IF('IP Triangle'!F34>0,'IP Triangle'!G34/'IP Triangle'!F34,"") | G34: =IF('IP Triangle'!G34>0,'IP Triangle'!H34/'IP Triangle'!G34,"") | H34: =IF('IP Triangle'!H34>0,'IP Triangle'!I34/'IP Triangle'!H34,"") | I34: =IF('IP Triangle'!I34>0,'IP Triangle'!J34/'IP Triangle'!I34,"") | ... M34: =IF('IP Triangle'!M34>0,'IP Triangle'!N34/'IP Triangle'!M34,"")
A35: 2025-10 | B35: =IF('IP Triangle'!B35>0,'IP Triangle'!C35/'IP Triangle'!B35,"") | C35: =IF('IP Triangle'!C35>0,'IP Triangle'!D35/'IP Triangle'!C35,"") | D35: =IF('IP Triangle'!D35>0,'IP Triangle'!E35/'IP Triangle'!D35,"") | E35: =IF('IP Triangle'!E35>0,'IP Triangle'!F35/'IP Triangle'!E35,"") | F35: =IF('IP Triangle'!F35>0,'IP Triangle'!G35/'IP Triangle'!F35,"") | G35: =IF('IP Triangle'!G35>0,'IP Triangle'!H35/'IP Triangle'!G35,"") | H35: =IF('IP Triangle'!H35>0,'IP Triangle'!I35/'IP Triangle'!H35,"") | I35: =IF('IP Triangle'!I35>0,'IP Triangle'!J35/'IP Triangle'!I35,"") | ... L35: =IF('IP Triangle'!L35>0,'IP Triangle'!M35/'IP Triangle'!L35,"")
A36: 2025-11 | B36: =IF('IP Triangle'!B36>0,'IP Triangle'!C36/'IP Triangle'!B36,"") | C36: =IF('IP Triangle'!C36>0,'IP Triangle'!D36/'IP Triangle'!C36,"") | D36: =IF('IP Triangle'!D36>0,'IP Triangle'!E36/'IP Triangle'!D36,"") | E36: =IF('IP Triangle'!E36>0,'IP Triangle'!F36/'IP Triangle'!E36,"") | F36: =IF('IP Triangle'!F36>0,'IP Triangle'!G36/'IP Triangle'!F36,"") | G36: =IF('IP Triangle'!G36>0,'IP Triangle'!H36/'IP Triangle'!G36,"") | H36: =IF('IP Triangle'!H36>0,'IP Triangle'!I36/'IP Triangle'!H36,"") | I36: =IF('IP Triangle'!I36>0,'IP Triangle'!J36/'IP Triangle'!I36,"") | ... K36: =IF('IP Triangle'!K36>0,'IP Triangle'!L36/'IP Triangle'!K36,"")
A37: 2025-12 | B37: =IF('IP Triangle'!B37>0,'IP Triangle'!C37/'IP Triangle'!B37,"") | C37: =IF('IP Triangle'!C37>0,'IP Triangle'!D37/'IP Triangle'!C37,"") | D37: =IF('IP Triangle'!D37>0,'IP Triangle'!E37/'IP Triangle'!D37,"") | E37: =IF('IP Triangle'!E37>0,'IP Triangle'!F37/'IP Triangle'!E37,"") | F37: =IF('IP Triangle'!F37>0,'IP Triangle'!G37/'IP Triangle'!F37,"") | G37: =IF('IP Triangle'!G37>0,'IP Triangle'!H37/'IP Triangle'!G37,"") | H37: =IF('IP Triangle'!H37>0,'IP Triangle'!I37/'IP Triangle'!H37,"") | I37: =IF('IP Triangle'!I37>0,'IP Triangle'!J37/'IP Triangle'!I37,"") | J37: =IF('IP Triangle'!J37>0,'IP Triangle'!K37/'IP Triangle'!J37,"")
A38: 2026-01 | B38: =IF('IP Triangle'!B38>0,'IP Triangle'!C38/'IP Triangle'!B38,"") | C38: =IF('IP Triangle'!C38>0,'IP Triangle'!D38/'IP Triangle'!C38,"") | D38: =IF('IP Triangle'!D38>0,'IP Triangle'!E38/'IP Triangle'!D38,"") | E38: =IF('IP Triangle'!E38>0,'IP Triangle'!F38/'IP Triangle'!E38,"") | F38: =IF('IP Triangle'!F38>0,'IP Triangle'!G38/'IP Triangle'!F38,"") | G38: =IF('IP Triangle'!G38>0,'IP Triangle'!H38/'IP Triangle'!G38,"") | H38: =IF('IP Triangle'!H38>0,'IP Triangle'!I38/'IP Triangle'!H38,"") | I38: =IF('IP Triangle'!I38>0,'IP Triangle'!J38/'IP Triangle'!I38,"")
A39: 2026-02 | B39: =IF('IP Triangle'!B39>0,'IP Triangle'!C39/'IP Triangle'!B39,"") | C39: =IF('IP Triangle'!C39>0,'IP Triangle'!D39/'IP Triangle'!C39,"") | D39: =IF('IP Triangle'!D39>0,'IP Triangle'!E39/'IP Triangle'!D39,"") | E39: =IF('IP Triangle'!E39>0,'IP Triangle'!F39/'IP Triangle'!E39,"") | F39: =IF('IP Triangle'!F39>0,'IP Triangle'!G39/'IP Triangle'!F39,"") | G39: =IF('IP Triangle'!G39>0,'IP Triangle'!H39/'IP Triangle'!G39,"") | H39: =IF('IP Triangle'!H39>0,'IP Triangle'!I39/'IP Triangle'!H39,"")
A40: 2026-03 | B40: =IF('IP Triangle'!B40>0,'IP Triangle'!C40/'IP Triangle'!B40,"") | C40: =IF('IP Triangle'!C40>0,'IP Triangle'!D40/'IP Triangle'!C40,"") | D40: =IF('IP Triangle'!D40>0,'IP Triangle'!E40/'IP Triangle'!D40,"") | E40: =IF('IP Triangle'!E40>0,'IP Triangle'!F40/'IP Triangle'!E40,"") | F40: =IF('IP Triangle'!F40>0,'IP Triangle'!G40/'IP Triangle'!F40,"") | G40: =IF('IP Triangle'!G40>0,'IP Triangle'!H40/'IP Triangle'!G40,"")
A41: 2026-04 | B41: =IF('IP Triangle'!B41>0,'IP Triangle'!C41/'IP Triangle'!B41,"") | C41: =IF('IP Triangle'!C41>0,'IP Triangle'!D41/'IP Triangle'!C41,"") | D41: =IF('IP Triangle'!D41>0,'IP Triangle'!E41/'IP Triangle'!D41,"") | E41: =IF('IP Triangle'!E41>0,'IP Triangle'!F41/'IP Triangle'!E41,"") | F41: =IF('IP Triangle'!F41>0,'IP Triangle'!G41/'IP Triangle'!F41,"")
A42: 2026-05 | B42: =IF('IP Triangle'!B42>0,'IP Triangle'!C42/'IP Triangle'!B42,"") | C42: =IF('IP Triangle'!C42>0,'IP Triangle'!D42/'IP Triangle'!C42,"") | D42: =IF('IP Triangle'!D42>0,'IP Triangle'!E42/'IP Triangle'!D42,"") | E42: =IF('IP Triangle'!E42>0,'IP Triangle'!F42/'IP Triangle'!E42,"")
A43: 2026-06 | B43: =IF('IP Triangle'!B43>0,'IP Triangle'!C43/'IP Triangle'!B43,"") | C43: =IF('IP Triangle'!C43>0,'IP Triangle'!D43/'IP Triangle'!C43,"") | D43: =IF('IP Triangle'!D43>0,'IP Triangle'!E43/'IP Triangle'!D43,"")
A44: 2026-07 | B44: =IF('IP Triangle'!B44>0,'IP Triangle'!C44/'IP Triangle'!B44,"") | C44: =IF('IP Triangle'!C44>0,'IP Triangle'!D44/'IP Triangle'!C44,"")
A45: 2026-08 | B45: =IF('IP Triangle'!B45>0,'IP Triangle'!C45/'IP Triangle'!B45,"")
A46: 2026-09

Sheet IP Factors
A1: Lag | B1: 6-mo avg ex hi/lo | C1: Override | D1: Selected link ratio | E1: Completion factor | F1: Months used
A2: 0 | B2: =(SUM('IP Ratios'!B38,'IP Ratios'!B39,'IP Ratios'!B40,'IP Ratios'!B41,'IP Ratios'!B44,'IP Ratios'!B45)-MAX('IP Ratios'!B38,'IP Ratios'!B39,'IP Ratios'!B40,'IP Ratios'!B41,'IP Ratios'!B44,'IP Ratios'!B45)-MIN('IP Ratios'!B38,'IP Ratios'!B39,'IP Ratios'!B40,'IP Ratios'!B41,'IP Ratios'!B44,'IP Ratios'!B45))/(COUNT('IP Ratios'!B38,'IP Ratios'!B39,'IP Ratios'!B40,'IP Ratios'!B41,'IP Ratios'!B44,'IP Ratios'!B45)-2) | D2: =IF(ISNUMBER(C2),C2,B2) | E2: =1/PRODUCT(D2:D46) | F2: 2026-01, 2026-02, 2026-03, 2026-04, 2026-07, 2026-08
A3: 1 | B3: =(SUM('IP Ratios'!C37,'IP Ratios'!C38,'IP Ratios'!C39,'IP Ratios'!C40,'IP Ratios'!C43,'IP Ratios'!C44)-MAX('IP Ratios'!C37,'IP Ratios'!C38,'IP Ratios'!C39,'IP Ratios'!C40,'IP Ratios'!C43,'IP Ratios'!C44)-MIN('IP Ratios'!C37,'IP Ratios'!C38,'IP Ratios'!C39,'IP Ratios'!C40,'IP Ratios'!C43,'IP Ratios'!C44))/(COUNT('IP Ratios'!C37,'IP Ratios'!C38,'IP Ratios'!C39,'IP Ratios'!C40,'IP Ratios'!C43,'IP Ratios'!C44)-2) | D3: =IF(ISNUMBER(C3),C3,B3) | E3: =1/PRODUCT(D3:D46) | F3: 2025-12, 2026-01, 2026-02, 2026-03, 2026-06, 2026-07
A4: 2 | B4: =(SUM('IP Ratios'!D36,'IP Ratios'!D37,'IP Ratios'!D38,'IP Ratios'!D39,'IP Ratios'!D42,'IP Ratios'!D43)-MAX('IP Ratios'!D36,'IP Ratios'!D37,'IP Ratios'!D38,'IP Ratios'!D39,'IP Ratios'!D42,'IP Ratios'!D43)-MIN('IP Ratios'!D36,'IP Ratios'!D37,'IP Ratios'!D38,'IP Ratios'!D39,'IP Ratios'!D42,'IP Ratios'!D43))/(COUNT('IP Ratios'!D36,'IP Ratios'!D37,'IP Ratios'!D38,'IP Ratios'!D39,'IP Ratios'!D42,'IP Ratios'!D43)-2) | D4: =IF(ISNUMBER(C4),C4,B4) | E4: =1/PRODUCT(D4:D46) | F4: 2025-11, 2025-12, 2026-01, 2026-02, 2026-05, 2026-06
A5: 3 | B5: =(SUM('IP Ratios'!E35,'IP Ratios'!E36,'IP Ratios'!E37,'IP Ratios'!E38,'IP Ratios'!E41,'IP Ratios'!E42)-MAX('IP Ratios'!E35,'IP Ratios'!E36,'IP Ratios'!E37,'IP Ratios'!E38,'IP Ratios'!E41,'IP Ratios'!E42)-MIN('IP Ratios'!E35,'IP Ratios'!E36,'IP Ratios'!E37,'IP Ratios'!E38,'IP Ratios'!E41,'IP Ratios'!E42))/(COUNT('IP Ratios'!E35,'IP Ratios'!E36,'IP Ratios'!E37,'IP Ratios'!E38,'IP Ratios'!E41,'IP Ratios'!E42)-2) | D5: =IF(ISNUMBER(C5),C5,B5) | E5: =1/PRODUCT(D5:D46) | F5: 2025-10, 2025-11, 2025-12, 2026-01, 2026-04, 2026-05
A6: 4 | B6: =(SUM('IP Ratios'!F34,'IP Ratios'!F35,'IP Ratios'!F36,'IP Ratios'!F37,'IP Ratios'!F40,'IP Ratios'!F41)-MAX('IP Ratios'!F34,'IP Ratios'!F35,'IP Ratios'!F36,'IP Ratios'!F37,'IP Ratios'!F40,'IP Ratios'!F41)-MIN('IP Ratios'!F34,'IP Ratios'!F35,'IP Ratios'!F36,'IP Ratios'!F37,'IP Ratios'!F40,'IP Ratios'!F41))/(COUNT('IP Ratios'!F34,'IP Ratios'!F35,'IP Ratios'!F36,'IP Ratios'!F37,'IP Ratios'!F40,'IP Ratios'!F41)-2) | D6: =IF(ISNUMBER(C6),C6,B6) | E6: =1/PRODUCT(D6:D46) | F6: 2025-09, 2025-10, 2025-11, 2025-12, 2026-03, 2026-04
A7: 5 | B7: =(SUM('IP Ratios'!G33,'IP Ratios'!G34,'IP Ratios'!G35,'IP Ratios'!G36,'IP Ratios'!G39,'IP Ratios'!G40)-MAX('IP Ratios'!G33,'IP Ratios'!G34,'IP Ratios'!G35,'IP Ratios'!G36,'IP Ratios'!G39,'IP Ratios'!G40)-MIN('IP Ratios'!G33,'IP Ratios'!G34,'IP Ratios'!G35,'IP Ratios'!G36,'IP Ratios'!G39,'IP Ratios'!G40))/(COUNT('IP Ratios'!G33,'IP Ratios'!G34,'IP Ratios'!G35,'IP Ratios'!G36,'IP Ratios'!G39,'IP Ratios'!G40)-2) | D7: =IF(ISNUMBER(C7),C7,B7) | E7: =1/PRODUCT(D7:D46) | F7: 2025-08, 2025-09, 2025-10, 2025-11, 2026-02, 2026-03
A8: 6 | B8: =(SUM('IP Ratios'!H32,'IP Ratios'!H33,'IP Ratios'!H34,'IP Ratios'!H35,'IP Ratios'!H38,'IP Ratios'!H39)-MAX('IP Ratios'!H32,'IP Ratios'!H33,'IP Ratios'!H34,'IP Ratios'!H35,'IP Ratios'!H38,'IP Ratios'!H39)-MIN('IP Ratios'!H32,'IP Ratios'!H33,'IP Ratios'!H34,'IP Ratios'!H35,'IP Ratios'!H38,'IP Ratios'!H39))/(COUNT('IP Ratios'!H32,'IP Ratios'!H33,'IP Ratios'!H34,'IP Ratios'!H35,'IP Ratios'!H38,'IP Ratios'!H39)-2) | D8: =IF(ISNUMBER(C8),C8,B8) | E8: =1/PRODUCT(D8:D46) | F8: 2025-07, 2025-08, 2025-09, 2025-10, 2026-01, 2026-02
A9: 7 | B9: =(SUM('IP Ratios'!I31,'IP Ratios'!I32,'IP Ratios'!I33,'IP Ratios'!I34,'IP Ratios'!I37,'IP Ratios'!I38)-MAX('IP Ratios'!I31,'IP Ratios'!I32,'IP Ratios'!I33,'IP Ratios'!I34,'IP Ratios'!I37,'IP Ratios'!I38)-MIN('IP Ratios'!I31,'IP Ratios'!I32,'IP Ratios'!I33,'IP Ratios'!I34,'IP Ratios'!I37,'IP Ratios'!I38))/(COUNT('IP Ratios'!I31,'IP Ratios'!I32,'IP Ratios'!I33,'IP Ratios'!I34,'IP Ratios'!I37,'IP Ratios'!I38)-2) | D9: =IF(ISNUMBER(C9),C9,B9) | E9: =1/PRODUCT(D9:D46) | F9: 2025-06, 2025-07, 2025-08, 2025-09, 2025-12, 2026-01
A10: 8 | B10: =(SUM('IP Ratios'!J30,'IP Ratios'!J31,'IP Ratios'!J32,'IP Ratios'!J33,'IP Ratios'!J36,'IP Ratios'!J37)-MAX('IP Ratios'!J30,'IP Ratios'!J31,'IP Ratios'!J32,'IP Ratios'!J33,'IP Ratios'!J36,'IP Ratios'!J37)-MIN('IP Ratios'!J30,'IP Ratios'!J31,'IP Ratios'!J32,'IP Ratios'!J33,'IP Ratios'!J36,'IP Ratios'!J37))/(COUNT('IP Ratios'!J30,'IP Ratios'!J31,'IP Ratios'!J32,'IP Ratios'!J33,'IP Ratios'!J36,'IP Ratios'!J37)-2) | D10: =IF(ISNUMBER(C10),C10,B10) | E10: =1/PRODUCT(D10:D46) | F10: 2025-05, 2025-06, 2025-07, 2025-08, 2025-11, 2025-12
A11: 9 | B11: =(SUM('IP Ratios'!K29,'IP Ratios'!K30,'IP Ratios'!K31,'IP Ratios'!K32,'IP Ratios'!K35,'IP Ratios'!K36)-MAX('IP Ratios'!K29,'IP Ratios'!K30,'IP Ratios'!K31,'IP Ratios'!K32,'IP Ratios'!K35,'IP Ratios'!K36)-MIN('IP Ratios'!K29,'IP Ratios'!K30,'IP Ratios'!K31,'IP Ratios'!K32,'IP Ratios'!K35,'IP Ratios'!K36))/(COUNT('IP Ratios'!K29,'IP Ratios'!K30,'IP Ratios'!K31,'IP Ratios'!K32,'IP Ratios'!K35,'IP Ratios'!K36)-2) | D11: =IF(ISNUMBER(C11),C11,B11) | E11: =1/PRODUCT(D11:D46) | F11: 2025-04, 2025-05, 2025-06, 2025-07, 2025-10, 2025-11
A12: 10 | B12: =(SUM('IP Ratios'!L28,'IP Ratios'!L29,'IP Ratios'!L30,'IP Ratios'!L31,'IP Ratios'!L34,'IP Ratios'!L35)-MAX('IP Ratios'!L28,'IP Ratios'!L29,'IP Ratios'!L30,'IP Ratios'!L31,'IP Ratios'!L34,'IP Ratios'!L35)-MIN('IP Ratios'!L28,'IP Ratios'!L29,'IP Ratios'!L30,'IP Ratios'!L31,'IP Ratios'!L34,'IP Ratios'!L35))/(COUNT('IP Ratios'!L28,'IP Ratios'!L29,'IP Ratios'!L30,'IP Ratios'!L31,'IP Ratios'!L34,'IP Ratios'!L35)-2) | D12: =IF(ISNUMBER(C12),C12,B12) | E12: =1/PRODUCT(D12:D46) | F12: 2025-03, 2025-04, 2025-05, 2025-06, 2025-09, 2025-10
A13: 11 | B13: =(SUM('IP Ratios'!M27,'IP Ratios'!M28,'IP Ratios'!M29,'IP Ratios'!M30,'IP Ratios'!M33,'IP Ratios'!M34)-MAX('IP Ratios'!M27,'IP Ratios'!M28,'IP Ratios'!M29,'IP Ratios'!M30,'IP Ratios'!M33,'IP Ratios'!M34)-MIN('IP Ratios'!M27,'IP Ratios'!M28,'IP Ratios'!M29,'IP Ratios'!M30,'IP Ratios'!M33,'IP Ratios'!M34))/(COUNT('IP Ratios'!M27,'IP Ratios'!M28,'IP Ratios'!M29,'IP Ratios'!M30,'IP Ratios'!M33,'IP Ratios'!M34)-2) | D13: =IF(ISNUMBER(C13),C13,B13) | E13: =1/PRODUCT(D13:D46) | F13: 2025-02, 2025-03, 2025-04, 2025-05, 2025-08, 2025-09
A14: 12 | B14: =(SUM('IP Ratios'!N26,'IP Ratios'!N27,'IP Ratios'!N28,'IP Ratios'!N29,'IP Ratios'!N32,'IP Ratios'!N33)-MAX('IP Ratios'!N26,'IP Ratios'!N27,'IP Ratios'!N28,'IP Ratios'!N29,'IP Ratios'!N32,'IP Ratios'!N33)-MIN('IP Ratios'!N26,'IP Ratios'!N27,'IP Ratios'!N28,'IP Ratios'!N29,'IP Ratios'!N32,'IP Ratios'!N33))/(COUNT('IP Ratios'!N26,'IP Ratios'!N27,'IP Ratios'!N28,'IP Ratios'!N29,'IP Ratios'!N32,'IP Ratios'!N33)-2) | D14: =IF(ISNUMBER(C14),C14,B14) | E14: =1/PRODUCT(D14:D46) | F14: 2025-01, 2025-02, 2025-03, 2025-04, 2025-07, 2025-08
A15: 13 | B15: =(SUM('IP Ratios'!O25,'IP Ratios'!O26,'IP Ratios'!O27,'IP Ratios'!O28,'IP Ratios'!O31,'IP Ratios'!O32)-MAX('IP Ratios'!O25,'IP Ratios'!O26,'IP Ratios'!O27,'IP Ratios'!O28,'IP Ratios'!O31,'IP Ratios'!O32)-MIN('IP Ratios'!O25,'IP Ratios'!O26,'IP Ratios'!O27,'IP Ratios'!O28,'IP Ratios'!O31,'IP Ratios'!O32))/(COUNT('IP Ratios'!O25,'IP Ratios'!O26,'IP Ratios'!O27,'IP Ratios'!O28,'IP Ratios'!O31,'IP Ratios'!O32)-2) | D15: =IF(ISNUMBER(C15),C15,B15) | E15: =1/PRODUCT(D15:D46) | F15: 2024-12, 2025-01, 2025-02, 2025-03, 2025-06, 2025-07
A16: 14 | B16: =(SUM('IP Ratios'!P24,'IP Ratios'!P25,'IP Ratios'!P26,'IP Ratios'!P27,'IP Ratios'!P30,'IP Ratios'!P31)-MAX('IP Ratios'!P24,'IP Ratios'!P25,'IP Ratios'!P26,'IP Ratios'!P27,'IP Ratios'!P30,'IP Ratios'!P31)-MIN('IP Ratios'!P24,'IP Ratios'!P25,'IP Ratios'!P26,'IP Ratios'!P27,'IP Ratios'!P30,'IP Ratios'!P31))/(COUNT('IP Ratios'!P24,'IP Ratios'!P25,'IP Ratios'!P26,'IP Ratios'!P27,'IP Ratios'!P30,'IP Ratios'!P31)-2) | D16: =IF(ISNUMBER(C16),C16,B16) | E16: =1/PRODUCT(D16:D46) | F16: 2024-11, 2024-12, 2025-01, 2025-02, 2025-05, 2025-06
A17: 15 | B17: =(SUM('IP Ratios'!Q23,'IP Ratios'!Q24,'IP Ratios'!Q25,'IP Ratios'!Q26,'IP Ratios'!Q29,'IP Ratios'!Q30)-MAX('IP Ratios'!Q23,'IP Ratios'!Q24,'IP Ratios'!Q25,'IP Ratios'!Q26,'IP Ratios'!Q29,'IP Ratios'!Q30)-MIN('IP Ratios'!Q23,'IP Ratios'!Q24,'IP Ratios'!Q25,'IP Ratios'!Q26,'IP Ratios'!Q29,'IP Ratios'!Q30))/(COUNT('IP Ratios'!Q23,'IP Ratios'!Q24,'IP Ratios'!Q25,'IP Ratios'!Q26,'IP Ratios'!Q29,'IP Ratios'!Q30)-2) | D17: =IF(ISNUMBER(C17),C17,B17) | E17: =1/PRODUCT(D17:D46) | F17: 2024-10, 2024-11, 2024-12, 2025-01, 2025-04, 2025-05
A18: 16 | B18: =(SUM('IP Ratios'!R22,'IP Ratios'!R23,'IP Ratios'!R24,'IP Ratios'!R25,'IP Ratios'!R28,'IP Ratios'!R29)-MAX('IP Ratios'!R22,'IP Ratios'!R23,'IP Ratios'!R24,'IP Ratios'!R25,'IP Ratios'!R28,'IP Ratios'!R29)-MIN('IP Ratios'!R22,'IP Ratios'!R23,'IP Ratios'!R24,'IP Ratios'!R25,'IP Ratios'!R28,'IP Ratios'!R29))/(COUNT('IP Ratios'!R22,'IP Ratios'!R23,'IP Ratios'!R24,'IP Ratios'!R25,'IP Ratios'!R28,'IP Ratios'!R29)-2) | D18: =IF(ISNUMBER(C18),C18,B18) | E18: =1/PRODUCT(D18:D46) | F18: 2024-09, 2024-10, 2024-11, 2024-12, 2025-03, 2025-04
A19: 17 | B19: =(SUM('IP Ratios'!S21,'IP Ratios'!S22,'IP Ratios'!S23,'IP Ratios'!S24,'IP Ratios'!S27,'IP Ratios'!S28)-MAX('IP Ratios'!S21,'IP Ratios'!S22,'IP Ratios'!S23,'IP Ratios'!S24,'IP Ratios'!S27,'IP Ratios'!S28)-MIN('IP Ratios'!S21,'IP Ratios'!S22,'IP Ratios'!S23,'IP Ratios'!S24,'IP Ratios'!S27,'IP Ratios'!S28))/(COUNT('IP Ratios'!S21,'IP Ratios'!S22,'IP Ratios'!S23,'IP Ratios'!S24,'IP Ratios'!S27,'IP Ratios'!S28)-2) | D19: =IF(ISNUMBER(C19),C19,B19) | E19: =1/PRODUCT(D19:D46) | F19: 2024-08, 2024-09, 2024-10, 2024-11, 2025-02, 2025-03
A20: 18 | B20: =(SUM('IP Ratios'!T20,'IP Ratios'!T21,'IP Ratios'!T22,'IP Ratios'!T23,'IP Ratios'!T26,'IP Ratios'!T27)-MAX('IP Ratios'!T20,'IP Ratios'!T21,'IP Ratios'!T22,'IP Ratios'!T23,'IP Ratios'!T26,'IP Ratios'!T27)-MIN('IP Ratios'!T20,'IP Ratios'!T21,'IP Ratios'!T22,'IP Ratios'!T23,'IP Ratios'!T26,'IP Ratios'!T27))/(COUNT('IP Ratios'!T20,'IP Ratios'!T21,'IP Ratios'!T22,'IP Ratios'!T23,'IP Ratios'!T26,'IP Ratios'!T27)-2) | D20: =IF(ISNUMBER(C20),C20,B20) | E20: =1/PRODUCT(D20:D46) | F20: 2024-07, 2024-08, 2024-09, 2024-10, 2025-01, 2025-02
A21: 19 | B21: =(SUM('IP Ratios'!U19,'IP Ratios'!U20,'IP Ratios'!U21,'IP Ratios'!U22,'IP Ratios'!U25,'IP Ratios'!U26)-MAX('IP Ratios'!U19,'IP Ratios'!U20,'IP Ratios'!U21,'IP Ratios'!U22,'IP Ratios'!U25,'IP Ratios'!U26)-MIN('IP Ratios'!U19,'IP Ratios'!U20,'IP Ratios'!U21,'IP Ratios'!U22,'IP Ratios'!U25,'IP Ratios'!U26))/(COUNT('IP Ratios'!U19,'IP Ratios'!U20,'IP Ratios'!U21,'IP Ratios'!U22,'IP Ratios'!U25,'IP Ratios'!U26)-2) | D21: =IF(ISNUMBER(C21),C21,B21) | E21: =1/PRODUCT(D21:D46) | F21: 2024-06, 2024-07, 2024-08, 2024-09, 2024-12, 2025-01
A22: 20 | B22: =(SUM('IP Ratios'!V18,'IP Ratios'!V19,'IP Ratios'!V20,'IP Ratios'!V21,'IP Ratios'!V24,'IP Ratios'!V25)-MAX('IP Ratios'!V18,'IP Ratios'!V19,'IP Ratios'!V20,'IP Ratios'!V21,'IP Ratios'!V24,'IP Ratios'!V25)-MIN('IP Ratios'!V18,'IP Ratios'!V19,'IP Ratios'!V20,'IP Ratios'!V21,'IP Ratios'!V24,'IP Ratios'!V25))/(COUNT('IP Ratios'!V18,'IP Ratios'!V19,'IP Ratios'!V20,'IP Ratios'!V21,'IP Ratios'!V24,'IP Ratios'!V25)-2) | D22: =IF(ISNUMBER(C22),C22,B22) | E22: =1/PRODUCT(D22:D46) | F22: 2024-05, 2024-06, 2024-07, 2024-08, 2024-11, 2024-12
A23: 21 | B23: =(SUM('IP Ratios'!W17,'IP Ratios'!W18,'IP Ratios'!W19,'IP Ratios'!W20,'IP Ratios'!W23,'IP Ratios'!W24)-MAX('IP Ratios'!W17,'IP Ratios'!W18,'IP Ratios'!W19,'IP Ratios'!W20,'IP Ratios'!W23,'IP Ratios'!W24)-MIN('IP Ratios'!W17,'IP Ratios'!W18,'IP Ratios'!W19,'IP Ratios'!W20,'IP Ratios'!W23,'IP Ratios'!W24))/(COUNT('IP Ratios'!W17,'IP Ratios'!W18,'IP Ratios'!W19,'IP Ratios'!W20,'IP Ratios'!W23,'IP Ratios'!W24)-2) | D23: =IF(ISNUMBER(C23),C23,B23) | E23: =1/PRODUCT(D23:D46) | F23: 2024-04, 2024-05, 2024-06, 2024-07, 2024-10, 2024-11
A24: 22 | B24: =(SUM('IP Ratios'!X16,'IP Ratios'!X17,'IP Ratios'!X18,'IP Ratios'!X19,'IP Ratios'!X22,'IP Ratios'!X23)-MAX('IP Ratios'!X16,'IP Ratios'!X17,'IP Ratios'!X18,'IP Ratios'!X19,'IP Ratios'!X22,'IP Ratios'!X23)-MIN('IP Ratios'!X16,'IP Ratios'!X17,'IP Ratios'!X18,'IP Ratios'!X19,'IP Ratios'!X22,'IP Ratios'!X23))/(COUNT('IP Ratios'!X16,'IP Ratios'!X17,'IP Ratios'!X18,'IP Ratios'!X19,'IP Ratios'!X22,'IP Ratios'!X23)-2) | D24: =IF(ISNUMBER(C24),C24,B24) | E24: =1/PRODUCT(D24:D46) | F24: 2024-03, 2024-04, 2024-05, 2024-06, 2024-09, 2024-10
A25: 23 | B25: =(SUM('IP Ratios'!Y15,'IP Ratios'!Y16,'IP Ratios'!Y17,'IP Ratios'!Y18,'IP Ratios'!Y21,'IP Ratios'!Y22)-MAX('IP Ratios'!Y15,'IP Ratios'!Y16,'IP Ratios'!Y17,'IP Ratios'!Y18,'IP Ratios'!Y21,'IP Ratios'!Y22)-MIN('IP Ratios'!Y15,'IP Ratios'!Y16,'IP Ratios'!Y17,'IP Ratios'!Y18,'IP Ratios'!Y21,'IP Ratios'!Y22))/(COUNT('IP Ratios'!Y15,'IP Ratios'!Y16,'IP Ratios'!Y17,'IP Ratios'!Y18,'IP Ratios'!Y21,'IP Ratios'!Y22)-2) | D25: =IF(ISNUMBER(C25),C25,B25) | E25: =1/PRODUCT(D25:D46) | F25: 2024-02, 2024-03, 2024-04, 2024-05, 2024-08, 2024-09
A26: 24 | B26: =(SUM('IP Ratios'!Z14,'IP Ratios'!Z15,'IP Ratios'!Z16,'IP Ratios'!Z17,'IP Ratios'!Z20,'IP Ratios'!Z21)-MAX('IP Ratios'!Z14,'IP Ratios'!Z15,'IP Ratios'!Z16,'IP Ratios'!Z17,'IP Ratios'!Z20,'IP Ratios'!Z21)-MIN('IP Ratios'!Z14,'IP Ratios'!Z15,'IP Ratios'!Z16,'IP Ratios'!Z17,'IP Ratios'!Z20,'IP Ratios'!Z21))/(COUNT('IP Ratios'!Z14,'IP Ratios'!Z15,'IP Ratios'!Z16,'IP Ratios'!Z17,'IP Ratios'!Z20,'IP Ratios'!Z21)-2) | D26: =IF(ISNUMBER(C26),C26,B26) | E26: =1/PRODUCT(D26:D46) | F26: 2024-01, 2024-02, 2024-03, 2024-04, 2024-07, 2024-08
A27: 25 | B27: =(SUM('IP Ratios'!AA13,'IP Ratios'!AA14,'IP Ratios'!AA15,'IP Ratios'!AA16,'IP Ratios'!AA19,'IP Ratios'!AA20)-MAX('IP Ratios'!AA13,'IP Ratios'!AA14,'IP Ratios'!AA15,'IP Ratios'!AA16,'IP Ratios'!AA19,'IP Ratios'!AA20)-MIN('IP Ratios'!AA13,'IP Ratios'!AA14,'IP Ratios'!AA15,'IP Ratios'!AA16,'IP Ratios'!AA19,'IP Ratios'!AA20))/(COUNT('IP Ratios'!AA13,'IP Ratios'!AA14,'IP Ratios'!AA15,'IP Ratios'!AA16,'IP Ratios'!AA19,'IP Ratios'!AA20)-2) | D27: =IF(ISNUMBER(C27),C27,B27) | E27: =1/PRODUCT(D27:D46) | F27: 2023-12, 2024-01, 2024-02, 2024-03, 2024-06, 2024-07
A28: 26 | B28: =(SUM('IP Ratios'!AB12,'IP Ratios'!AB13,'IP Ratios'!AB14,'IP Ratios'!AB15,'IP Ratios'!AB18,'IP Ratios'!AB19)-MAX('IP Ratios'!AB12,'IP Ratios'!AB13,'IP Ratios'!AB14,'IP Ratios'!AB15,'IP Ratios'!AB18,'IP Ratios'!AB19)-MIN('IP Ratios'!AB12,'IP Ratios'!AB13,'IP Ratios'!AB14,'IP Ratios'!AB15,'IP Ratios'!AB18,'IP Ratios'!AB19))/(COUNT('IP Ratios'!AB12,'IP Ratios'!AB13,'IP Ratios'!AB14,'IP Ratios'!AB15,'IP Ratios'!AB18,'IP Ratios'!AB19)-2) | D28: =IF(ISNUMBER(C28),C28,B28) | E28: =1/PRODUCT(D28:D46) | F28: 2023-11, 2023-12, 2024-01, 2024-02, 2024-05, 2024-06
A29: 27 | B29: =(SUM('IP Ratios'!AC11,'IP Ratios'!AC12,'IP Ratios'!AC13,'IP Ratios'!AC14,'IP Ratios'!AC17,'IP Ratios'!AC18)-MAX('IP Ratios'!AC11,'IP Ratios'!AC12,'IP Ratios'!AC13,'IP Ratios'!AC14,'IP Ratios'!AC17,'IP Ratios'!AC18)-MIN('IP Ratios'!AC11,'IP Ratios'!AC12,'IP Ratios'!AC13,'IP Ratios'!AC14,'IP Ratios'!AC17,'IP Ratios'!AC18))/(COUNT('IP Ratios'!AC11,'IP Ratios'!AC12,'IP Ratios'!AC13,'IP Ratios'!AC14,'IP Ratios'!AC17,'IP Ratios'!AC18)-2) | D29: =IF(ISNUMBER(C29),C29,B29) | E29: =1/PRODUCT(D29:D46) | F29: 2023-10, 2023-11, 2023-12, 2024-01, 2024-04, 2024-05
A30: 28 | B30: =(SUM('IP Ratios'!AD10,'IP Ratios'!AD11,'IP Ratios'!AD12,'IP Ratios'!AD13,'IP Ratios'!AD16,'IP Ratios'!AD17)-MAX('IP Ratios'!AD10,'IP Ratios'!AD11,'IP Ratios'!AD12,'IP Ratios'!AD13,'IP Ratios'!AD16,'IP Ratios'!AD17)-MIN('IP Ratios'!AD10,'IP Ratios'!AD11,'IP Ratios'!AD12,'IP Ratios'!AD13,'IP Ratios'!AD16,'IP Ratios'!AD17))/(COUNT('IP Ratios'!AD10,'IP Ratios'!AD11,'IP Ratios'!AD12,'IP Ratios'!AD13,'IP Ratios'!AD16,'IP Ratios'!AD17)-2) | D30: =IF(ISNUMBER(C30),C30,B30) | E30: =1/PRODUCT(D30:D46) | F30: 2023-09, 2023-10, 2023-11, 2023-12, 2024-03, 2024-04
A31: 29 | B31: =(SUM('IP Ratios'!AE9,'IP Ratios'!AE10,'IP Ratios'!AE11,'IP Ratios'!AE12,'IP Ratios'!AE15,'IP Ratios'!AE16)-MAX('IP Ratios'!AE9,'IP Ratios'!AE10,'IP Ratios'!AE11,'IP Ratios'!AE12,'IP Ratios'!AE15,'IP Ratios'!AE16)-MIN('IP Ratios'!AE9,'IP Ratios'!AE10,'IP Ratios'!AE11,'IP Ratios'!AE12,'IP Ratios'!AE15,'IP Ratios'!AE16))/(COUNT('IP Ratios'!AE9,'IP Ratios'!AE10,'IP Ratios'!AE11,'IP Ratios'!AE12,'IP Ratios'!AE15,'IP Ratios'!AE16)-2) | D31: =IF(ISNUMBER(C31),C31,B31) | E31: =1/PRODUCT(D31:D46) | F31: 2023-08, 2023-09, 2023-10, 2023-11, 2024-02, 2024-03
A32: 30 | B32: =(SUM('IP Ratios'!AF8,'IP Ratios'!AF9,'IP Ratios'!AF10,'IP Ratios'!AF11,'IP Ratios'!AF14,'IP Ratios'!AF15)-MAX('IP Ratios'!AF8,'IP Ratios'!AF9,'IP Ratios'!AF10,'IP Ratios'!AF11,'IP Ratios'!AF14,'IP Ratios'!AF15)-MIN('IP Ratios'!AF8,'IP Ratios'!AF9,'IP Ratios'!AF10,'IP Ratios'!AF11,'IP Ratios'!AF14,'IP Ratios'!AF15))/(COUNT('IP Ratios'!AF8,'IP Ratios'!AF9,'IP Ratios'!AF10,'IP Ratios'!AF11,'IP Ratios'!AF14,'IP Ratios'!AF15)-2) | D32: =IF(ISNUMBER(C32),C32,B32) | E32: =1/PRODUCT(D32:D46) | F32: 2023-07, 2023-08, 2023-09, 2023-10, 2024-01, 2024-02
A33: 31 | B33: =(SUM('IP Ratios'!AG7,'IP Ratios'!AG8,'IP Ratios'!AG9,'IP Ratios'!AG10,'IP Ratios'!AG13,'IP Ratios'!AG14)-MAX('IP Ratios'!AG7,'IP Ratios'!AG8,'IP Ratios'!AG9,'IP Ratios'!AG10,'IP Ratios'!AG13,'IP Ratios'!AG14)-MIN('IP Ratios'!AG7,'IP Ratios'!AG8,'IP Ratios'!AG9,'IP Ratios'!AG10,'IP Ratios'!AG13,'IP Ratios'!AG14))/(COUNT('IP Ratios'!AG7,'IP Ratios'!AG8,'IP Ratios'!AG9,'IP Ratios'!AG10,'IP Ratios'!AG13,'IP Ratios'!AG14)-2) | D33: =IF(ISNUMBER(C33),C33,B33) | E33: =1/PRODUCT(D33:D46) | F33: 2023-06, 2023-07, 2023-08, 2023-09, 2023-12, 2024-01
A34: 32 | B34: =(SUM('IP Ratios'!AH6,'IP Ratios'!AH7,'IP Ratios'!AH8,'IP Ratios'!AH9,'IP Ratios'!AH12,'IP Ratios'!AH13)-MAX('IP Ratios'!AH6,'IP Ratios'!AH7,'IP Ratios'!AH8,'IP Ratios'!AH9,'IP Ratios'!AH12,'IP Ratios'!AH13)-MIN('IP Ratios'!AH6,'IP Ratios'!AH7,'IP Ratios'!AH8,'IP Ratios'!AH9,'IP Ratios'!AH12,'IP Ratios'!AH13))/(COUNT('IP Ratios'!AH6,'IP Ratios'!AH7,'IP Ratios'!AH8,'IP Ratios'!AH9,'IP Ratios'!AH12,'IP Ratios'!AH13)-2) | D34: =IF(ISNUMBER(C34),C34,B34) | E34: =1/PRODUCT(D34:D46) | F34: 2023-05, 2023-06, 2023-07, 2023-08, 2023-11, 2023-12
A35: 33 | B35: =(SUM('IP Ratios'!AI5,'IP Ratios'!AI6,'IP Ratios'!AI7,'IP Ratios'!AI8,'IP Ratios'!AI11,'IP Ratios'!AI12)-MAX('IP Ratios'!AI5,'IP Ratios'!AI6,'IP Ratios'!AI7,'IP Ratios'!AI8,'IP Ratios'!AI11,'IP Ratios'!AI12)-MIN('IP Ratios'!AI5,'IP Ratios'!AI6,'IP Ratios'!AI7,'IP Ratios'!AI8,'IP Ratios'!AI11,'IP Ratios'!AI12))/(COUNT('IP Ratios'!AI5,'IP Ratios'!AI6,'IP Ratios'!AI7,'IP Ratios'!AI8,'IP Ratios'!AI11,'IP Ratios'!AI12)-2) | D35: =IF(ISNUMBER(C35),C35,B35) | E35: =1/PRODUCT(D35:D46) | F35: 2023-04, 2023-05, 2023-06, 2023-07, 2023-10, 2023-11
A36: 34 | B36: =(SUM('IP Ratios'!AJ4,'IP Ratios'!AJ5,'IP Ratios'!AJ6,'IP Ratios'!AJ7,'IP Ratios'!AJ10,'IP Ratios'!AJ11)-MAX('IP Ratios'!AJ4,'IP Ratios'!AJ5,'IP Ratios'!AJ6,'IP Ratios'!AJ7,'IP Ratios'!AJ10,'IP Ratios'!AJ11)-MIN('IP Ratios'!AJ4,'IP Ratios'!AJ5,'IP Ratios'!AJ6,'IP Ratios'!AJ7,'IP Ratios'!AJ10,'IP Ratios'!AJ11))/(COUNT('IP Ratios'!AJ4,'IP Ratios'!AJ5,'IP Ratios'!AJ6,'IP Ratios'!AJ7,'IP Ratios'!AJ10,'IP Ratios'!AJ11)-2) | D36: =IF(ISNUMBER(C36),C36,B36) | E36: =1/PRODUCT(D36:D46) | F36: 2023-03, 2023-04, 2023-05, 2023-06, 2023-09, 2023-10
A37: 35 | B37: =(SUM('IP Ratios'!AK3,'IP Ratios'!AK4,'IP Ratios'!AK5,'IP Ratios'!AK6,'IP Ratios'!AK9,'IP Ratios'!AK10)-MAX('IP Ratios'!AK3,'IP Ratios'!AK4,'IP Ratios'!AK5,'IP Ratios'!AK6,'IP Ratios'!AK9,'IP Ratios'!AK10)-MIN('IP Ratios'!AK3,'IP Ratios'!AK4,'IP Ratios'!AK5,'IP Ratios'!AK6,'IP Ratios'!AK9,'IP Ratios'!AK10))/(COUNT('IP Ratios'!AK3,'IP Ratios'!AK4,'IP Ratios'!AK5,'IP Ratios'!AK6,'IP Ratios'!AK9,'IP Ratios'!AK10)-2) | D37: =IF(ISNUMBER(C37),C37,B37) | E37: =1/PRODUCT(D37:D46) | F37: 2023-02, 2023-03, 2023-04, 2023-05, 2023-08, 2023-09
A38: 36 | B38: 1 | D38: =IF(ISNUMBER(C38),C38,B38) | E38: =1/PRODUCT(D38:D46) | F38: 2023-01, 2023-02, 2023-03, 2023-04, 2023-07, 2023-08
A39: 37 | B39: 1 | D39: =IF(ISNUMBER(C39),C39,B39) | E39: =1/PRODUCT(D39:D46) | F39: 2023-01, 2023-02, 2023-03, 2023-06, 2023-07
A40: 38 | B40: 1 | D40: =IF(ISNUMBER(C40),C40,B40) | E40: =1/PRODUCT(D40:D46) | F40: 2023-01, 2023-02, 2023-05, 2023-06
A41: 39 | B41: 1 | D41: =IF(ISNUMBER(C41),C41,B41) | E41: =1/PRODUCT(D41:D46) | F41: 2023-01, 2023-04, 2023-05
A42: 40 | B42: 1 | D42: =IF(ISNUMBER(C42),C42,B42) | E42: =1/PRODUCT(D42:D46) | F42: 2023-03, 2023-04
A43: 41 | B43: 1 | D43: =IF(ISNUMBER(C43),C43,B43) | E43: =1/PRODUCT(D43:D46) | F43: 2023-02, 2023-03
A44: 42 | B44: 1 | D44: =IF(ISNUMBER(C44),C44,B44) | E44: =1/PRODUCT(D44:D46) | F44: 2023-01, 2023-02
A45: 43 | B45: 1 | D45: =IF(ISNUMBER(C45),C45,B45) | E45: =1/PRODUCT(D45:D46) | F45: 2023-01
A46: 44 | B46: 1 | D46: =IF(ISNUMBER(C46),C46,B46) | E46: =1/PRODUCT(D46:D46) | F46: complete

Sheet IP Reserve
A1: Incurred | B1: Member months | C1: Age | D1: Paid to date | E1: Paid for estimation | F1: Completion factor | G1: CF ultimate | H1: Expected PMPM | I1: Expected claims | J1: B-F ultimate | K1: Selected ultimate | L1: IBNR | M1: Method
A2: 2023-01 | B2: 185202 | C2: 44 | D2: ='IP Triangle'!AT2 | E2: ='IP Triangle'!AS2+(D2-'IP Triangle'!AS2)/Assumptions!$B$6 | F2: =INDEX('IP Factors'!$E:$E,C2+2) | G2: =E2/F2 | H2: 97.560013 | I2: =H2*B2 | J2: =E2+(1-F2)*I2 | K2: =IF(C2>=Assumptions!$B$3,G2,J2) | L2: =K2-D2 | M2: =IF(C2>=Assumptions!$B$3,"Completion factor","PMPM / B-F")
A3: 2023-02 | B3: 185248 | C3: 43 | D3: ='IP Triangle'!AS3 | E3: ='IP Triangle'!AR3+(D3-'IP Triangle'!AR3)/Assumptions!$B$6 | F3: =INDEX('IP Factors'!$E:$E,C3+2) | G3: =E3/F3 | H3: 96.359811 | I3: =H3*B3 | J3: =E3+(1-F3)*I3 | K3: =IF(C3>=Assumptions!$B$3,G3,J3) | L3: =K3-D3 | M3: =IF(C3>=Assumptions!$B$3,"Completion factor","PMPM / B-F")
A4: 2023-03 | B4: 185435 | C4: 42 | D4: ='IP Triangle'!AR4 | E4: ='IP Triangle'!AQ4+(D4-'IP Triangle'!AQ4)/Assumptions!$B$6 | F4: =INDEX('IP Factors'!$E:$E,C4+2) | G4: =E4/F4 | H4: 96.572832 | I4: =H4*B4 | J4: =E4+(1-F4)*I4 | K4: =IF(C4>=Assumptions!$B$3,G4,J4) | L4: =K4-D4 | M4: =IF(C4>=Assumptions!$B$3,"Completion factor","PMPM / B-F")
A5: 2023-04 | B5: 185785 | C5: 41 | D5: ='IP Triangle'!AQ5 | E5: ='IP Triangle'!AP5+(D5-'IP Triangle'!AP5)/Assumptions!$B$6 | F5: =INDEX('IP Factors'!$E:$E,C5+2) | G5: =E5/F5 | H5: 103.70607 | I5: =H5*B5 | J5: =E5+(1-F5)*I5 | K5: =IF(C5>=Assumptions!$B$3,G5,J5) | L5: =K5-D5 | M5: =IF(C5>=Assumptions!$B$3,"Completion factor","PMPM / B-F")
A6: 2023-05 | B6: 185684 | C6: 40 | D6: ='IP Triangle'!AP6 | E6: ='IP Triangle'!AO6+(D6-'IP Triangle'!AO6)/Assumptions!$B$6 | F6: =INDEX('IP Factors'!$E:$E,C6+2) | G6: =E6/F6 | H6: 103.15534 | I6: =H6*B6 | J6: =E6+(1-F6)*I6 | K6: =IF(C6>=Assumptions!$B$3,G6,J6) | L6: =K6-D6 | M6: =IF(C6>=Assumptions!$B$3,"Completion factor","PMPM / B-F")
A7: 2023-06 | B7: 186376 | C7: 39 | D7: ='IP Triangle'!AO7 | E7: ='IP Triangle'!AN7+(D7-'IP Triangle'!AN7)/Assumptions!$B$6 | F7: =INDEX('IP Factors'!$E:$E,C7+2) | G7: =E7/F7 | H7: 101.31239 | I7: =H7*B7 | J7: =E7+(1-F7)*I7 | K7: =IF(C7>=Assumptions!$B$3,G7,J7) | L7: =K7-D7 | M7: =IF(C7>=Assumptions!$B$3,"Completion factor","PMPM / B-F")
A8: 2023-07 | B8: 186902 | C8: 38 | D8: ='IP Triangle'!AN8 | E8: ='IP Triangle'!AM8+(D8-'IP Triangle'!AM8)/Assumptions!$B$6 | F8: =INDEX('IP Factors'!$E:$E,C8+2) | G8: =E8/F8 | H8: 98.790968 | I8: =H8*B8 | J8: =E8+(1-F8)*I8 | K8: =IF(C8>=Assumptions!$B$3,G8,J8) | L8: =K8-D8 | M8: =IF(C8>=Assumptions!$B$3,"Completion factor","PMPM / B-F")
A9: 2023-08 | B9: 187226 | C9: 37 | D9: ='IP Triangle'!AM9 | E9: ='IP Triangle'!AL9+(D9-'IP Triangle'!AL9)/Assumptions!$B$6 | F9: =INDEX('IP Factors'!$E:$E,C9+2) | G9: =E9/F9 | H9: 99.086726 | I9: =H9*B9 | J9: =E9+(1-F9)*I9 | K9: =IF(C9>=Assumptions!$B$3,G9,J9) | L9: =K9-D9 | M9: =IF(C9>=Assumptions!$B$3,"Completion factor","PMPM / B-F")
A10: 2023-09 | B10: 187750 | C10: 36 | D10: ='IP Triangle'!AL10 | E10: ='IP Triangle'!AK10+(D10-'IP Triangle'!AK10)/Assumptions!$B$6 | F10: =INDEX('IP Factors'!$E:$E,C10+2) | G10: =E10/F10 | H10: 102.08037 | I10: =H10*B10 | J10: =E10+(1-F10)*I10 | K10: =IF(C10>=Assumptions!$B$3,G10,J10) | L10: =K10-D10 | M10: =IF(C10>=Assumptions!$B$3,"Completion factor","PMPM / B-F")
A11: 2023-10 | B11: 187725 | C11: 35 | D11: ='IP Triangle'!AK11 | E11: ='IP Triangle'!AJ11+(D11-'IP Triangle'!AJ11)/Assumptions!$B$6 | F11: =INDEX('IP Factors'!$E:$E,C11+2) | G11: =E11/F11 | H11: 110.81026 | I11: =H11*B11 | J11: =E11+(1-F11)*I11 | K11: =IF(C11>=Assumptions!$B$3,G11,J11) | L11: =K11-D11 | M11: =IF(C11>=Assumptions!$B$3,"Completion factor","PMPM / B-F")
A12: 2023-11 | B12: 187816 | C12: 34 | D12: ='IP Triangle'!AJ12 | E12: ='IP Triangle'!AI12+(D12-'IP Triangle'!AI12)/Assumptions!$B$6 | F12: =INDEX('IP Factors'!$E:$E,C12+2) | G12: =E12/F12 | H12: 109.75884 | I12: =H12*B12 | J12: =E12+(1-F12)*I12 | K12: =IF(C12>=Assumptions!$B$3,G12,J12) | L12: =K12-D12 | M12: =IF(C12>=Assumptions!$B$3,"Completion factor","PMPM / B-F")
A13: 2023-12 | B13: 188296 | C13: 33 | D13: ='IP Triangle'!AI13 | E13: ='IP Triangle'!AH13+(D13-'IP Triangle'!AH13)/Assumptions!$B$6 | F13: =INDEX('IP Factors'!$E:$E,C13+2) | G13: =E13/F13 | H13: 115.93324 | I13: =H13*B13 | J13: =E13+(1-F13)*I13 | K13: =IF(C13>=Assumptions!$B$3,G13,J13) | L13: =K13-D13 | M13: =IF(C13>=Assumptions!$B$3,"Completion factor","PMPM / B-F")
A14: 2024-01 | B14: 195186 | C14: 32 | D14: ='IP Triangle'!AH14 | E14: ='IP Triangle'!AG14+(D14-'IP Triangle'!AG14)/Assumptions!$B$6 | F14: =INDEX('IP Factors'!$E:$E,C14+2) | G14: =E14/F14 | H14: 102.22408 | I14: =H14*B14 | J14: =E14+(1-F14)*I14 | K14: =IF(C14>=Assumptions!$B$3,G14,J14) | L14: =K14-D14 | M14: =IF(C14>=Assumptions!$B$3,"Completion factor","PMPM / B-F")
A15: 2024-02 | B15: 195754 | C15: 31 | D15: ='IP Triangle'!AG15 | E15: ='IP Triangle'!AF15+(D15-'IP Triangle'!AF15)/Assumptions!$B$6 | F15: =INDEX('IP Factors'!$E:$E,C15+2) | G15: =E15/F15 | H15: 100.9665 | I15: =H15*B15 | J15: =E15+(1-F15)*I15 | K15: =IF(C15>=Assumptions!$B$3,G15,J15) | L15: =K15-D15 | M15: =IF(C15>=Assumptions!$B$3,"Completion factor","PMPM / B-F")
A16: 2024-03 | B16: 196371 | C16: 30 | D16: ='IP Triangle'!AF16 | E16: ='IP Triangle'!AE16+(D16-'IP Triangle'!AE16)/Assumptions!$B$6 | F16: =INDEX('IP Factors'!$E:$E,C16+2) | G16: =E16/F16 | H16: 101.1897 | I16: =H16*B16 | J16: =E16+(1-F16)*I16 | K16: =IF(C16>=Assumptions!$B$3,G16,J16) | L16: =K16-D16 | M16: =IF(C16>=Assumptions!$B$3,"Completion factor","PMPM / B-F")
A17: 2024-04 | B17: 196912 | C17: 29 | D17: ='IP Triangle'!AE17 | E17: ='IP Triangle'!AD17+(D17-'IP Triangle'!AD17)/Assumptions!$B$6 | F17: =INDEX('IP Factors'!$E:$E,C17+2) | G17: =E17/F17 | H17: 108.66396 | I17: =H17*B17 | J17: =E17+(1-F17)*I17 | K17: =IF(C17>=Assumptions!$B$3,G17,J17) | L17: =K17-D17 | M17: =IF(C17>=Assumptions!$B$3,"Completion factor","PMPM / B-F")
A18: 2024-05 | B18: 197352 | C18: 28 | D18: ='IP Triangle'!AD18 | E18: ='IP Triangle'!AC18+(D18-'IP Triangle'!AC18)/Assumptions!$B$6 | F18: =INDEX('IP Factors'!$E:$E,C18+2) | G18: =E18/F18 | H18: 108.0869 | I18: =H18*B18 | J18: =E18+(1-F18)*I18 | K18: =IF(C18>=Assumptions!$B$3,G18,J18) | L18: =K18-D18 | M18: =IF(C18>=Assumptions!$B$3,"Completion factor","PMPM / B-F")
A19: 2024-06 | B19: 198493 | C19: 27 | D19: ='IP Triangle'!AC19 | E19: ='IP Triangle'!AB19+(D19-'IP Triangle'!AB19)/Assumptions!$B$6 | F19: =INDEX('IP Factors'!$E:$E,C19+2) | G19: =E19/F19 | H19: 106.15584 | I19: =H19*B19 | J19: =E19+(1-F19)*I19 | K19: =IF(C19>=Assumptions!$B$3,G19,J19) | L19: =K19-D19 | M19: =IF(C19>=Assumptions!$B$3,"Completion factor","PMPM / B-F")
A20: 2024-07 | B20: 198829 | C20: 26 | D20: ='IP Triangle'!AB20 | E20: ='IP Triangle'!AA20+(D20-'IP Triangle'!AA20)/Assumptions!$B$6 | F20: =INDEX('IP Factors'!$E:$E,C20+2) | G20: =E20/F20 | H20: 103.51388 | I20: =H20*B20 | J20: =E20+(1-F20)*I20 | K20: =IF(C20>=Assumptions!$B$3,G20,J20) | L20: =K20-D20 | M20: =IF(C20>=Assumptions!$B$3,"Completion factor","PMPM / B-F")
A21: 2024-08 | B21: 199099 | C21: 25 | D21: ='IP Triangle'!AA21 | E21: ='IP Triangle'!Z21+(D21-'IP Triangle'!Z21)/Assumptions!$B$6 | F21: =INDEX('IP Factors'!$E:$E,C21+2) | G21: =E21/F21 | H21: 103.82378 | I21: =H21*B21 | J21: =E21+(1-F21)*I21 | K21: =IF(C21>=Assumptions!$B$3,G21,J21) | L21: =K21-D21 | M21: =IF(C21>=Assumptions!$B$3,"Completion factor","PMPM / B-F")
A22: 2024-09 | B22: 199429 | C22: 24 | D22: ='IP Triangle'!Z22 | E22: ='IP Triangle'!Y22+(D22-'IP Triangle'!Y22)/Assumptions!$B$6 | F22: =INDEX('IP Factors'!$E:$E,C22+2) | G22: =E22/F22 | H22: 106.96054 | I22: =H22*B22 | J22: =E22+(1-F22)*I22 | K22: =IF(C22>=Assumptions!$B$3,G22,J22) | L22: =K22-D22 | M22: =IF(C22>=Assumptions!$B$3,"Completion factor","PMPM / B-F")
A23: 2024-10 | B23: 199749 | C23: 23 | D23: ='IP Triangle'!Y23 | E23: ='IP Triangle'!X23+(D23-'IP Triangle'!X23)/Assumptions!$B$6 | F23: =INDEX('IP Factors'!$E:$E,C23+2) | G23: =E23/F23 | H23: 116.10778 | I23: =H23*B23 | J23: =E23+(1-F23)*I23 | K23: =IF(C23>=Assumptions!$B$3,G23,J23) | L23: =K23-D23 | M23: =IF(C23>=Assumptions!$B$3,"Completion factor","PMPM / B-F")
A24: 2024-11 | B24: 200252 | C24: 22 | D24: ='IP Triangle'!X24 | E24: ='IP Triangle'!W24+(D24-'IP Triangle'!W24)/Assumptions!$B$6 | F24: =INDEX('IP Factors'!$E:$E,C24+2) | G24: =E24/F24 | H24: 115.0061 | I24: =H24*B24 | J24: =E24+(1-F24)*I24 | K24: =IF(C24>=Assumptions!$B$3,G24,J24) | L24: =K24-D24 | M24: =IF(C24>=Assumptions!$B$3,"Completion factor","PMPM / B-F")
A25: 2024-12 | B25: 200297 | C25: 21 | D25: ='IP Triangle'!W25 | E25: ='IP Triangle'!V25+(D25-'IP Triangle'!V25)/Assumptions!$B$6 | F25: =INDEX('IP Factors'!$E:$E,C25+2) | G25: =E25/F25 | H25: 121.47567 | I25: =H25*B25 | J25: =E25+(1-F25)*I25 | K25: =IF(C25>=Assumptions!$B$3,G25,J25) | L25: =K25-D25 | M25: =IF(C25>=Assumptions!$B$3,"Completion factor","PMPM / B-F")
A26: 2025-01 | B26: 206379 | C26: 20 | D26: ='IP Triangle'!V26 | E26: ='IP Triangle'!U26+(D26-'IP Triangle'!U26)/Assumptions!$B$6 | F26: =INDEX('IP Factors'!$E:$E,C26+2) | G26: =E26/F26 | H26: 107.11112 | I26: =H26*B26 | J26: =E26+(1-F26)*I26 | K26: =IF(C26>=Assumptions!$B$3,G26,J26) | L26: =K26-D26 | M26: =IF(C26>=Assumptions!$B$3,"Completion factor","PMPM / B-F")
A27: 2025-02 | B27: 206414 | C27: 19 | D27: ='IP Triangle'!U27 | E27: ='IP Triangle'!T27+(D27-'IP Triangle'!T27)/Assumptions!$B$6 | F27: =INDEX('IP Factors'!$E:$E,C27+2) | G27: =E27/F27 | H27: 105.79342 | I27: =H27*B27 | J27: =E27+(1-F27)*I27 | K27: =IF(C27>=Assumptions!$B$3,G27,J27) | L27: =K27-D27 | M27: =IF(C27>=Assumptions!$B$3,"Completion factor","PMPM / B-F")
A28: 2025-03 | B28: 207034 | C28: 18 | D28: ='IP Triangle'!T28 | E28: ='IP Triangle'!S28+(D28-'IP Triangle'!S28)/Assumptions!$B$6 | F28: =INDEX('IP Factors'!$E:$E,C28+2) | G28: =E28/F28 | H28: 106.02729 | I28: =H28*B28 | J28: =E28+(1-F28)*I28 | K28: =IF(C28>=Assumptions!$B$3,G28,J28) | L28: =K28-D28 | M28: =IF(C28>=Assumptions!$B$3,"Completion factor","PMPM / B-F")
A29: 2025-04 | B29: 207074 | C29: 17 | D29: ='IP Triangle'!S29 | E29: ='IP Triangle'!R29+(D29-'IP Triangle'!R29)/Assumptions!$B$6 | F29: =INDEX('IP Factors'!$E:$E,C29+2) | G29: =E29/F29 | H29: 113.85888 | I29: =H29*B29 | J29: =E29+(1-F29)*I29 | K29: =IF(C29>=Assumptions!$B$3,G29,J29) | L29: =K29-D29 | M29: =IF(C29>=Assumptions!$B$3,"Completion factor","PMPM / B-F")
A30: 2025-05 | B30: 207656 | C30: 16 | D30: ='IP Triangle'!R30 | E30: ='IP Triangle'!Q30+(D30-'IP Triangle'!Q30)/Assumptions!$B$6 | F30: =INDEX('IP Factors'!$E:$E,C30+2) | G30: =E30/F30 | H30: 113.25423 | I30: =H30*B30 | J30: =E30+(1-F30)*I30 | K30: =IF(C30>=Assumptions!$B$3,G30,J30) | L30: =K30-D30 | M30: =IF(C30>=Assumptions!$B$3,"Completion factor","PMPM / B-F")
A31: 2025-06 | B31: 208551 | C31: 15 | D31: ='IP Triangle'!Q31 | E31: ='IP Triangle'!P31+(D31-'IP Triangle'!P31)/Assumptions!$B$6 | F31: =INDEX('IP Factors'!$E:$E,C31+2) | G31: =E31/F31 | H31: 111.23085 | I31: =H31*B31 | J31: =E31+(1-F31)*I31 | K31: =IF(C31>=Assumptions!$B$3,G31,J31) | L31: =K31-D31 | M31: =IF(C31>=Assumptions!$B$3,"Completion factor","PMPM / B-F")
A32: 2025-07 | B32: 208290 | C32: 14 | D32: ='IP Triangle'!P32 | E32: ='IP Triangle'!O32+(D32-'IP Triangle'!O32)/Assumptions!$B$6 | F32: =INDEX('IP Factors'!$E:$E,C32+2) | G32: =E32/F32 | H32: 108.46258 | I32: =H32*B32 | J32: =E32+(1-F32)*I32 | K32: =IF(C32>=Assumptions!$B$3,G32,J32) | L32: =K32-D32 | M32: =IF(C32>=Assumptions!$B$3,"Completion factor","PMPM / B-F")
A33: 2025-08 | B33: 209114 | C33: 13 | D33: ='IP Triangle'!O33 | E33: ='IP Triangle'!N33+(D33-'IP Triangle'!N33)/Assumptions!$B$6 | F33: =INDEX('IP Factors'!$E:$E,C33+2) | G33: =E33/F33 | H33: 108.7873 | I33: =H33*B33 | J33: =E33+(1-F33)*I33 | K33: =IF(C33>=Assumptions!$B$3,G33,J33) | L33: =K33-D33 | M33: =IF(C33>=Assumptions!$B$3,"Completion factor","PMPM / B-F")
A34: 2025-09 | B34: 209604 | C34: 12 | D34: ='IP Triangle'!N34 | E34: ='IP Triangle'!M34+(D34-'IP Triangle'!M34)/Assumptions!$B$6 | F34: =INDEX('IP Factors'!$E:$E,C34+2) | G34: =E34/F34 | H34: 112.07401 | I34: =H34*B34 | J34: =E34+(1-F34)*I34 | K34: =IF(C34>=Assumptions!$B$3,G34,J34) | L34: =K34-D34 | M34: =IF(C34>=Assumptions!$B$3,"Completion factor","PMPM / B-F")
A35: 2025-10 | B35: 210074 | C35: 11 | D35: ='IP Triangle'!M35 | E35: ='IP Triangle'!L35+(D35-'IP Triangle'!L35)/Assumptions!$B$6 | F35: =INDEX('IP Factors'!$E:$E,C35+2) | G35: =E35/F35 | H35: 121.65856 | I35: =H35*B35 | J35: =E35+(1-F35)*I35 | K35: =IF(C35>=Assumptions!$B$3,G35,J35) | L35: =K35-D35 | M35: =IF(C35>=Assumptions!$B$3,"Completion factor","PMPM / B-F")
A36: 2025-11 | B36: 210375 | C36: 10 | D36: ='IP Triangle'!L36 | E36: ='IP Triangle'!K36+(D36-'IP Triangle'!K36)/Assumptions!$B$6 | F36: =INDEX('IP Factors'!$E:$E,C36+2) | G36: =E36/F36 | H36: 120.50421 | I36: =H36*B36 | J36: =E36+(1-F36)*I36 | K36: =IF(C36>=Assumptions!$B$3,G36,J36) | L36: =K36-D36 | M36: =IF(C36>=Assumptions!$B$3,"Completion factor","PMPM / B-F")
A37: 2025-12 | B37: 211296 | C37: 9 | D37: ='IP Triangle'!K37 | E37: ='IP Triangle'!J37+(D37-'IP Triangle'!J37)/Assumptions!$B$6 | F37: =INDEX('IP Factors'!$E:$E,C37+2) | G37: =E37/F37 | H37: 127.28308 | I37: =H37*B37 | J37: =E37+(1-F37)*I37 | K37: =IF(C37>=Assumptions!$B$3,G37,J37) | L37: =K37-D37 | M37: =IF(C37>=Assumptions!$B$3,"Completion factor","PMPM / B-F")
A38: 2026-01 | B38: 218809 | C38: 8 | D38: ='IP Triangle'!J38 | E38: ='IP Triangle'!I38+(D38-'IP Triangle'!I38)/Assumptions!$B$6 | F38: =INDEX('IP Factors'!$E:$E,C38+2) | G38: =E38/F38 | H38: 112.23179 | I38: =H38*B38 | J38: =E38+(1-F38)*I38 | K38: =IF(C38>=Assumptions!$B$3,G38,J38) | L38: =K38-D38 | M38: =IF(C38>=Assumptions!$B$3,"Completion factor","PMPM / B-F")
A39: 2026-02 | B39: 219372 | C39: 7 | D39: ='IP Triangle'!I39 | E39: ='IP Triangle'!H39+(D39-'IP Triangle'!H39)/Assumptions!$B$6 | F39: =INDEX('IP Factors'!$E:$E,C39+2) | G39: =E39/F39 | H39: 110.8511 | I39: =H39*B39 | J39: =E39+(1-F39)*I39 | K39: =IF(C39>=Assumptions!$B$3,G39,J39) | L39: =K39-D39 | M39: =IF(C39>=Assumptions!$B$3,"Completion factor","PMPM / B-F")
A40: 2026-03 | B40: 219455 | C40: 6 | D40: ='IP Triangle'!H40 | E40: ='IP Triangle'!G40+(D40-'IP Triangle'!G40)/Assumptions!$B$6 | F40: =INDEX('IP Factors'!$E:$E,C40+2) | G40: =E40/F40 | H40: 111.09615 | I40: =H40*B40 | J40: =E40+(1-F40)*I40 | K40: =IF(C40>=Assumptions!$B$3,G40,J40) | L40: =K40-D40 | M40: =IF(C40>=Assumptions!$B$3,"Completion factor","PMPM / B-F")
A41: 2026-04 | B41: 219206 | C41: 5 | D41: ='IP Triangle'!G41 | E41: ='IP Triangle'!F41+(D41-'IP Triangle'!F41)/Assumptions!$B$6 | F41: =INDEX('IP Factors'!$E:$E,C41+2) | G41: =E41/F41 | H41: 119.30214 | I41: =H41*B41 | J41: =E41+(1-F41)*I41 | K41: =IF(C41>=Assumptions!$B$3,G41,J41) | L41: =K41-D41 | M41: =IF(C41>=Assumptions!$B$3,"Completion factor","PMPM / B-F")
A42: 2026-05 | B42: 219383 | C42: 4 | D42: ='IP Triangle'!F42 | E42: ='IP Triangle'!E42+(D42-'IP Triangle'!E42)/Assumptions!$B$6 | F42: =INDEX('IP Factors'!$E:$E,C42+2) | G42: =E42/F42 | H42: 118.66859 | I42: =H42*B42 | J42: =E42+(1-F42)*I42 | K42: =IF(C42>=Assumptions!$B$3,G42,J42) | L42: =K42-D42 | M42: =IF(C42>=Assumptions!$B$3,"Completion factor","PMPM / B-F")
A43: 2026-06 | B43: 219891 | C43: 3 | D43: ='IP Triangle'!E43 | E43: ='IP Triangle'!D43+(D43-'IP Triangle'!D43)/Assumptions!$B$6 | F43: =INDEX('IP Factors'!$E:$E,C43+2) | G43: =E43/F43 | H43: 116.54847 | I43: =H43*B43 | J43: =E43+(1-F43)*I43 | K43: =IF(C43>=Assumptions!$B$3,G43,J43) | L43: =K43-D43 | M43: =IF(C43>=Assumptions!$B$3,"Completion factor","PMPM / B-F")
A44: 2026-07 | B44: 220771 | C44: 2 | D44: ='IP Triangle'!D44 | E44: ='IP Triangle'!C44+(D44-'IP Triangle'!C44)/Assumptions!$B$6 | F44: =INDEX('IP Factors'!$E:$E,C44+2) | G44: =E44/F44 | H44: 113.64787 | I44: =H44*B44 | J44: =E44+(1-F44)*I44 | K44: =IF(C44>=Assumptions!$B$3,G44,J44) | L44: =K44-D44 | M44: =IF(C44>=Assumptions!$B$3,"Completion factor","PMPM / B-F")
A45: 2026-08 | B45: 221871 | C45: 1 | D45: ='IP Triangle'!C45 | E45: ='IP Triangle'!B45+(D45-'IP Triangle'!B45)/Assumptions!$B$6 | F45: =INDEX('IP Factors'!$E:$E,C45+2) | G45: =E45/F45 | H45: 113.98811 | I45: =H45*B45 | J45: =E45+(1-F45)*I45 | K45: =IF(C45>=Assumptions!$B$3,G45,J45) | L45: =K45-D45 | M45: =IF(C45>=Assumptions!$B$3,"Completion factor","PMPM / B-F")
A46: 2026-09 | B46: 222253 | C46: 0 | D46: ='IP Triangle'!B46 | E46: =0+(D46-0)/Assumptions!$B$6 | F46: =INDEX('IP Factors'!$E:$E,C46+2) | G46: =E46/F46 | H46: 117.43195 | I46: =H46*B46 | J46: =E46+(1-F46)*I46 | K46: =IF(C46>=Assumptions!$B$3,G46,J46) | L46: =K46-D46 | M46: =IF(C46>=Assumptions!$B$3,"Completion factor","PMPM / B-F")
A47: Total | B47: =SUM(B2:B46) | D47: =SUM(D2:D46) | G47: =SUM(G2:G46) | I47: =SUM(I2:I46) | K47: =SUM(K2:K46) | L47: =SUM(L2:L46)

Sheet OP Triangle
A1: Incurred | B1: Lag 0 | C1: Lag 1 | D1: Lag 2 | E1: Lag 3 | F1: Lag 4 | G1: Lag 5 | H1: Lag 6 | I1: Lag 7 | J1: Lag 8 | K1: Lag 9 | L1: Lag 10 | M1: Lag 11 | N1: Lag 12 | O1: Lag 13 | P1: Lag 14 | Q1: Lag 15 | R1: Lag 16 | S1: Lag 17 | T1: Lag 18 | U1: Lag 19 | V1: Lag 20 | W1: Lag 21 | X1: Lag 22 | Y1: Lag 23 | Z1: Lag 24 | AA1: Lag 25 | AB1: Lag 26 | AC1: Lag 27 | AD1: Lag 28 | AE1: Lag 29 | AF1: Lag 30 | AG1: Lag 31 | AH1: Lag 32 | AI1: Lag 33 | AJ1: Lag 34 | AK1: Lag 35 | AL1: Lag 36 | AM1: Lag 37 | AN1: Lag 38 | AO1: Lag 39 | AP1: Lag 40 | AQ1: Lag 41 | AR1: Lag 42 | AS1: Lag 43 | AT1: Lag 44
A2: 2023-01 | B2: 4269628 | C2: 12532731 | D2: 17656830 | E2: 20679239 | F2: 22318963 | G2: 23147144 | H2: 23577216 | I2: 23792026 | J2: 23897897 | K2: 23949123 | L2: 23975481 | M2: 23987006 | N2: 23992872 | O2: 23995551 | P2: 23996867 | Q2: 23997526 | R2: 23997833 | S2: 23997988 | T2: 23998058 | U2: 23998092 | V2: 23998107 | W2: 23998115 | X2: 23998118 | Y2: 23998120 | Z2: 23998121 | AA2: 23998121 | AB2: 23998121 | AC2: 23998121 | AD2: 23998121 | AE2: 23998121 | AF2: 23998121 | AG2: 23998121 | AH2: 23998121 | AI2: 23998121 | AJ2: 23998121 | AK2: 23998121 | AL2: 23998121 | AM2: 23998121 | AN2: 23998121 | AO2: 23998121 | AP2: 23998121 | AQ2: 23998121 | AR2: 23998121 | AS2: 23998121 | AT2: 23998121
A3: 2023-02 | B3: 5181033.2 | C3: 14391944 | D3: 20086390 | E3: 23590700 | F3: 25518263 | G3: 26476244 | H3: 26956407 | I3: 27213908 | J3: 27334126 | K3: 27392001 | L3: 27421318 | M3: 27434889 | N3: 27441410 | O3: 27444736 | P3: 27446204 | Q3: 27446916 | R3: 27447267 | S3: 27447431 | T3: 27447503 | U3: 27447540 | V3: 27447558 | W3: 27447566 | X3: 27447570 | Y3: 27447572 | Z3: 27447573 | AA3: 27447573 | AB3: 27447573 | AC3: 27447573 | AD3: 27447573 | AE3: 27447573 | AF3: 27447573 | AG3: 27447573 | AH3: 27447573 | AI3: 27447573 | AJ3: 27447573 | AK3: 27447573 | AL3: 27447573 | AM3: 27447573 | AN3: 27447573 | AO3: 27447573 | AP3: 27447573 | AQ3: 27447573 | AR3: 27447573 | AS3: 27447573
A4: 2023-03 | B4: 4879407.9 | C4: 13974292 | D4: 19542998 | E4: 22852750 | F4: 24664465 | G4: 25569880 | H4: 26017951 | I4: 26233455 | J4: 26344847 | K4: 26399714 | L4: 26426456 | M4: 26439170 | N4: 26445362 | O4: 26448163 | P4: 26449538 | Q4: 26450194 | R4: 26450508 | S4: 26450651 | T4: 26450725 | U4: 26450760 | V4: 26450775 | W4: 26450782 | X4: 26450786 | Y4: 26450788 | Z4: 26450788 | AA4: 26450789 | AB4: 26450789 | AC4: 26450789 | AD4: 26450789 | AE4: 26450789 | AF4: 26450789 | AG4: 26450789 | AH4: 26450789 | AI4: 26450789 | AJ4: 26450789 | AK4: 26450789 | AL4: 26450789 | AM4: 26450789 | AN4: 26450789 | AO4: 26450789 | AP4: 26450789 | AQ4: 26450789 | AR4: 26450789
A5: 2023-04 | B5: 4556068.5 | C5: 13173354 | D5: 18669941 | E5: 21721972 | F5: 23391170 | G5: 24225415 | H5: 24682704 | I5: 24884163 | J5: 24986737 | K5: 25037160 | L5: 25060815 | M5: 25072994 | N5: 25079029 | O5: 25081663 | P5: 25082973 | Q5: 25083582 | R5: 25083877 | S5: 25084013 | T5: 25084075 | U5: 25084105 | V5: 25084119 | W5: 25084126 | X5: 25084129 | Y5: 25084131 | Z5: 25084132 | AA5: 25084132 | AB5: 25084132 | AC5: 25084132 | AD5: 25084132 | AE5: 25084132 | AF5: 25084132 | AG5: 25084132 | AH5: 25084132 | AI5: 25084132 | AJ5: 25084132 | AK5: 25084132 | AL5: 25084132 | AM5: 25084132 | AN5: 25084132 | AO5: 25084132 | AP5: 25084132 | AQ5: 25084132
A6: 2023-05 | B6: 4839556.9 | C6: 14904135 | D6: 21173583 | E6: 24601736 | F6: 26448941 | G6: 27341996 | H6: 27831349 | I6: 28076695 | J6: 28191572 | K6: 28247586 | L6: 28274217 | M6: 28286756 | N6: 28292580 | O6: 28295621 | P6: 28297000 | Q6: 28297667 | R6: 28297978 | S6: 28298122 | T6: 28298190 | U6: 28298221 | V6: 28298236 | W6: 28298243 | X6: 28298247 | Y6: 28298248 | Z6: 28298249 | AA6: 28298249 | AB6: 28298249 | AC6: 28298249 | AD6: 28298250 | AE6: 28298250 | AF6: 28298250 | AG6: 28298250 | AH6: 28298250 | AI6: 28298250 | AJ6: 28298250 | AK6: 28298250 | AL6: 28298250 | AM6: 28298250 | AN6: 28298250 | AO6: 28298250 | AP6: 28298250
A7: 2023-06 | B7: 5127380.2 | C7: 14170589 | D7: 20042083 | E7: 23476730 | F7: 25402171 | G7: 26311680 | H7: 26776523 | I7: 26998168 | J7: 27110607 | K7: 27165892 | L7: 27192762 | M7: 27205052 | N7: 27210980 | O7: 27213884 | P7: 27215271 | Q7: 27215906 | R7: 27216193 | S7: 27216330 | T7: 27216395 | U7: 27216427 | V7: 27216442 | W7: 27216449 | X7: 27216452 | Y7: 27216454 | Z7: 27216454 | AA7: 27216455 | AB7: 27216455 | AC7: 27216455 | AD7: 27216455 | AE7: 27216455 | AF7: 27216455 | AG7: 27216455 | AH7: 27216455 | AI7: 27216455 | AJ7: 27216455 | AK7: 27216455 | AL7: 27216455 | AM7: 27216455 | AN7: 27216455 | AO7: 27216455
A8: 2023-07 | B8: 5416237.6 | C8: 15454306 | D8: 22063451 | E8: 25650419 | F8: 27425818 | G8: 28347852 | H8: 28846217 | I8: 29081454 | J8: 29195130 | K8: 29248931 | L8: 29275717 | M8: 29288464 | N8: 29294713 | O8: 29297542 | P8: 29298869 | Q8: 29299505 | R8: 29299807 | S8: 29299942 | T8: 29300010 | U8: 29300041 | V8: 29300055 | W8: 29300062 | X8: 29300065 | Y8: 29300067 | Z8: 29300068 | AA8: 29300068 | AB8: 29300068 | AC8: 29300068 | AD8: 29300068 | AE8: 29300068 | AF8: 29300068 | AG8: 29300068 | AH8: 29300068 | AI8: 29300068 | AJ8: 29300068 | AK8: 29300068 | AL8: 29300068 | AM8: 29300068 | AN8: 29300068
A9: 2023-08 | B9: 5712537.2 | C9: 15980836 | D9: 22788612 | E9: 26412637 | F9: 28356000 | G9: 29313469 | H9: 29804865 | I9: 30036748 | J9: 30151976 | K9: 30210341 | L9: 30237454 | M9: 30250327 | N9: 30256734 | O9: 30259861 | P9: 30261250 | Q9: 30261914 | R9: 30262217 | S9: 30262362 | T9: 30262430 | U9: 30262461 | V9: 30262476 | W9: 30262482 | X9: 30262486 | Y9: 30262487 | Z9: 30262488 | AA9: 30262488 | AB9: 30262488 | AC9: 30262488 | AD9: 30262488 | AE9: 30262488 | AF9: 30262488 | AG9: 30262488 | AH9: 30262488 | AI9: 30262488 | AJ9: 30262488 | AK9: 30262488 | AL9: 30262488 | AM9: 30262488
A10: 2023-09 | B10: 5548985 | C10: 15788300 | D10: 22443704 | E10: 26112451 | F10: 28058555 | G10: 29004906 | H10: 29473750 | I10: 29701174 | J10: 29816772 | K10: 29870145 | L10: 29897469 | M10: 29910564 | N10: 29916882 | O10: 29919636 | P10: 29920977 | Q10: 29921621 | R10: 29921913 | S10: 29922045 | T10: 29922113 | U10: 29922143 | V10: 29922158 | W10: 29922164 | X10: 29922167 | Y10: 29922169 | Z10: 29922170 | AA10: 29922170 | AB10: 29922170 | AC10: 29922170 | AD10: 29922170 | AE10: 29922170 | AF10: 29922170 | AG10: 29922170 | AH10: 29922170 | AI10: 29922170 | AJ10: 29922170 | AK10: 29922170 | AL10: 29922170
A11: 2023-10 | B11: 5786666.6 | C11: 16473580 | D11: 22742720 | E11: 26650237 | F11: 28658099 | G11: 29668581 | H11: 30139579 | I11: 30384933 | J11: 30503652 | K11: 30561041 | L11: 30589173 | M11: 30602041 | N11: 30608373 | O11: 30611129 | P11: 30612472 | Q11: 30613100 | R11: 30613411 | S11: 30613544 | T11: 30613607 | U11: 30613636 | V11: 30613649 | W11: 30613656 | X11: 30613659 | Y11: 30613660 | Z11: 30613661 | AA11: 30613661 | AB11: 30613661 | AC11: 30613661 | AD11: 30613661 | AE11: 30613661 | AF11: 30613661 | AG11: 30613661 | AH11: 30613661 | AI11: 30613661 | AJ11: 30613661 | AK11: 30613661
A12: 2023-11 | B12: 5837848.1 | C12: 16698595 | D12: 23182392 | E12: 26651252 | F12: 28721516 | G12: 29648732 | H12: 30117713 | I12: 30358870 | J12: 30467096 | K12: 30522512 | L12: 30547694 | M12: 30560198 | N12: 30565737 | O12: 30568377 | P12: 30569675 | Q12: 30570294 | R12: 30570571 | S12: 30570698 | T12: 30570761 | U12: 30570789 | V12: 30570801 | W12: 30570808 | X12: 30570810 | Y12: 30570812 | Z12: 30570812 | AA12: 30570813 | AB12: 30570813 | AC12: 30570813 | AD12: 30570813 | AE12: 30570813 | AF12: 30570813 | AG12: 30570813 | AH12: 30570813 | AI12: 30570813 | AJ12: 30570813
A13: 2023-12 | B13: 6217411 | C13: 18219934 | D13: 25519737 | E13: 29632943 | F13: 31794476 | G13: 32886574 | H13: 33407017 | I13: 33666945 | J13: 33793373 | K13: 33853248 | L13: 33882397 | M13: 33895561 | N13: 33901896 | O13: 33904843 | P13: 33906270 | Q13: 33906897 | R13: 33907203 | S13: 33907339 | T13: 33907404 | U13: 33907435 | V13: 33907450 | W13: 33907456 | X13: 33907459 | Y13: 33907460 | Z13: 33907461 | AA13: 33907461 | AB13: 33907461 | AC13: 33907461 | AD13: 33907461 | AE13: 33907461 | AF13: 33907461 | AG13: 33907461 | AH13: 33907461 | AI13: 33907461
A14: 2024-01 | B14: 5069765.9 | C14: 14605560 | D14: 20485477 | E14: 23764830 | F14: 25441054 | G14: 26299676 | H14: 26732106 | I14: 26932187 | J14: 27036366 | K14: 27082979 | L14: 27105306 | M14: 27116006 | N14: 27121380 | O14: 27123834 | P14: 27124933 | Q14: 27125425 | R14: 27125663 | S14: 27125770 | T14: 27125820 | U14: 27125843 | V14: 27125854 | W14: 27125858 | X14: 27125861 | Y14: 27125862 | Z14: 27125862 | AA14: 27125863 | AB14: 27125863 | AC14: 27125863 | AD14: 27125863 | AE14: 27125863 | AF14: 27125863 | AG14: 27125863 | AH14: 27125863
A15: 2024-02 | B15: 5788511.7 | C15: 16479710 | D15: 23549904 | E15: 27417488 | F15: 29289623 | G15: 30283916 | H15: 30766730 | I15: 30997084 | J15: 31111019 | K15: 31161826 | L15: 31187452 | M15: 31199563 | N15: 31205080 | O15: 31207617 | P15: 31208818 | Q15: 31209387 | R15: 31209636 | S15: 31209761 | T15: 31209817 | U15: 31209844 | V15: 31209855 | W15: 31209861 | X15: 31209864 | Y15: 31209865 | Z15: 31209865 | AA15: 31209866 | AB15: 31209866 | AC15: 31209866 | AD15: 31209866 | AE15: 31209866 | AF15: 31209866 | AG15: 31209866
A16: 2024-03 | B16: 6067858 | C16: 17069475 | D16: 23908831 | E16: 27563010 | F16: 29444068 | G16: 30415064 | H16: 30895129 | I16: 31121350 | J16: 31226855 | K16: 31277522 | L16: 31300040 | M16: 31311779 | N16: 31317275 | O16: 31319855 | P16: 31321039 | Q16: 31321597 | R16: 31321852 | S16: 31321967 | T16: 31322022 | U16: 31322047 | V16: 31322058 | W16: 31322063 | X16: 31322066 | Y16: 31322067 | Z16: 31322067 | AA16: 31322068 | AB16: 31322068 | AC16: 31322068 | AD16: 31322068 | AE16: 31322068 | AF16: 31322068
A17: 2024-04 | B17: 5634157 | C17: 15985916 | D17: 22581792 | E17: 26262457 | F17: 28172131 | G17: 29094302 | H17: 29601330 | I17: 29828886 | J17: 29933086 | K17: 29987396 | L17: 30011106 | M17: 30022505 | N17: 30027881 | O17: 30030362 | P17: 30031525 | Q17: 30032072 | R17: 30032311 | S17: 30032423 | T17: 30032477 | U17: 30032500 | V17: 30032512 | W17: 30032516 | X17: 30032518 | Y17: 30032520 | Z17: 30032520 | AA17: 30032520 | AB17: 30032520 | AC17: 30032520 | AD17: 30032520 | AE17: 30032520
A18: 2024-05 | B18: 5945348.4 | C18: 16961762 | D18: 23462480 | E18: 27254344 | F18: 29229476 | G18: 30193752 | H18: 30668746 | I18: 30891589 | J18: 30997697 | K18: 31047824 | L18: 31072513 | M18: 31083355 | N18: 31088349 | O18: 31090715 | P18: 31091837 | Q18: 31092362 | R18: 31092602 | S18: 31092708 | T18: 31092758 | U18: 31092782 | V18: 31092792 | W18: 31092797 | X18: 31092799 | Y18: 31092800 | Z18: 31092800 | AA18: 31092801 | AB18: 31092801 | AC18: 31092801 | AD18: 31092801
A19: 2024-06 | B19: 6654096 | C19: 18615945 | D19: 25872759 | E19: 29846297 | F19: 31846683 | G19: 32906967 | H19: 33397739 | I19: 33645788 | J19: 33758423 | K19: 33812508 | L19: 33837031 | M19: 33849105 | N19: 33854629 | O19: 33857167 | P19: 33858344 | Q19: 33858890 | R19: 33859140 | S19: 33859254 | T19: 33859306 | U19: 33859329 | V19: 33859340 | W19: 33859345 | X19: 33859348 | Y19: 33859349 | Z19: 33859349 | AA19: 33859349 | AB19: 33859349 | AC19: 33859349
A20: 2024-07 | B20: 6008984.8 | C20: 16132133 | D20: 23273381 | E20: 26903265 | F20: 28733239 | G20: 29687185 | H20: 30118980 | I20: 30339628 | J20: 30446884 | K20: 30496256 | L20: 30519646 | M20: 30529988 | N20: 30534689 | O20: 30537094 | P20: 30538174 | Q20: 30538654 | R20: 30538878 | S20: 30538983 | T20: 30539029 | U20: 30539051 | V20: 30539062 | W20: 30539066 | X20: 30539068 | Y20: 30539069 | Z20: 30539070 | AA20: 30539070 | AB20: 30539070
A21: 2024-08 | B21: 6916062 | C21: 19277155 | D21: 26836346 | E21: 31163047 | F21: 33288676 | G21: 34291653 | H21: 34787239 | I21: 35034730 | J21: 35150124 | K21: 35202435 | L21: 35227250 | M21: 35238453 | N21: 35243651 | O21: 35246050 | P21: 35247097 | Q21: 35247634 | R21: 35247879 | S21: 35247988 | T21: 35248036 | U21: 35248060 | V21: 35248070 | W21: 35248075 | X21: 35248076 | Y21: 35248078 | Z21: 35248078 | AA21: 35248078
A22: 2024-09 | B22: 6541575.2 | C22: 18580575 | D22: 25992724 | E22: 30138912 | F22: 32333546 | G22: 33329242 | H22: 33811489 | I22: 34052243 | J22: 34165181 | K22: 34220659 | L22: 34246204 | M22: 34257825 | N22: 34263027 | O22: 34265602 | P22: 34266778 | Q22: 34267313 | R22: 34267548 | S22: 34267655 | T22: 34267703 | U22: 34267725 | V22: 34267736 | W22: 34267740 | X22: 34267742 | Y22: 34267743 | Z22: 34267744
A23: 2024-10 | B23: 7387079.1 | C23: 19970290 | D23: 28057476 | E23: 32486913 | F23: 34701156 | G23: 35820003 | H23: 36347319 | I23: 36603230 | J23: 36718241 | K23: 36772969 | L23: 36797976 | M23: 36810005 | N23: 36815478 | O23: 36818110 | P23: 36819271 | Q23: 36819800 | R23: 36820047 | S23: 36820155 | T23: 36820203 | U23: 36820225 | V23: 36820234 | W23: 36820240 | X23: 36820242 | Y23: 36820243
A24: 2024-11 | B24: 6857811.3 | C24: 18782903 | D24: 26373862 | E24: 30343646 | F24: 32518787 | G24: 33535315 | H24: 34057416 | I24: 34291363 | J24: 34397417 | K24: 34445917 | L24: 34468580 | M24: 34480051 | N24: 34484917 | O24: 34487126 | P24: 34488182 | Q24: 34488656 | R24: 34488868 | S24: 34488967 | T24: 34489013 | U24: 34489030 | V24: 34489041 | W24: 34489045 | X24: 34489047
A25: 2024-12 | B25: 7473893.9 | C25: 22060963 | D25: 30616524 | E25: 35322726 | F25: 37770971 | G25: 38950569 | H25: 39493101 | I25: 39754789 | J25: 39884499 | K25: 39942203 | L25: 39967936 | M25: 39981266 | N25: 39987250 | O25: 39989904 | P25: 39991024 | Q25: 39991549 | R25: 39991794 | S25: 39991906 | T25: 39991947 | U25: 39991975 | V25: 39991985 | W25: 39991990
A26: 2025-01 | B26: 6679630.2 | C26: 18525336 | D26: 26225663 | E26: 30223187 | F26: 32307479 | G26: 33342451 | H26: 33834445 | I26: 34064911 | J26: 34171050 | K26: 34218664 | L26: 34239818 | M26: 34249947 | N26: 34254630 | O26: 34256733 | P26: 34257731 | Q26: 34258173 | R26: 34258372 | S26: 34258452 | T26: 34258503 | U26: 34258521 | V26: 34258530
A27: 2025-02 | B27: 6811110.6 | C27: 19414754 | D27: 26968086 | E27: 30939456 | F27: 32997264 | G27: 33948626 | H27: 34411356 | I27: 34637933 | J27: 34742866 | K27: 34787906 | L27: 34810662 | M27: 34820733 | N27: 34825284 | O27: 34827371 | P27: 34828342 | Q27: 34828771 | R27: 34828940 | S27: 34829051 | T27: 34829089 | U27: 34829106
A28: 2025-03 | B28: 7535319 | C28: 20821689 | D28: 29172782 | E28: 33478372 | F28: 35710989 | G28: 36734042 | H28: 37239416 | I28: 37464832 | J28: 37578905 | K28: 37628928 | L28: 37652703 | M28: 37663232 | N28: 37668182 | O28: 37670379 | P28: 37671367 | Q28: 37671735 | R28: 37671991 | S28: 37672081 | T28: 37672122
A29: 2025-04 | B29: 7455673.2 | C29: 20579534 | D29: 27889430 | E29: 32146467 | F29: 34164598 | G29: 35162888 | H29: 35638327 | I29: 35857775 | J29: 35962819 | K29: 36009461 | L29: 36032279 | M29: 36042176 | N29: 36046761 | O29: 36048855 | P29: 36049649 | Q29: 36050184 | R29: 36050371 | S29: 36050457
A30: 2025-05 | B30: 6698966 | C30: 19114322 | D30: 27036842 | E30: 30975992 | F30: 33027699 | G30: 33976592 | H30: 34423705 | I30: 34643343 | J30: 34739477 | K30: 34786592 | L30: 34806733 | M30: 34816335 | N30: 34820781 | O30: 34822407 | P30: 34823533 | Q30: 34823914 | R30: 34824091
A31: 2025-06 | B31: 7109165.4 | C31: 19384641 | D31: 27251917 | E31: 31317686 | F31: 33317236 | G31: 34257154 | H31: 34678580 | I31: 34891854 | J31: 34984492 | K31: 35029143 | L31: 35049244 | M31: 35058403 | N31: 35062087 | O31: 35064406 | P31: 35065232 | Q31: 35065618
A32: 2025-07 | B32: 7689729.9 | C32: 21159107 | D32: 28928727 | E32: 33034291 | F32: 35272666 | G32: 36283724 | H32: 36768109 | I32: 36993816 | J32: 37097363 | K32: 37146995 | L32: 37168083 | M32: 37177012 | N32: 37182571 | O32: 37184532 | P32: 37185412
A33: 2025-08 | B33: 7341787.8 | C33: 21254460 | D33: 30135216 | E33: 34275751 | F33: 36422259 | G33: 37506157 | H33: 37984205 | I33: 38230114 | J33: 38340532 | K33: 38389699 | L33: 38408714 | M33: 38421368 | N33: 38425798 | O33: 38427738
A34: 2025-09 | B34: 7776954.3 | C34: 20861280 | D34: 28713043 | E34: 33020729 | F34: 35059509 | G34: 36065496 | H34: 36535350 | I34: 36753376 | J34: 36855057 | K34: 36896191 | L34: 36922006 | M34: 36931673 | N34: 36935842
A35: 2025-10 | B35: 8028927.2 | C35: 22242338 | D35: 31053550 | E35: 35491283 | F35: 37616859 | G35: 38662421 | H35: 39172522 | I35: 39402692 | J35: 39495679 | K35: 39556984 | L35: 39578782 | M35: 39588728
A36: 2025-11 | B36: 8177124.7 | C36: 22905021 | D36: 31875227 | E36: 36601106 | F36: 38903696 | G36: 39980942 | H36: 40487624 | I36: 40696852 | J36: 40829604 | K36: 40876157 | L36: 40896755
A37: 2025-12 | B37: 9521967.4 | C37: 25856461 | D37: 35603369 | E37: 40924677 | F37: 43420429 | G37: 44702497 | H37: 45232148 | I37: 45570689 | J37: 45686782 | K37: 45740855
A38: 2026-01 | B38: 8209203.8 | C38: 22522462 | D38: 31246888 | E38: 35771094 | F38: 37953967 | G38: 38838330 | H38: 39440702 | I38: 39658267 | J38: 39761187
A39: 2026-02 | B39: 8227331.6 | C39: 22483085 | D39: 31110293 | E39: 35603114 | F39: 37569200 | G39: 38867098 | H39: 39349254 | I39: 39576995
A40: 2026-03 | B40: 8494284.2 | C40: 23493220 | D40: 32087299 | E40: 36291296 | F40: 39204995 | G40: 40224702 | H40: 40709158
A41: 2026-04 | B41: 8578777.2 | C41: 24360123 | D41: 32067572 | E41: 37559184 | F41: 39911942 | G41: 40983866
A42: 2026-05 | B42: 9174306.2 | C42: 22198341 | D42: 33108770 | E42: 37822199 | F42: 39984088
A43: 2026-06 | B43: 7215208.3 | C43: 23324385 | D43: 32294620 | E43: 36907577
A44: 2026-07 | B44: 8222373.5 | C44: 22791212 | D44: 31315628
A45: 2026-08 | B45: 9350822.1 | C45: 25559368
A46: 2026-09 | B46: 8949177.3

Sheet OP Ratios
A1: Incurred | B1: 0-1 | C1: 1-2 | D1: 2-3 | E1: 3-4 | F1: 4-5 | G1: 5-6 | H1: 6-7 | I1: 7-8 | J1: 8-9 | K1: 9-10 | L1: 10-11 | M1: 11-12 | N1: 12-13 | O1: 13-14 | P1: 14-15 | Q1: 15-16 | R1: 16-17 | S1: 17-18 | T1: 18-19 | U1: 19-20 | V1: 20-21 | W1: 21-22 | X1: 22-23 | Y1: 23-24 | Z1: 24-25 | AA1: 25-26 | AB1: 26-27 | AC1: 27-28 | AD1: 28-29 | AE1: 29-30 | AF1: 30-31 | AG1: 31-32 | AH1: 32-33 | AI1: 33-34 | AJ1: 34-35 | AK1: 35-36 | AL1: 36-37 | AM1: 37-38 | AN1: 38-39 | AO1: 39-40 | AP1: 40-41 | AQ1: 41-42 | AR1: 42-43 | AS1: 43-44
A2: 2023-01 | B2: =IF('OP Triangle'!B2>0,'OP Triangle'!C2/'OP Triangle'!B2,"") | C2: =IF('OP Triangle'!C2>0,'OP Triangle'!D2/'OP Triangle'!C2,"") | D2: =IF('OP Triangle'!D2>0,'OP Triangle'!E2/'OP Triangle'!D2,"") | E2: =IF('OP Triangle'!E2>0,'OP Triangle'!F2/'OP Triangle'!E2,"") | F2: =IF('OP Triangle'!F2>0,'OP Triangle'!G2/'OP Triangle'!F2,"") | G2: =IF('OP Triangle'!G2>0,'OP Triangle'!H2/'OP Triangle'!G2,"") | H2: =IF('OP Triangle'!H2>0,'OP Triangle'!I2/'OP Triangle'!H2,"") | I2: =IF('OP Triangle'!I2>0,'OP Triangle'!J2/'OP Triangle'!I2,"") | ... AS2: =IF('OP Triangle'!AS2>0,'OP Triangle'!AT2/'OP Triangle'!AS2,"")
A3: 2023-02 | B3: =IF('OP Triangle'!B3>0,'OP Triangle'!C3/'OP Triangle'!B3,"") | C3: =IF('OP Triangle'!C3>0,'OP Triangle'!D3/'OP Triangle'!C3,"") | D3: =IF('OP Triangle'!D3>0,'OP Triangle'!E3/'OP Triangle'!D3,"") | E3: =IF('OP Triangle'!E3>0,'OP Triangle'!F3/'OP Triangle'!E3,"") | F3: =IF('OP Triangle'!F3>0,'OP Triangle'!G3/'OP Triangle'!F3,"") | G3: =IF('OP Triangle'!G3>0,'OP Triangle'!H3/'OP Triangle'!G3,"") | H3: =IF('OP Triangle'!H3>0,'OP Triangle'!I3/'OP Triangle'!H3,"") | I3: =IF('OP Triangle'!I3>0,'OP Triangle'!J3/'OP Triangle'!I3,"") | ... AR3: =IF('OP Triangle'!AR3>0,'OP Triangle'!AS3/'OP Triangle'!AR3,"")
A4: 2023-03 | B4: =IF('OP Triangle'!B4>0,'OP Triangle'!C4/'OP Triangle'!B4,"") | C4: =IF('OP Triangle'!C4>0,'OP Triangle'!D4/'OP Triangle'!C4,"") | D4: =IF('OP Triangle'!D4>0,'OP Triangle'!E4/'OP Triangle'!D4,"") | E4: =IF('OP Triangle'!E4>0,'OP Triangle'!F4/'OP Triangle'!E4,"") | F4: =IF('OP Triangle'!F4>0,'OP Triangle'!G4/'OP Triangle'!F4,"") | G4: =IF('OP Triangle'!G4>0,'OP Triangle'!H4/'OP Triangle'!G4,"") | H4: =IF('OP Triangle'!H4>0,'OP Triangle'!I4/'OP Triangle'!H4,"") | I4: =IF('OP Triangle'!I4>0,'OP Triangle'!J4/'OP Triangle'!I4,"") | ... AQ4: =IF('OP Triangle'!AQ4>0,'OP Triangle'!AR4/'OP Triangle'!AQ4,"")
A5: 2023-04 | B5: =IF('OP Triangle'!B5>0,'OP Triangle'!C5/'OP Triangle'!B5,"") | C5: =IF('OP Triangle'!C5>0,'OP Triangle'!D5/'OP Triangle'!C5,"") | D5: =IF('OP Triangle'!D5>0,'OP Triangle'!E5/'OP Triangle'!D5,"") | E5: =IF('OP Triangle'!E5>0,'OP Triangle'!F5/'OP Triangle'!E5,"") | F5: =IF('OP Triangle'!F5>0,'OP Triangle'!G5/'OP Triangle'!F5,"") | G5: =IF('OP Triangle'!G5>0,'OP Triangle'!H5/'OP Triangle'!G5,"") | H5: =IF('OP Triangle'!H5>0,'OP Triangle'!I5/'OP Triangle'!H5,"") | I5: =IF('OP Triangle'!I5>0,'OP Triangle'!J5/'OP Triangle'!I5,"") | ... AP5: =IF('OP Triangle'!AP5>0,'OP Triangle'!AQ5/'OP Triangle'!AP5,"")
A6: 2023-05 | B6: =IF('OP Triangle'!B6>0,'OP Triangle'!C6/'OP Triangle'!B6,"") | C6: =IF('OP Triangle'!C6>0,'OP Triangle'!D6/'OP Triangle'!C6,"") | D6: =IF('OP Triangle'!D6>0,'OP Triangle'!E6/'OP Triangle'!D6,"") | E6: =IF('OP Triangle'!E6>0,'OP Triangle'!F6/'OP Triangle'!E6,"") | F6: =IF('OP Triangle'!F6>0,'OP Triangle'!G6/'OP Triangle'!F6,"") | G6: =IF('OP Triangle'!G6>0,'OP Triangle'!H6/'OP Triangle'!G6,"") | H6: =IF('OP Triangle'!H6>0,'OP Triangle'!I6/'OP Triangle'!H6,"") | I6: =IF('OP Triangle'!I6>0,'OP Triangle'!J6/'OP Triangle'!I6,"") | ... AO6: =IF('OP Triangle'!AO6>0,'OP Triangle'!AP6/'OP Triangle'!AO6,"")
A7: 2023-06 | B7: =IF('OP Triangle'!B7>0,'OP Triangle'!C7/'OP Triangle'!B7,"") | C7: =IF('OP Triangle'!C7>0,'OP Triangle'!D7/'OP Triangle'!C7,"") | D7: =IF('OP Triangle'!D7>0,'OP Triangle'!E7/'OP Triangle'!D7,"") | E7: =IF('OP Triangle'!E7>0,'OP Triangle'!F7/'OP Triangle'!E7,"") | F7: =IF('OP Triangle'!F7>0,'OP Triangle'!G7/'OP Triangle'!F7,"") | G7: =IF('OP Triangle'!G7>0,'OP Triangle'!H7/'OP Triangle'!G7,"") | H7: =IF('OP Triangle'!H7>0,'OP Triangle'!I7/'OP Triangle'!H7,"") | I7: =IF('OP Triangle'!I7>0,'OP Triangle'!J7/'OP Triangle'!I7,"") | ... AN7: =IF('OP Triangle'!AN7>0,'OP Triangle'!AO7/'OP Triangle'!AN7,"")
A8: 2023-07 | B8: =IF('OP Triangle'!B8>0,'OP Triangle'!C8/'OP Triangle'!B8,"") | C8: =IF('OP Triangle'!C8>0,'OP Triangle'!D8/'OP Triangle'!C8,"") | D8: =IF('OP Triangle'!D8>0,'OP Triangle'!E8/'OP Triangle'!D8,"") | E8: =IF('OP Triangle'!E8>0,'OP Triangle'!F8/'OP Triangle'!E8,"") | F8: =IF('OP Triangle'!F8>0,'OP Triangle'!G8/'OP Triangle'!F8,"") | G8: =IF('OP Triangle'!G8>0,'OP Triangle'!H8/'OP Triangle'!G8,"") | H8: =IF('OP Triangle'!H8>0,'OP Triangle'!I8/'OP Triangle'!H8,"") | I8: =IF('OP Triangle'!I8>0,'OP Triangle'!J8/'OP Triangle'!I8,"") | ... AM8: =IF('OP Triangle'!AM8>0,'OP Triangle'!AN8/'OP Triangle'!AM8,"")
A9: 2023-08 | B9: =IF('OP Triangle'!B9>0,'OP Triangle'!C9/'OP Triangle'!B9,"") | C9: =IF('OP Triangle'!C9>0,'OP Triangle'!D9/'OP Triangle'!C9,"") | D9: =IF('OP Triangle'!D9>0,'OP Triangle'!E9/'OP Triangle'!D9,"") | E9: =IF('OP Triangle'!E9>0,'OP Triangle'!F9/'OP Triangle'!E9,"") | F9: =IF('OP Triangle'!F9>0,'OP Triangle'!G9/'OP Triangle'!F9,"") | G9: =IF('OP Triangle'!G9>0,'OP Triangle'!H9/'OP Triangle'!G9,"") | H9: =IF('OP Triangle'!H9>0,'OP Triangle'!I9/'OP Triangle'!H9,"") | I9: =IF('OP Triangle'!I9>0,'OP Triangle'!J9/'OP Triangle'!I9,"") | ... AL9: =IF('OP Triangle'!AL9>0,'OP Triangle'!AM9/'OP Triangle'!AL9,"")
A10: 2023-09 | B10: =IF('OP Triangle'!B10>0,'OP Triangle'!C10/'OP Triangle'!B10,"") | C10: =IF('OP Triangle'!C10>0,'OP Triangle'!D10/'OP Triangle'!C10,"") | D10: =IF('OP Triangle'!D10>0,'OP Triangle'!E10/'OP Triangle'!D10,"") | E10: =IF('OP Triangle'!E10>0,'OP Triangle'!F10/'OP Triangle'!E10,"") | F10: =IF('OP Triangle'!F10>0,'OP Triangle'!G10/'OP Triangle'!F10,"") | G10: =IF('OP Triangle'!G10>0,'OP Triangle'!H10/'OP Triangle'!G10,"") | H10: =IF('OP Triangle'!H10>0,'OP Triangle'!I10/'OP Triangle'!H10,"") | I10: =IF('OP Triangle'!I10>0,'OP Triangle'!J10/'OP Triangle'!I10,"") | ... AK10: =IF('OP Triangle'!AK10>0,'OP Triangle'!AL10/'OP Triangle'!AK10,"")
A11: 2023-10 | B11: =IF('OP Triangle'!B11>0,'OP Triangle'!C11/'OP Triangle'!B11,"") | C11: =IF('OP Triangle'!C11>0,'OP Triangle'!D11/'OP Triangle'!C11,"") | D11: =IF('OP Triangle'!D11>0,'OP Triangle'!E11/'OP Triangle'!D11,"") | E11: =IF('OP Triangle'!E11>0,'OP Triangle'!F11/'OP Triangle'!E11,"") | F11: =IF('OP Triangle'!F11>0,'OP Triangle'!G11/'OP Triangle'!F11,"") | G11: =IF('OP Triangle'!G11>0,'OP Triangle'!H11/'OP Triangle'!G11,"") | H11: =IF('OP Triangle'!H11>0,'OP Triangle'!I11/'OP Triangle'!H11,"") | I11: =IF('OP Triangle'!I11>0,'OP Triangle'!J11/'OP Triangle'!I11,"") | ... AJ11: =IF('OP Triangle'!AJ11>0,'OP Triangle'!AK11/'OP Triangle'!AJ11,"")
A12: 2023-11 | B12: =IF('OP Triangle'!B12>0,'OP Triangle'!C12/'OP Triangle'!B12,"") | C12: =IF('OP Triangle'!C12>0,'OP Triangle'!D12/'OP Triangle'!C12,"") | D12: =IF('OP Triangle'!D12>0,'OP Triangle'!E12/'OP Triangle'!D12,"") | E12: =IF('OP Triangle'!E12>0,'OP Triangle'!F12/'OP Triangle'!E12,"") | F12: =IF('OP Triangle'!F12>0,'OP Triangle'!G12/'OP Triangle'!F12,"") | G12: =IF('OP Triangle'!G12>0,'OP Triangle'!H12/'OP Triangle'!G12,"") | H12: =IF('OP Triangle'!H12>0,'OP Triangle'!I12/'OP Triangle'!H12,"") | I12: =IF('OP Triangle'!I12>0,'OP Triangle'!J12/'OP Triangle'!I12,"") | ... AI12: =IF('OP Triangle'!AI12>0,'OP Triangle'!AJ12/'OP Triangle'!AI12,"")
A13: 2023-12 | B13: =IF('OP Triangle'!B13>0,'OP Triangle'!C13/'OP Triangle'!B13,"") | C13: =IF('OP Triangle'!C13>0,'OP Triangle'!D13/'OP Triangle'!C13,"") | D13: =IF('OP Triangle'!D13>0,'OP Triangle'!E13/'OP Triangle'!D13,"") | E13: =IF('OP Triangle'!E13>0,'OP Triangle'!F13/'OP Triangle'!E13,"") | F13: =IF('OP Triangle'!F13>0,'OP Triangle'!G13/'OP Triangle'!F13,"") | G13: =IF('OP Triangle'!G13>0,'OP Triangle'!H13/'OP Triangle'!G13,"") | H13: =IF('OP Triangle'!H13>0,'OP Triangle'!I13/'OP Triangle'!H13,"") | I13: =IF('OP Triangle'!I13>0,'OP Triangle'!J13/'OP Triangle'!I13,"") | ... AH13: =IF('OP Triangle'!AH13>0,'OP Triangle'!AI13/'OP Triangle'!AH13,"")
A14: 2024-01 | B14: =IF('OP Triangle'!B14>0,'OP Triangle'!C14/'OP Triangle'!B14,"") | C14: =IF('OP Triangle'!C14>0,'OP Triangle'!D14/'OP Triangle'!C14,"") | D14: =IF('OP Triangle'!D14>0,'OP Triangle'!E14/'OP Triangle'!D14,"") | E14: =IF('OP Triangle'!E14>0,'OP Triangle'!F14/'OP Triangle'!E14,"") | F14: =IF('OP Triangle'!F14>0,'OP Triangle'!G14/'OP Triangle'!F14,"") | G14: =IF('OP Triangle'!G14>0,'OP Triangle'!H14/'OP Triangle'!G14,"") | H14: =IF('OP Triangle'!H14>0,'OP Triangle'!I14/'OP Triangle'!H14,"") | I14: =IF('OP Triangle'!I14>0,'OP Triangle'!J14/'OP Triangle'!I14,"") | ... AG14: =IF('OP Triangle'!AG14>0,'OP Triangle'!AH14/'OP Triangle'!AG14,"")
A15: 2024-02 | B15: =IF('OP Triangle'!B15>0,'OP Triangle'!C15/'OP Triangle'!B15,"") | C15: =IF('OP Triangle'!C15>0,'OP Triangle'!D15/'OP Triangle'!C15,"") | D15: =IF('OP Triangle'!D15>0,'OP Triangle'!E15/'OP Triangle'!D15,"") | E15: =IF('OP Triangle'!E15>0,'OP Triangle'!F15/'OP Triangle'!E15,"") | F15: =IF('OP Triangle'!F15>0,'OP Triangle'!G15/'OP Triangle'!F15,"") | G15: =IF('OP Triangle'!G15>0,'OP Triangle'!H15/'OP Triangle'!G15,"") | H15: =IF('OP Triangle'!H15>0,'OP Triangle'!I15/'OP Triangle'!H15,"") | I15: =IF('OP Triangle'!I15>0,'OP Triangle'!J15/'OP Triangle'!I15,"") | ... AF15: =IF('OP Triangle'!AF15>0,'OP Triangle'!AG15/'OP Triangle'!AF15,"")
A16: 2024-03 | B16: =IF('OP Triangle'!B16>0,'OP Triangle'!C16/'OP Triangle'!B16,"") | C16: =IF('OP Triangle'!C16>0,'OP Triangle'!D16/'OP Triangle'!C16,"") | D16: =IF('OP Triangle'!D16>0,'OP Triangle'!E16/'OP Triangle'!D16,"") | E16: =IF('OP Triangle'!E16>0,'OP Triangle'!F16/'OP Triangle'!E16,"") | F16: =IF('OP Triangle'!F16>0,'OP Triangle'!G16/'OP Triangle'!F16,"") | G16: =IF('OP Triangle'!G16>0,'OP Triangle'!H16/'OP Triangle'!G16,"") | H16: =IF('OP Triangle'!H16>0,'OP Triangle'!I16/'OP Triangle'!H16,"") | I16: =IF('OP Triangle'!I16>0,'OP Triangle'!J16/'OP Triangle'!I16,"") | ... AE16: =IF('OP Triangle'!AE16>0,'OP Triangle'!AF16/'OP Triangle'!AE16,"")
A17: 2024-04 | B17: =IF('OP Triangle'!B17>0,'OP Triangle'!C17/'OP Triangle'!B17,"") | C17: =IF('OP Triangle'!C17>0,'OP Triangle'!D17/'OP Triangle'!C17,"") | D17: =IF('OP Triangle'!D17>0,'OP Triangle'!E17/'OP Triangle'!D17,"") | E17: =IF('OP Triangle'!E17>0,'OP Triangle'!F17/'OP Triangle'!E17,"") | F17: =IF('OP Triangle'!F17>0,'OP Triangle'!G17/'OP Triangle'!F17,"") | G17: =IF('OP Triangle'!G17>0,'OP Triangle'!H17/'OP Triangle'!G17,"") | H17: =IF('OP Triangle'!H17>0,'OP Triangle'!I17/'OP Triangle'!H17,"") | I17: =IF('OP Triangle'!I17>0,'OP Triangle'!J17/'OP Triangle'!I17,"") | ... AD17: =IF('OP Triangle'!AD17>0,'OP Triangle'!AE17/'OP Triangle'!AD17,"")
A18: 2024-05 | B18: =IF('OP Triangle'!B18>0,'OP Triangle'!C18/'OP Triangle'!B18,"") | C18: =IF('OP Triangle'!C18>0,'OP Triangle'!D18/'OP Triangle'!C18,"") | D18: =IF('OP Triangle'!D18>0,'OP Triangle'!E18/'OP Triangle'!D18,"") | E18: =IF('OP Triangle'!E18>0,'OP Triangle'!F18/'OP Triangle'!E18,"") | F18: =IF('OP Triangle'!F18>0,'OP Triangle'!G18/'OP Triangle'!F18,"") | G18: =IF('OP Triangle'!G18>0,'OP Triangle'!H18/'OP Triangle'!G18,"") | H18: =IF('OP Triangle'!H18>0,'OP Triangle'!I18/'OP Triangle'!H18,"") | I18: =IF('OP Triangle'!I18>0,'OP Triangle'!J18/'OP Triangle'!I18,"") | ... AC18: =IF('OP Triangle'!AC18>0,'OP Triangle'!AD18/'OP Triangle'!AC18,"")
A19: 2024-06 | B19: =IF('OP Triangle'!B19>0,'OP Triangle'!C19/'OP Triangle'!B19,"") | C19: =IF('OP Triangle'!C19>0,'OP Triangle'!D19/'OP Triangle'!C19,"") | D19: =IF('OP Triangle'!D19>0,'OP Triangle'!E19/'OP Triangle'!D19,"") | E19: =IF('OP Triangle'!E19>0,'OP Triangle'!F19/'OP Triangle'!E19,"") | F19: =IF('OP Triangle'!F19>0,'OP Triangle'!G19/'OP Triangle'!F19,"") | G19: =IF('OP Triangle'!G19>0,'OP Triangle'!H19/'OP Triangle'!G19,"") | H19: =IF('OP Triangle'!H19>0,'OP Triangle'!I19/'OP Triangle'!H19,"") | I19: =IF('OP Triangle'!I19>0,'OP Triangle'!J19/'OP Triangle'!I19,"") | ... AB19: =IF('OP Triangle'!AB19>0,'OP Triangle'!AC19/'OP Triangle'!AB19,"")
A20: 2024-07 | B20: =IF('OP Triangle'!B20>0,'OP Triangle'!C20/'OP Triangle'!B20,"") | C20: =IF('OP Triangle'!C20>0,'OP Triangle'!D20/'OP Triangle'!C20,"") | D20: =IF('OP Triangle'!D20>0,'OP Triangle'!E20/'OP Triangle'!D20,"") | E20: =IF('OP Triangle'!E20>0,'OP Triangle'!F20/'OP Triangle'!E20,"") | F20: =IF('OP Triangle'!F20>0,'OP Triangle'!G20/'OP Triangle'!F20,"") | G20: =IF('OP Triangle'!G20>0,'OP Triangle'!H20/'OP Triangle'!G20,"") | H20: =IF('OP Triangle'!H20>0,'OP Triangle'!I20/'OP Triangle'!H20,"") | I20: =IF('OP Triangle'!I20>0,'OP Triangle'!J20/'OP Triangle'!I20,"") | ... AA20: =IF('OP Triangle'!AA20>0,'OP Triangle'!AB20/'OP Triangle'!AA20,"")
A21: 2024-08 | B21: =IF('OP Triangle'!B21>0,'OP Triangle'!C21/'OP Triangle'!B21,"") | C21: =IF('OP Triangle'!C21>0,'OP Triangle'!D21/'OP Triangle'!C21,"") | D21: =IF('OP Triangle'!D21>0,'OP Triangle'!E21/'OP Triangle'!D21,"") | E21: =IF('OP Triangle'!E21>0,'OP Triangle'!F21/'OP Triangle'!E21,"") | F21: =IF('OP Triangle'!F21>0,'OP Triangle'!G21/'OP Triangle'!F21,"") | G21: =IF('OP Triangle'!G21>0,'OP Triangle'!H21/'OP Triangle'!G21,"") | H21: =IF('OP Triangle'!H21>0,'OP Triangle'!I21/'OP Triangle'!H21,"") | I21: =IF('OP Triangle'!I21>0,'OP Triangle'!J21/'OP Triangle'!I21,"") | ... Z21: =IF('OP Triangle'!Z21>0,'OP Triangle'!AA21/'OP Triangle'!Z21,"")
A22: 2024-09 | B22: =IF('OP Triangle'!B22>0,'OP Triangle'!C22/'OP Triangle'!B22,"") | C22: =IF('OP Triangle'!C22>0,'OP Triangle'!D22/'OP Triangle'!C22,"") | D22: =IF('OP Triangle'!D22>0,'OP Triangle'!E22/'OP Triangle'!D22,"") | E22: =IF('OP Triangle'!E22>0,'OP Triangle'!F22/'OP Triangle'!E22,"") | F22: =IF('OP Triangle'!F22>0,'OP Triangle'!G22/'OP Triangle'!F22,"") | G22: =IF('OP Triangle'!G22>0,'OP Triangle'!H22/'OP Triangle'!G22,"") | H22: =IF('OP Triangle'!H22>0,'OP Triangle'!I22/'OP Triangle'!H22,"") | I22: =IF('OP Triangle'!I22>0,'OP Triangle'!J22/'OP Triangle'!I22,"") | ... Y22: =IF('OP Triangle'!Y22>0,'OP Triangle'!Z22/'OP Triangle'!Y22,"")
A23: 2024-10 | B23: =IF('OP Triangle'!B23>0,'OP Triangle'!C23/'OP Triangle'!B23,"") | C23: =IF('OP Triangle'!C23>0,'OP Triangle'!D23/'OP Triangle'!C23,"") | D23: =IF('OP Triangle'!D23>0,'OP Triangle'!E23/'OP Triangle'!D23,"") | E23: =IF('OP Triangle'!E23>0,'OP Triangle'!F23/'OP Triangle'!E23,"") | F23: =IF('OP Triangle'!F23>0,'OP Triangle'!G23/'OP Triangle'!F23,"") | G23: =IF('OP Triangle'!G23>0,'OP Triangle'!H23/'OP Triangle'!G23,"") | H23: =IF('OP Triangle'!H23>0,'OP Triangle'!I23/'OP Triangle'!H23,"") | I23: =IF('OP Triangle'!I23>0,'OP Triangle'!J23/'OP Triangle'!I23,"") | ... X23: =IF('OP Triangle'!X23>0,'OP Triangle'!Y23/'OP Triangle'!X23,"")
A24: 2024-11 | B24: =IF('OP Triangle'!B24>0,'OP Triangle'!C24/'OP Triangle'!B24,"") | C24: =IF('OP Triangle'!C24>0,'OP Triangle'!D24/'OP Triangle'!C24,"") | D24: =IF('OP Triangle'!D24>0,'OP Triangle'!E24/'OP Triangle'!D24,"") | E24: =IF('OP Triangle'!E24>0,'OP Triangle'!F24/'OP Triangle'!E24,"") | F24: =IF('OP Triangle'!F24>0,'OP Triangle'!G24/'OP Triangle'!F24,"") | G24: =IF('OP Triangle'!G24>0,'OP Triangle'!H24/'OP Triangle'!G24,"") | H24: =IF('OP Triangle'!H24>0,'OP Triangle'!I24/'OP Triangle'!H24,"") | I24: =IF('OP Triangle'!I24>0,'OP Triangle'!J24/'OP Triangle'!I24,"") | ... W24: =IF('OP Triangle'!W24>0,'OP Triangle'!X24/'OP Triangle'!W24,"")
A25: 2024-12 | B25: =IF('OP Triangle'!B25>0,'OP Triangle'!C25/'OP Triangle'!B25,"") | C25: =IF('OP Triangle'!C25>0,'OP Triangle'!D25/'OP Triangle'!C25,"") | D25: =IF('OP Triangle'!D25>0,'OP Triangle'!E25/'OP Triangle'!D25,"") | E25: =IF('OP Triangle'!E25>0,'OP Triangle'!F25/'OP Triangle'!E25,"") | F25: =IF('OP Triangle'!F25>0,'OP Triangle'!G25/'OP Triangle'!F25,"") | G25: =IF('OP Triangle'!G25>0,'OP Triangle'!H25/'OP Triangle'!G25,"") | H25: =IF('OP Triangle'!H25>0,'OP Triangle'!I25/'OP Triangle'!H25,"") | I25: =IF('OP Triangle'!I25>0,'OP Triangle'!J25/'OP Triangle'!I25,"") | ... V25: =IF('OP Triangle'!V25>0,'OP Triangle'!W25/'OP Triangle'!V25,"")
A26: 2025-01 | B26: =IF('OP Triangle'!B26>0,'OP Triangle'!C26/'OP Triangle'!B26,"") | C26: =IF('OP Triangle'!C26>0,'OP Triangle'!D26/'OP Triangle'!C26,"") | D26: =IF('OP Triangle'!D26>0,'OP Triangle'!E26/'OP Triangle'!D26,"") | E26: =IF('OP Triangle'!E26>0,'OP Triangle'!F26/'OP Triangle'!E26,"") | F26: =IF('OP Triangle'!F26>0,'OP Triangle'!G26/'OP Triangle'!F26,"") | G26: =IF('OP Triangle'!G26>0,'OP Triangle'!H26/'OP Triangle'!G26,"") | H26: =IF('OP Triangle'!H26>0,'OP Triangle'!I26/'OP Triangle'!H26,"") | I26: =IF('OP Triangle'!I26>0,'OP Triangle'!J26/'OP Triangle'!I26,"") | ... U26: =IF('OP Triangle'!U26>0,'OP Triangle'!V26/'OP Triangle'!U26,"")
A27: 2025-02 | B27: =IF('OP Triangle'!B27>0,'OP Triangle'!C27/'OP Triangle'!B27,"") | C27: =IF('OP Triangle'!C27>0,'OP Triangle'!D27/'OP Triangle'!C27,"") | D27: =IF('OP Triangle'!D27>0,'OP Triangle'!E27/'OP Triangle'!D27,"") | E27: =IF('OP Triangle'!E27>0,'OP Triangle'!F27/'OP Triangle'!E27,"") | F27: =IF('OP Triangle'!F27>0,'OP Triangle'!G27/'OP Triangle'!F27,"") | G27: =IF('OP Triangle'!G27>0,'OP Triangle'!H27/'OP Triangle'!G27,"") | H27: =IF('OP Triangle'!H27>0,'OP Triangle'!I27/'OP Triangle'!H27,"") | I27: =IF('OP Triangle'!I27>0,'OP Triangle'!J27/'OP Triangle'!I27,"") | ... T27: =IF('OP Triangle'!T27>0,'OP Triangle'!U27/'OP Triangle'!T27,"")
A28: 2025-03 | B28: =IF('OP Triangle'!B28>0,'OP Triangle'!C28/'OP Triangle'!B28,"") | C28: =IF('OP Triangle'!C28>0,'OP Triangle'!D28/'OP Triangle'!C28,"") | D28: =IF('OP Triangle'!D28>0,'OP Triangle'!E28/'OP Triangle'!D28,"") | E28: =IF('OP Triangle'!E28>0,'OP Triangle'!F28/'OP Triangle'!E28,"") | F28: =IF('OP Triangle'!F28>0,'OP Triangle'!G28/'OP Triangle'!F28,"") | G28: =IF('OP Triangle'!G28>0,'OP Triangle'!H28/'OP Triangle'!G28,"") | H28: =IF('OP Triangle'!H28>0,'OP Triangle'!I28/'OP Triangle'!H28,"") | I28: =IF('OP Triangle'!I28>0,'OP Triangle'!J28/'OP Triangle'!I28,"") | ... S28: =IF('OP Triangle'!S28>0,'OP Triangle'!T28/'OP Triangle'!S28,"")
A29: 2025-04 | B29: =IF('OP Triangle'!B29>0,'OP Triangle'!C29/'OP Triangle'!B29,"") | C29: =IF('OP Triangle'!C29>0,'OP Triangle'!D29/'OP Triangle'!C29,"") | D29: =IF('OP Triangle'!D29>0,'OP Triangle'!E29/'OP Triangle'!D29,"") | E29: =IF('OP Triangle'!E29>0,'OP Triangle'!F29/'OP Triangle'!E29,"") | F29: =IF('OP Triangle'!F29>0,'OP Triangle'!G29/'OP Triangle'!F29,"") | G29: =IF('OP Triangle'!G29>0,'OP Triangle'!H29/'OP Triangle'!G29,"") | H29: =IF('OP Triangle'!H29>0,'OP Triangle'!I29/'OP Triangle'!H29,"") | I29: =IF('OP Triangle'!I29>0,'OP Triangle'!J29/'OP Triangle'!I29,"") | ... R29: =IF('OP Triangle'!R29>0,'OP Triangle'!S29/'OP Triangle'!R29,"")
A30: 2025-05 | B30: =IF('OP Triangle'!B30>0,'OP Triangle'!C30/'OP Triangle'!B30,"") | C30: =IF('OP Triangle'!C30>0,'OP Triangle'!D30/'OP Triangle'!C30,"") | D30: =IF('OP Triangle'!D30>0,'OP Triangle'!E30/'OP Triangle'!D30,"") | E30: =IF('OP Triangle'!E30>0,'OP Triangle'!F30/'OP Triangle'!E30,"") | F30: =IF('OP Triangle'!F30>0,'OP Triangle'!G30/'OP Triangle'!F30,"") | G30: =IF('OP Triangle'!G30>0,'OP Triangle'!H30/'OP Triangle'!G30,"") | H30: =IF('OP Triangle'!H30>0,'OP Triangle'!I30/'OP Triangle'!H30,"") | I30: =IF('OP Triangle'!I30>0,'OP Triangle'!J30/'OP Triangle'!I30,"") | ... Q30: =IF('OP Triangle'!Q30>0,'OP Triangle'!R30/'OP Triangle'!Q30,"")
A31: 2025-06 | B31: =IF('OP Triangle'!B31>0,'OP Triangle'!C31/'OP Triangle'!B31,"") | C31: =IF('OP Triangle'!C31>0,'OP Triangle'!D31/'OP Triangle'!C31,"") | D31: =IF('OP Triangle'!D31>0,'OP Triangle'!E31/'OP Triangle'!D31,"") | E31: =IF('OP Triangle'!E31>0,'OP Triangle'!F31/'OP Triangle'!E31,"") | F31: =IF('OP Triangle'!F31>0,'OP Triangle'!G31/'OP Triangle'!F31,"") | G31: =IF('OP Triangle'!G31>0,'OP Triangle'!H31/'OP Triangle'!G31,"") | H31: =IF('OP Triangle'!H31>0,'OP Triangle'!I31/'OP Triangle'!H31,"") | I31: =IF('OP Triangle'!I31>0,'OP Triangle'!J31/'OP Triangle'!I31,"") | ... P31: =IF('OP Triangle'!P31>0,'OP Triangle'!Q31/'OP Triangle'!P31,"")
A32: 2025-07 | B32: =IF('OP Triangle'!B32>0,'OP Triangle'!C32/'OP Triangle'!B32,"") | C32: =IF('OP Triangle'!C32>0,'OP Triangle'!D32/'OP Triangle'!C32,"") | D32: =IF('OP Triangle'!D32>0,'OP Triangle'!E32/'OP Triangle'!D32,"") | E32: =IF('OP Triangle'!E32>0,'OP Triangle'!F32/'OP Triangle'!E32,"") | F32: =IF('OP Triangle'!F32>0,'OP Triangle'!G32/'OP Triangle'!F32,"") | G32: =IF('OP Triangle'!G32>0,'OP Triangle'!H32/'OP Triangle'!G32,"") | H32: =IF('OP Triangle'!H32>0,'OP Triangle'!I32/'OP Triangle'!H32,"") | I32: =IF('OP Triangle'!I32>0,'OP Triangle'!J32/'OP Triangle'!I32,"") | ... O32: =IF('OP Triangle'!O32>0,'OP Triangle'!P32/'OP Triangle'!O32,"")
A33: 2025-08 | B33: =IF('OP Triangle'!B33>0,'OP Triangle'!C33/'OP Triangle'!B33,"") | C33: =IF('OP Triangle'!C33>0,'OP Triangle'!D33/'OP Triangle'!C33,"") | D33: =IF('OP Triangle'!D33>0,'OP Triangle'!E33/'OP Triangle'!D33,"") | E33: =IF('OP Triangle'!E33>0,'OP Triangle'!F33/'OP Triangle'!E33,"") | F33: =IF('OP Triangle'!F33>0,'OP Triangle'!G33/'OP Triangle'!F33,"") | G33: =IF('OP Triangle'!G33>0,'OP Triangle'!H33/'OP Triangle'!G33,"") | H33: =IF('OP Triangle'!H33>0,'OP Triangle'!I33/'OP Triangle'!H33,"") | I33: =IF('OP Triangle'!I33>0,'OP Triangle'!J33/'OP Triangle'!I33,"") | ... N33: =IF('OP Triangle'!N33>0,'OP Triangle'!O33/'OP Triangle'!N33,"")
A34: 2025-09 | B34: =IF('OP Triangle'!B34>0,'OP Triangle'!C34/'OP Triangle'!B34,"") | C34: =IF('OP Triangle'!C34>0,'OP Triangle'!D34/'OP Triangle'!C34,"") | D34: =IF('OP Triangle'!D34>0,'OP Triangle'!E34/'OP Triangle'!D34,"") | E34: =IF('OP Triangle'!E34>0,'OP Triangle'!F34/'OP Triangle'!E34,"") | F34: =IF('OP Triangle'!F34>0,'OP Triangle'!G34/'OP Triangle'!F34,"") | G34: =IF('OP Triangle'!G34>0,'OP Triangle'!H34/'OP Triangle'!G34,"") | H34: =IF('OP Triangle'!H34>0,'OP Triangle'!I34/'OP Triangle'!H34,"") | I34: =IF('OP Triangle'!I34>0,'OP Triangle'!J34/'OP Triangle'!I34,"") | ... M34: =IF('OP Triangle'!M34>0,'OP Triangle'!N34/'OP Triangle'!M34,"")
A35: 2025-10 | B35: =IF('OP Triangle'!B35>0,'OP Triangle'!C35/'OP Triangle'!B35,"") | C35: =IF('OP Triangle'!C35>0,'OP Triangle'!D35/'OP Triangle'!C35,"") | D35: =IF('OP Triangle'!D35>0,'OP Triangle'!E35/'OP Triangle'!D35,"") | E35: =IF('OP Triangle'!E35>0,'OP Triangle'!F35/'OP Triangle'!E35,"") | F35: =IF('OP Triangle'!F35>0,'OP Triangle'!G35/'OP Triangle'!F35,"") | G35: =IF('OP Triangle'!G35>0,'OP Triangle'!H35/'OP Triangle'!G35,"") | H35: =IF('OP Triangle'!H35>0,'OP Triangle'!I35/'OP Triangle'!H35,"") | I35: =IF('OP Triangle'!I35>0,'OP Triangle'!J35/'OP Triangle'!I35,"") | ... L35: =IF('OP Triangle'!L35>0,'OP Triangle'!M35/'OP Triangle'!L35,"")
A36: 2025-11 | B36: =IF('OP Triangle'!B36>0,'OP Triangle'!C36/'OP Triangle'!B36,"") | C36: =IF('OP Triangle'!C36>0,'OP Triangle'!D36/'OP Triangle'!C36,"") | D36: =IF('OP Triangle'!D36>0,'OP Triangle'!E36/'OP Triangle'!D36,"") | E36: =IF('OP Triangle'!E36>0,'OP Triangle'!F36/'OP Triangle'!E36,"") | F36: =IF('OP Triangle'!F36>0,'OP Triangle'!G36/'OP Triangle'!F36,"") | G36: =IF('OP Triangle'!G36>0,'OP Triangle'!H36/'OP Triangle'!G36,"") | H36: =IF('OP Triangle'!H36>0,'OP Triangle'!I36/'OP Triangle'!H36,"") | I36: =IF('OP Triangle'!I36>0,'OP Triangle'!J36/'OP Triangle'!I36,"") | ... K36: =IF('OP Triangle'!K36>0,'OP Triangle'!L36/'OP Triangle'!K36,"")
A37: 2025-12 | B37: =IF('OP Triangle'!B37>0,'OP Triangle'!C37/'OP Triangle'!B37,"") | C37: =IF('OP Triangle'!C37>0,'OP Triangle'!D37/'OP Triangle'!C37,"") | D37: =IF('OP Triangle'!D37>0,'OP Triangle'!E37/'OP Triangle'!D37,"") | E37: =IF('OP Triangle'!E37>0,'OP Triangle'!F37/'OP Triangle'!E37,"") | F37: =IF('OP Triangle'!F37>0,'OP Triangle'!G37/'OP Triangle'!F37,"") | G37: =IF('OP Triangle'!G37>0,'OP Triangle'!H37/'OP Triangle'!G37,"") | H37: =IF('OP Triangle'!H37>0,'OP Triangle'!I37/'OP Triangle'!H37,"") | I37: =IF('OP Triangle'!I37>0,'OP Triangle'!J37/'OP Triangle'!I37,"") | J37: =IF('OP Triangle'!J37>0,'OP Triangle'!K37/'OP Triangle'!J37,"")
A38: 2026-01 | B38: =IF('OP Triangle'!B38>0,'OP Triangle'!C38/'OP Triangle'!B38,"") | C38: =IF('OP Triangle'!C38>0,'OP Triangle'!D38/'OP Triangle'!C38,"") | D38: =IF('OP Triangle'!D38>0,'OP Triangle'!E38/'OP Triangle'!D38,"") | E38: =IF('OP Triangle'!E38>0,'OP Triangle'!F38/'OP Triangle'!E38,"") | F38: =IF('OP Triangle'!F38>0,'OP Triangle'!G38/'OP Triangle'!F38,"") | G38: =IF('OP Triangle'!G38>0,'OP Triangle'!H38/'OP Triangle'!G38,"") | H38: =IF('OP Triangle'!H38>0,'OP Triangle'!I38/'OP Triangle'!H38,"") | I38: =IF('OP Triangle'!I38>0,'OP Triangle'!J38/'OP Triangle'!I38,"")
A39: 2026-02 | B39: =IF('OP Triangle'!B39>0,'OP Triangle'!C39/'OP Triangle'!B39,"") | C39: =IF('OP Triangle'!C39>0,'OP Triangle'!D39/'OP Triangle'!C39,"") | D39: =IF('OP Triangle'!D39>0,'OP Triangle'!E39/'OP Triangle'!D39,"") | E39: =IF('OP Triangle'!E39>0,'OP Triangle'!F39/'OP Triangle'!E39,"") | F39: =IF('OP Triangle'!F39>0,'OP Triangle'!G39/'OP Triangle'!F39,"") | G39: =IF('OP Triangle'!G39>0,'OP Triangle'!H39/'OP Triangle'!G39,"") | H39: =IF('OP Triangle'!H39>0,'OP Triangle'!I39/'OP Triangle'!H39,"")
A40: 2026-03 | B40: =IF('OP Triangle'!B40>0,'OP Triangle'!C40/'OP Triangle'!B40,"") | C40: =IF('OP Triangle'!C40>0,'OP Triangle'!D40/'OP Triangle'!C40,"") | D40: =IF('OP Triangle'!D40>0,'OP Triangle'!E40/'OP Triangle'!D40,"") | E40: =IF('OP Triangle'!E40>0,'OP Triangle'!F40/'OP Triangle'!E40,"") | F40: =IF('OP Triangle'!F40>0,'OP Triangle'!G40/'OP Triangle'!F40,"") | G40: =IF('OP Triangle'!G40>0,'OP Triangle'!H40/'OP Triangle'!G40,"")
A41: 2026-04 | B41: =IF('OP Triangle'!B41>0,'OP Triangle'!C41/'OP Triangle'!B41,"") | C41: =IF('OP Triangle'!C41>0,'OP Triangle'!D41/'OP Triangle'!C41,"") | D41: =IF('OP Triangle'!D41>0,'OP Triangle'!E41/'OP Triangle'!D41,"") | E41: =IF('OP Triangle'!E41>0,'OP Triangle'!F41/'OP Triangle'!E41,"") | F41: =IF('OP Triangle'!F41>0,'OP Triangle'!G41/'OP Triangle'!F41,"")
A42: 2026-05 | B42: =IF('OP Triangle'!B42>0,'OP Triangle'!C42/'OP Triangle'!B42,"") | C42: =IF('OP Triangle'!C42>0,'OP Triangle'!D42/'OP Triangle'!C42,"") | D42: =IF('OP Triangle'!D42>0,'OP Triangle'!E42/'OP Triangle'!D42,"") | E42: =IF('OP Triangle'!E42>0,'OP Triangle'!F42/'OP Triangle'!E42,"")
A43: 2026-06 | B43: =IF('OP Triangle'!B43>0,'OP Triangle'!C43/'OP Triangle'!B43,"") | C43: =IF('OP Triangle'!C43>0,'OP Triangle'!D43/'OP Triangle'!C43,"") | D43: =IF('OP Triangle'!D43>0,'OP Triangle'!E43/'OP Triangle'!D43,"")
A44: 2026-07 | B44: =IF('OP Triangle'!B44>0,'OP Triangle'!C44/'OP Triangle'!B44,"") | C44: =IF('OP Triangle'!C44>0,'OP Triangle'!D44/'OP Triangle'!C44,"")
A45: 2026-08 | B45: =IF('OP Triangle'!B45>0,'OP Triangle'!C45/'OP Triangle'!B45,"")
A46: 2026-09

Sheet OP Factors
A1: Lag | B1: 6-mo avg ex hi/lo | C1: Override | D1: Selected link ratio | E1: Completion factor | F1: Months used
A2: 0 | B2: =(SUM('OP Ratios'!B38,'OP Ratios'!B39,'OP Ratios'!B40,'OP Ratios'!B41,'OP Ratios'!B44,'OP Ratios'!B45)-MAX('OP Ratios'!B38,'OP Ratios'!B39,'OP Ratios'!B40,'OP Ratios'!B41,'OP Ratios'!B44,'OP Ratios'!B45)-MIN('OP Ratios'!B38,'OP Ratios'!B39,'OP Ratios'!B40,'OP Ratios'!B41,'OP Ratios'!B44,'OP Ratios'!B45))/(COUNT('OP Ratios'!B38,'OP Ratios'!B39,'OP Ratios'!B40,'OP Ratios'!B41,'OP Ratios'!B44,'OP Ratios'!B45)-2) | D2: =IF(ISNUMBER(C2),C2,B2) | E2: =1/PRODUCT(D2:D46) | F2: 2026-01, 2026-02, 2026-03, 2026-04, 2026-07, 2026-08
A3: 1 | B3: =(SUM('OP Ratios'!C37,'OP Ratios'!C38,'OP Ratios'!C39,'OP Ratios'!C40,'OP Ratios'!C43,'OP Ratios'!C44)-MAX('OP Ratios'!C37,'OP Ratios'!C38,'OP Ratios'!C39,'OP Ratios'!C40,'OP Ratios'!C43,'OP Ratios'!C44)-MIN('OP Ratios'!C37,'OP Ratios'!C38,'OP Ratios'!C39,'OP Ratios'!C40,'OP Ratios'!C43,'OP Ratios'!C44))/(COUNT('OP Ratios'!C37,'OP Ratios'!C38,'OP Ratios'!C39,'OP Ratios'!C40,'OP Ratios'!C43,'OP Ratios'!C44)-2) | D3: =IF(ISNUMBER(C3),C3,B3) | E3: =1/PRODUCT(D3:D46) | F3: 2025-12, 2026-01, 2026-02, 2026-03, 2026-06, 2026-07
A4: 2 | B4: =(SUM('OP Ratios'!D36,'OP Ratios'!D37,'OP Ratios'!D38,'OP Ratios'!D39,'OP Ratios'!D42,'OP Ratios'!D43)-MAX('OP Ratios'!D36,'OP Ratios'!D37,'OP Ratios'!D38,'OP Ratios'!D39,'OP Ratios'!D42,'OP Ratios'!D43)-MIN('OP Ratios'!D36,'OP Ratios'!D37,'OP Ratios'!D38,'OP Ratios'!D39,'OP Ratios'!D42,'OP Ratios'!D43))/(COUNT('OP Ratios'!D36,'OP Ratios'!D37,'OP Ratios'!D38,'OP Ratios'!D39,'OP Ratios'!D42,'OP Ratios'!D43)-2) | D4: =IF(ISNUMBER(C4),C4,B4) | E4: =1/PRODUCT(D4:D46) | F4: 2025-11, 2025-12, 2026-01, 2026-02, 2026-05, 2026-06
A5: 3 | B5: =(SUM('OP Ratios'!E35,'OP Ratios'!E36,'OP Ratios'!E37,'OP Ratios'!E38,'OP Ratios'!E41,'OP Ratios'!E42)-MAX('OP Ratios'!E35,'OP Ratios'!E36,'OP Ratios'!E37,'OP Ratios'!E38,'OP Ratios'!E41,'OP Ratios'!E42)-MIN('OP Ratios'!E35,'OP Ratios'!E36,'OP Ratios'!E37,'OP Ratios'!E38,'OP Ratios'!E41,'OP Ratios'!E42))/(COUNT('OP Ratios'!E35,'OP Ratios'!E36,'OP Ratios'!E37,'OP Ratios'!E38,'OP Ratios'!E41,'OP Ratios'!E42)-2) | D5: =IF(ISNUMBER(C5),C5,B5) | E5: =1/PRODUCT(D5:D46) | F5: 2025-10, 2025-11, 2025-12, 2026-01, 2026-04, 2026-05
A6: 4 | B6: =(SUM('OP Ratios'!F34,'OP Ratios'!F35,'OP Ratios'!F36,'OP Ratios'!F37,'OP Ratios'!F40,'OP Ratios'!F41)-MAX('OP Ratios'!F34,'OP Ratios'!F35,'OP Ratios'!F36,'OP Ratios'!F37,'OP Ratios'!F40,'OP Ratios'!F41)-MIN('OP Ratios'!F34,'OP Ratios'!F35,'OP Ratios'!F36,'OP Ratios'!F37,'OP Ratios'!F40,'OP Ratios'!F41))/(COUNT('OP Ratios'!F34,'OP Ratios'!F35,'OP Ratios'!F36,'OP Ratios'!F37,'OP Ratios'!F40,'OP Ratios'!F41)-2) | D6: =IF(ISNUMBER(C6),C6,B6) | E6: =1/PRODUCT(D6:D46) | F6: 2025-09, 2025-10, 2025-11, 2025-12, 2026-03, 2026-04
A7: 5 | B7: =(SUM('OP Ratios'!G33,'OP Ratios'!G34,'OP Ratios'!G35,'OP Ratios'!G36,'OP Ratios'!G39,'OP Ratios'!G40)-MAX('OP Ratios'!G33,'OP Ratios'!G34,'OP Ratios'!G35,'OP Ratios'!G36,'OP Ratios'!G39,'OP Ratios'!G40)-MIN('OP Ratios'!G33,'OP Ratios'!G34,'OP Ratios'!G35,'OP Ratios'!G36,'OP Ratios'!G39,'OP Ratios'!G40))/(COUNT('OP Ratios'!G33,'OP Ratios'!G34,'OP Ratios'!G35,'OP Ratios'!G36,'OP Ratios'!G39,'OP Ratios'!G40)-2) | D7: =IF(ISNUMBER(C7),C7,B7) | E7: =1/PRODUCT(D7:D46) | F7: 2025-08, 2025-09, 2025-10, 2025-11, 2026-02, 2026-03
A8: 6 | B8: =(SUM('OP Ratios'!H32,'OP Ratios'!H33,'OP Ratios'!H34,'OP Ratios'!H35,'OP Ratios'!H38,'OP Ratios'!H39)-MAX('OP Ratios'!H32,'OP Ratios'!H33,'OP Ratios'!H34,'OP Ratios'!H35,'OP Ratios'!H38,'OP Ratios'!H39)-MIN('OP Ratios'!H32,'OP Ratios'!H33,'OP Ratios'!H34,'OP Ratios'!H35,'OP Ratios'!H38,'OP Ratios'!H39))/(COUNT('OP Ratios'!H32,'OP Ratios'!H33,'OP Ratios'!H34,'OP Ratios'!H35,'OP Ratios'!H38,'OP Ratios'!H39)-2) | D8: =IF(ISNUMBER(C8),C8,B8) | E8: =1/PRODUCT(D8:D46) | F8: 2025-07, 2025-08, 2025-09, 2025-10, 2026-01, 2026-02
A9: 7 | B9: =(SUM('OP Ratios'!I31,'OP Ratios'!I32,'OP Ratios'!I33,'OP Ratios'!I34,'OP Ratios'!I37,'OP Ratios'!I38)-MAX('OP Ratios'!I31,'OP Ratios'!I32,'OP Ratios'!I33,'OP Ratios'!I34,'OP Ratios'!I37,'OP Ratios'!I38)-MIN('OP Ratios'!I31,'OP Ratios'!I32,'OP Ratios'!I33,'OP Ratios'!I34,'OP Ratios'!I37,'OP Ratios'!I38))/(COUNT('OP Ratios'!I31,'OP Ratios'!I32,'OP Ratios'!I33,'OP Ratios'!I34,'OP Ratios'!I37,'OP Ratios'!I38)-2) | D9: =IF(ISNUMBER(C9),C9,B9) | E9: =1/PRODUCT(D9:D46) | F9: 2025-06, 2025-07, 2025-08, 2025-09, 2025-12, 2026-01
A10: 8 | B10: =(SUM('OP Ratios'!J30,'OP Ratios'!J31,'OP Ratios'!J32,'OP Ratios'!J33,'OP Ratios'!J36,'OP Ratios'!J37)-MAX('OP Ratios'!J30,'OP Ratios'!J31,'OP Ratios'!J32,'OP Ratios'!J33,'OP Ratios'!J36,'OP Ratios'!J37)-MIN('OP Ratios'!J30,'OP Ratios'!J31,'OP Ratios'!J32,'OP Ratios'!J33,'OP Ratios'!J36,'OP Ratios'!J37))/(COUNT('OP Ratios'!J30,'OP Ratios'!J31,'OP Ratios'!J32,'OP Ratios'!J33,'OP Ratios'!J36,'OP Ratios'!J37)-2) | D10: =IF(ISNUMBER(C10),C10,B10) | E10: =1/PRODUCT(D10:D46) | F10: 2025-05, 2025-06, 2025-07, 2025-08, 2025-11, 2025-12
A11: 9 | B11: =(SUM('OP Ratios'!K29,'OP Ratios'!K30,'OP Ratios'!K31,'OP Ratios'!K32,'OP Ratios'!K35,'OP Ratios'!K36)-MAX('OP Ratios'!K29,'OP Ratios'!K30,'OP Ratios'!K31,'OP Ratios'!K32,'OP Ratios'!K35,'OP Ratios'!K36)-MIN('OP Ratios'!K29,'OP Ratios'!K30,'OP Ratios'!K31,'OP Ratios'!K32,'OP Ratios'!K35,'OP Ratios'!K36))/(COUNT('OP Ratios'!K29,'OP Ratios'!K30,'OP Ratios'!K31,'OP Ratios'!K32,'OP Ratios'!K35,'OP Ratios'!K36)-2) | D11: =IF(ISNUMBER(C11),C11,B11) | E11: =1/PRODUCT(D11:D46) | F11: 2025-04, 2025-05, 2025-06, 2025-07, 2025-10, 2025-11
A12: 10 | B12: =(SUM('OP Ratios'!L28,'OP Ratios'!L29,'OP Ratios'!L30,'OP Ratios'!L31,'OP Ratios'!L34,'OP Ratios'!L35)-MAX('OP Ratios'!L28,'OP Ratios'!L29,'OP Ratios'!L30,'OP Ratios'!L31,'OP Ratios'!L34,'OP Ratios'!L35)-MIN('OP Ratios'!L28,'OP Ratios'!L29,'OP Ratios'!L30,'OP Ratios'!L31,'OP Ratios'!L34,'OP Ratios'!L35))/(COUNT('OP Ratios'!L28,'OP Ratios'!L29,'OP Ratios'!L30,'OP Ratios'!L31,'OP Ratios'!L34,'OP Ratios'!L35)-2) | D12: =IF(ISNUMBER(C12),C12,B12) | E12: =1/PRODUCT(D12:D46) | F12: 2025-03, 2025-04, 2025-05, 2025-06, 2025-09, 2025-10
A13: 11 | B13: =(SUM('OP Ratios'!M27,'OP Ratios'!M28,'OP Ratios'!M29,'OP Ratios'!M30,'OP Ratios'!M33,'OP Ratios'!M34)-MAX('OP Ratios'!M27,'OP Ratios'!M28,'OP Ratios'!M29,'OP Ratios'!M30,'OP Ratios'!M33,'OP Ratios'!M34)-MIN('OP Ratios'!M27,'OP Ratios'!M28,'OP Ratios'!M29,'OP Ratios'!M30,'OP Ratios'!M33,'OP Ratios'!M34))/(COUNT('OP Ratios'!M27,'OP Ratios'!M28,'OP Ratios'!M29,'OP Ratios'!M30,'OP Ratios'!M33,'OP Ratios'!M34)-2) | D13: =IF(ISNUMBER(C13),C13,B13) | E13: =1/PRODUCT(D13:D46) | F13: 2025-02, 2025-03, 2025-04, 2025-05, 2025-08, 2025-09
A14: 12 | B14: =(SUM('OP Ratios'!N26,'OP Ratios'!N27,'OP Ratios'!N28,'OP Ratios'!N29,'OP Ratios'!N32,'OP Ratios'!N33)-MAX('OP Ratios'!N26,'OP Ratios'!N27,'OP Ratios'!N28,'OP Ratios'!N29,'OP Ratios'!N32,'OP Ratios'!N33)-MIN('OP Ratios'!N26,'OP Ratios'!N27,'OP Ratios'!N28,'OP Ratios'!N29,'OP Ratios'!N32,'OP Ratios'!N33))/(COUNT('OP Ratios'!N26,'OP Ratios'!N27,'OP Ratios'!N28,'OP Ratios'!N29,'OP Ratios'!N32,'OP Ratios'!N33)-2) | D14: =IF(ISNUMBER(C14),C14,B14) | E14: =1/PRODUCT(D14:D46) | F14: 2025-01, 2025-02, 2025-03, 2025-04, 2025-07, 2025-08
A15: 13 | B15: =(SUM('OP Ratios'!O25,'OP Ratios'!O26,'OP Ratios'!O27,'OP Ratios'!O28,'OP Ratios'!O31,'OP Ratios'!O32)-MAX('OP Ratios'!O25,'OP Ratios'!O26,'OP Ratios'!O27,'OP Ratios'!O28,'OP Ratios'!O31,'OP Ratios'!O32)-MIN('OP Ratios'!O25,'OP Ratios'!O26,'OP Ratios'!O27,'OP Ratios'!O28,'OP Ratios'!O31,'OP Ratios'!O32))/(COUNT('OP Ratios'!O25,'OP Ratios'!O26,'OP Ratios'!O27,'OP Ratios'!O28,'OP Ratios'!O31,'OP Ratios'!O32)-2) | D15: =IF(ISNUMBER(C15),C15,B15) | E15: =1/PRODUCT(D15:D46) | F15: 2024-12, 2025-01, 2025-02, 2025-03, 2025-06, 2025-07
A16: 14 | B16: =(SUM('OP Ratios'!P24,'OP Ratios'!P25,'OP Ratios'!P26,'OP Ratios'!P27,'OP Ratios'!P30,'OP Ratios'!P31)-MAX('OP Ratios'!P24,'OP Ratios'!P25,'OP Ratios'!P26,'OP Ratios'!P27,'OP Ratios'!P30,'OP Ratios'!P31)-MIN('OP Ratios'!P24,'OP Ratios'!P25,'OP Ratios'!P26,'OP Ratios'!P27,'OP Ratios'!P30,'OP Ratios'!P31))/(COUNT('OP Ratios'!P24,'OP Ratios'!P25,'OP Ratios'!P26,'OP Ratios'!P27,'OP Ratios'!P30,'OP Ratios'!P31)-2) | D16: =IF(ISNUMBER(C16),C16,B16) | E16: =1/PRODUCT(D16:D46) | F16: 2024-11, 2024-12, 2025-01, 2025-02, 2025-05, 2025-06
A17: 15 | B17: =(SUM('OP Ratios'!Q23,'OP Ratios'!Q24,'OP Ratios'!Q25,'OP Ratios'!Q26,'OP Ratios'!Q29,'OP Ratios'!Q30)-MAX('OP Ratios'!Q23,'OP Ratios'!Q24,'OP Ratios'!Q25,'OP Ratios'!Q26,'OP Ratios'!Q29,'OP Ratios'!Q30)-MIN('OP Ratios'!Q23,'OP Ratios'!Q24,'OP Ratios'!Q25,'OP Ratios'!Q26,'OP Ratios'!Q29,'OP Ratios'!Q30))/(COUNT('OP Ratios'!Q23,'OP Ratios'!Q24,'OP Ratios'!Q25,'OP Ratios'!Q26,'OP Ratios'!Q29,'OP Ratios'!Q30)-2) | D17: =IF(ISNUMBER(C17),C17,B17) | E17: =1/PRODUCT(D17:D46) | F17: 2024-10, 2024-11, 2024-12, 2025-01, 2025-04, 2025-05
A18: 16 | B18: =(SUM('OP Ratios'!R22,'OP Ratios'!R23,'OP Ratios'!R24,'OP Ratios'!R25,'OP Ratios'!R28,'OP Ratios'!R29)-MAX('OP Ratios'!R22,'OP Ratios'!R23,'OP Ratios'!R24,'OP Ratios'!R25,'OP Ratios'!R28,'OP Ratios'!R29)-MIN('OP Ratios'!R22,'OP Ratios'!R23,'OP Ratios'!R24,'OP Ratios'!R25,'OP Ratios'!R28,'OP Ratios'!R29))/(COUNT('OP Ratios'!R22,'OP Ratios'!R23,'OP Ratios'!R24,'OP Ratios'!R25,'OP Ratios'!R28,'OP Ratios'!R29)-2) | D18: =IF(ISNUMBER(C18),C18,B18) | E18: =1/PRODUCT(D18:D46) | F18: 2024-09, 2024-10, 2024-11, 2024-12, 2025-03, 2025-04
A19: 17 | B19: =(SUM('OP Ratios'!S21,'OP Ratios'!S22,'OP Ratios'!S23,'OP Ratios'!S24,'OP Ratios'!S27,'OP Ratios'!S28)-MAX('OP Ratios'!S21,'OP Ratios'!S22,'OP Ratios'!S23,'OP Ratios'!S24,'OP Ratios'!S27,'OP Ratios'!S28)-MIN('OP Ratios'!S21,'OP Ratios'!S22,'OP Ratios'!S23,'OP Ratios'!S24,'OP Ratios'!S27,'OP Ratios'!S28))/(COUNT('OP Ratios'!S21,'OP Ratios'!S22,'OP Ratios'!S23,'OP Ratios'!S24,'OP Ratios'!S27,'OP Ratios'!S28)-2) | D19: =IF(ISNUMBER(C19),C19,B19) | E19: =1/PRODUCT(D19:D46) | F19: 2024-08, 2024-09, 2024-10, 2024-11, 2025-02, 2025-03
A20: 18 | B20: =(SUM('OP Ratios'!T20,'OP Ratios'!T21,'OP Ratios'!T22,'OP Ratios'!T23,'OP Ratios'!T26,'OP Ratios'!T27)-MAX('OP Ratios'!T20,'OP Ratios'!T21,'OP Ratios'!T22,'OP Ratios'!T23,'OP Ratios'!T26,'OP Ratios'!T27)-MIN('OP Ratios'!T20,'OP Ratios'!T21,'OP Ratios'!T22,'OP Ratios'!T23,'OP Ratios'!T26,'OP Ratios'!T27))/(COUNT('OP Ratios'!T20,'OP Ratios'!T21,'OP Ratios'!T22,'OP Ratios'!T23,'OP Ratios'!T26,'OP Ratios'!T27)-2) | D20: =IF(ISNUMBER(C20),C20,B20) | E20: =1/PRODUCT(D20:D46) | F20: 2024-07, 2024-08, 2024-09, 2024-10, 2025-01, 2025-02
A21: 19 | B21: =(SUM('OP Ratios'!U19,'OP Ratios'!U20,'OP Ratios'!U21,'OP Ratios'!U22,'OP Ratios'!U25,'OP Ratios'!U26)-MAX('OP Ratios'!U19,'OP Ratios'!U20,'OP Ratios'!U21,'OP Ratios'!U22,'OP Ratios'!U25,'OP Ratios'!U26)-MIN('OP Ratios'!U19,'OP Ratios'!U20,'OP Ratios'!U21,'OP Ratios'!U22,'OP Ratios'!U25,'OP Ratios'!U26))/(COUNT('OP Ratios'!U19,'OP Ratios'!U20,'OP Ratios'!U21,'OP Ratios'!U22,'OP Ratios'!U25,'OP Ratios'!U26)-2) | D21: =IF(ISNUMBER(C21),C21,B21) | E21: =1/PRODUCT(D21:D46) | F21: 2024-06, 2024-07, 2024-08, 2024-09, 2024-12, 2025-01
A22: 20 | B22: =(SUM('OP Ratios'!V18,'OP Ratios'!V19,'OP Ratios'!V20,'OP Ratios'!V21,'OP Ratios'!V24,'OP Ratios'!V25)-MAX('OP Ratios'!V18,'OP Ratios'!V19,'OP Ratios'!V20,'OP Ratios'!V21,'OP Ratios'!V24,'OP Ratios'!V25)-MIN('OP Ratios'!V18,'OP Ratios'!V19,'OP Ratios'!V20,'OP Ratios'!V21,'OP Ratios'!V24,'OP Ratios'!V25))/(COUNT('OP Ratios'!V18,'OP Ratios'!V19,'OP Ratios'!V20,'OP Ratios'!V21,'OP Ratios'!V24,'OP Ratios'!V25)-2) | D22: =IF(ISNUMBER(C22),C22,B22) | E22: =1/PRODUCT(D22:D46) | F22: 2024-05, 2024-06, 2024-07, 2024-08, 2024-11, 2024-12
A23: 21 | B23: =(SUM('OP Ratios'!W17,'OP Ratios'!W18,'OP Ratios'!W19,'OP Ratios'!W20,'OP Ratios'!W23,'OP Ratios'!W24)-MAX('OP Ratios'!W17,'OP Ratios'!W18,'OP Ratios'!W19,'OP Ratios'!W20,'OP Ratios'!W23,'OP Ratios'!W24)-MIN('OP Ratios'!W17,'OP Ratios'!W18,'OP Ratios'!W19,'OP Ratios'!W20,'OP Ratios'!W23,'OP Ratios'!W24))/(COUNT('OP Ratios'!W17,'OP Ratios'!W18,'OP Ratios'!W19,'OP Ratios'!W20,'OP Ratios'!W23,'OP Ratios'!W24)-2) | D23: =IF(ISNUMBER(C23),C23,B23) | E23: =1/PRODUCT(D23:D46) | F23: 2024-04, 2024-05, 2024-06, 2024-07, 2024-10, 2024-11
A24: 22 | B24: =(SUM('OP Ratios'!X16,'OP Ratios'!X17,'OP Ratios'!X18,'OP Ratios'!X19,'OP Ratios'!X22,'OP Ratios'!X23)-MAX('OP Ratios'!X16,'OP Ratios'!X17,'OP Ratios'!X18,'OP Ratios'!X19,'OP Ratios'!X22,'OP Ratios'!X23)-MIN('OP Ratios'!X16,'OP Ratios'!X17,'OP Ratios'!X18,'OP Ratios'!X19,'OP Ratios'!X22,'OP Ratios'!X23))/(COUNT('OP Ratios'!X16,'OP Ratios'!X17,'OP Ratios'!X18,'OP Ratios'!X19,'OP Ratios'!X22,'OP Ratios'!X23)-2) | D24: =IF(ISNUMBER(C24),C24,B24) | E24: =1/PRODUCT(D24:D46) | F24: 2024-03, 2024-04, 2024-05, 2024-06, 2024-09, 2024-10
A25: 23 | B25: =(SUM('OP Ratios'!Y15,'OP Ratios'!Y16,'OP Ratios'!Y17,'OP Ratios'!Y18,'OP Ratios'!Y21,'OP Ratios'!Y22)-MAX('OP Ratios'!Y15,'OP Ratios'!Y16,'OP Ratios'!Y17,'OP Ratios'!Y18,'OP Ratios'!Y21,'OP Ratios'!Y22)-MIN('OP Ratios'!Y15,'OP Ratios'!Y16,'OP Ratios'!Y17,'OP Ratios'!Y18,'OP Ratios'!Y21,'OP Ratios'!Y22))/(COUNT('OP Ratios'!Y15,'OP Ratios'!Y16,'OP Ratios'!Y17,'OP Ratios'!Y18,'OP Ratios'!Y21,'OP Ratios'!Y22)-2) | D25: =IF(ISNUMBER(C25),C25,B25) | E25: =1/PRODUCT(D25:D46) | F25: 2024-02, 2024-03, 2024-04, 2024-05, 2024-08, 2024-09
A26: 24 | B26: =(SUM('OP Ratios'!Z14,'OP Ratios'!Z15,'OP Ratios'!Z16,'OP Ratios'!Z17,'OP Ratios'!Z20,'OP Ratios'!Z21)-MAX('OP Ratios'!Z14,'OP Ratios'!Z15,'OP Ratios'!Z16,'OP Ratios'!Z17,'OP Ratios'!Z20,'OP Ratios'!Z21)-MIN('OP Ratios'!Z14,'OP Ratios'!Z15,'OP Ratios'!Z16,'OP Ratios'!Z17,'OP Ratios'!Z20,'OP Ratios'!Z21))/(COUNT('OP Ratios'!Z14,'OP Ratios'!Z15,'OP Ratios'!Z16,'OP Ratios'!Z17,'OP Ratios'!Z20,'OP Ratios'!Z21)-2) | D26: =IF(ISNUMBER(C26),C26,B26) | E26: =1/PRODUCT(D26:D46) | F26: 2024-01, 2024-02, 2024-03, 2024-04, 2024-07, 2024-08
A27: 25 | B27: =(SUM('OP Ratios'!AA13,'OP Ratios'!AA14,'OP Ratios'!AA15,'OP Ratios'!AA16,'OP Ratios'!AA19,'OP Ratios'!AA20)-MAX('OP Ratios'!AA13,'OP Ratios'!AA14,'OP Ratios'!AA15,'OP Ratios'!AA16,'OP Ratios'!AA19,'OP Ratios'!AA20)-MIN('OP Ratios'!AA13,'OP Ratios'!AA14,'OP Ratios'!AA15,'OP Ratios'!AA16,'OP Ratios'!AA19,'OP Ratios'!AA20))/(COUNT('OP Ratios'!AA13,'OP Ratios'!AA14,'OP Ratios'!AA15,'OP Ratios'!AA16,'OP Ratios'!AA19,'OP Ratios'!AA20)-2) | D27: =IF(ISNUMBER(C27),C27,B27) | E27: =1/PRODUCT(D27:D46) | F27: 2023-12, 2024-01, 2024-02, 2024-03, 2024-06, 2024-07
A28: 26 | B28: =(SUM('OP Ratios'!AB12,'OP Ratios'!AB13,'OP Ratios'!AB14,'OP Ratios'!AB15,'OP Ratios'!AB18,'OP Ratios'!AB19)-MAX('OP Ratios'!AB12,'OP Ratios'!AB13,'OP Ratios'!AB14,'OP Ratios'!AB15,'OP Ratios'!AB18,'OP Ratios'!AB19)-MIN('OP Ratios'!AB12,'OP Ratios'!AB13,'OP Ratios'!AB14,'OP Ratios'!AB15,'OP Ratios'!AB18,'OP Ratios'!AB19))/(COUNT('OP Ratios'!AB12,'OP Ratios'!AB13,'OP Ratios'!AB14,'OP Ratios'!AB15,'OP Ratios'!AB18,'OP Ratios'!AB19)-2) | D28: =IF(ISNUMBER(C28),C28,B28) | E28: =1/PRODUCT(D28:D46) | F28: 2023-11, 2023-12, 2024-01, 2024-02, 2024-05, 2024-06
A29: 27 | B29: =(SUM('OP Ratios'!AC11,'OP Ratios'!AC12,'OP Ratios'!AC13,'OP Ratios'!AC14,'OP Ratios'!AC17,'OP Ratios'!AC18)-MAX('OP Ratios'!AC11,'OP Ratios'!AC12,'OP Ratios'!AC13,'OP Ratios'!AC14,'OP Ratios'!AC17,'OP Ratios'!AC18)-MIN('OP Ratios'!AC11,'OP Ratios'!AC12,'OP Ratios'!AC13,'OP Ratios'!AC14,'OP Ratios'!AC17,'OP Ratios'!AC18))/(COUNT('OP Ratios'!AC11,'OP Ratios'!AC12,'OP Ratios'!AC13,'OP Ratios'!AC14,'OP Ratios'!AC17,'OP Ratios'!AC18)-2) | D29: =IF(ISNUMBER(C29),C29,B29) | E29: =1/PRODUCT(D29:D46) | F29: 2023-10, 2023-11, 2023-12, 2024-01, 2024-04, 2024-05
A30: 28 | B30: =(SUM('OP Ratios'!AD10,'OP Ratios'!AD11,'OP Ratios'!AD12,'OP Ratios'!AD13,'OP Ratios'!AD16,'OP Ratios'!AD17)-MAX('OP Ratios'!AD10,'OP Ratios'!AD11,'OP Ratios'!AD12,'OP Ratios'!AD13,'OP Ratios'!AD16,'OP Ratios'!AD17)-MIN('OP Ratios'!AD10,'OP Ratios'!AD11,'OP Ratios'!AD12,'OP Ratios'!AD13,'OP Ratios'!AD16,'OP Ratios'!AD17))/(COUNT('OP Ratios'!AD10,'OP Ratios'!AD11,'OP Ratios'!AD12,'OP Ratios'!AD13,'OP Ratios'!AD16,'OP Ratios'!AD17)-2) | D30: =IF(ISNUMBER(C30),C30,B30) | E30: =1/PRODUCT(D30:D46) | F30: 2023-09, 2023-10, 2023-11, 2023-12, 2024-03, 2024-04
A31: 29 | B31: =(SUM('OP Ratios'!AE9,'OP Ratios'!AE10,'OP Ratios'!AE11,'OP Ratios'!AE12,'OP Ratios'!AE15,'OP Ratios'!AE16)-MAX('OP Ratios'!AE9,'OP Ratios'!AE10,'OP Ratios'!AE11,'OP Ratios'!AE12,'OP Ratios'!AE15,'OP Ratios'!AE16)-MIN('OP Ratios'!AE9,'OP Ratios'!AE10,'OP Ratios'!AE11,'OP Ratios'!AE12,'OP Ratios'!AE15,'OP Ratios'!AE16))/(COUNT('OP Ratios'!AE9,'OP Ratios'!AE10,'OP Ratios'!AE11,'OP Ratios'!AE12,'OP Ratios'!AE15,'OP Ratios'!AE16)-2) | D31: =IF(ISNUMBER(C31),C31,B31) | E31: =1/PRODUCT(D31:D46) | F31: 2023-08, 2023-09, 2023-10, 2023-11, 2024-02, 2024-03
A32: 30 | B32: =(SUM('OP Ratios'!AF8,'OP Ratios'!AF9,'OP Ratios'!AF10,'OP Ratios'!AF11,'OP Ratios'!AF14,'OP Ratios'!AF15)-MAX('OP Ratios'!AF8,'OP Ratios'!AF9,'OP Ratios'!AF10,'OP Ratios'!AF11,'OP Ratios'!AF14,'OP Ratios'!AF15)-MIN('OP Ratios'!AF8,'OP Ratios'!AF9,'OP Ratios'!AF10,'OP Ratios'!AF11,'OP Ratios'!AF14,'OP Ratios'!AF15))/(COUNT('OP Ratios'!AF8,'OP Ratios'!AF9,'OP Ratios'!AF10,'OP Ratios'!AF11,'OP Ratios'!AF14,'OP Ratios'!AF15)-2) | D32: =IF(ISNUMBER(C32),C32,B32) | E32: =1/PRODUCT(D32:D46) | F32: 2023-07, 2023-08, 2023-09, 2023-10, 2024-01, 2024-02
A33: 31 | B33: =(SUM('OP Ratios'!AG7,'OP Ratios'!AG8,'OP Ratios'!AG9,'OP Ratios'!AG10,'OP Ratios'!AG13,'OP Ratios'!AG14)-MAX('OP Ratios'!AG7,'OP Ratios'!AG8,'OP Ratios'!AG9,'OP Ratios'!AG10,'OP Ratios'!AG13,'OP Ratios'!AG14)-MIN('OP Ratios'!AG7,'OP Ratios'!AG8,'OP Ratios'!AG9,'OP Ratios'!AG10,'OP Ratios'!AG13,'OP Ratios'!AG14))/(COUNT('OP Ratios'!AG7,'OP Ratios'!AG8,'OP Ratios'!AG9,'OP Ratios'!AG10,'OP Ratios'!AG13,'OP Ratios'!AG14)-2) | D33: =IF(ISNUMBER(C33),C33,B33) | E33: =1/PRODUCT(D33:D46) | F33: 2023-06, 2023-07, 2023-08, 2023-09, 2023-12, 2024-01
A34: 32 | B34: =(SUM('OP Ratios'!AH6,'OP Ratios'!AH7,'OP Ratios'!AH8,'OP Ratios'!AH9,'OP Ratios'!AH12,'OP Ratios'!AH13)-MAX('OP Ratios'!AH6,'OP Ratios'!AH7,'OP Ratios'!AH8,'OP Ratios'!AH9,'OP Ratios'!AH12,'OP Ratios'!AH13)-MIN('OP Ratios'!AH6,'OP Ratios'!AH7,'OP Ratios'!AH8,'OP Ratios'!AH9,'OP Ratios'!AH12,'OP Ratios'!AH13))/(COUNT('OP Ratios'!AH6,'OP Ratios'!AH7,'OP Ratios'!AH8,'OP Ratios'!AH9,'OP Ratios'!AH12,'OP Ratios'!AH13)-2) | D34: =IF(ISNUMBER(C34),C34,B34) | E34: =1/PRODUCT(D34:D46) | F34: 2023-05, 2023-06, 2023-07, 2023-08, 2023-11, 2023-12
A35: 33 | B35: =(SUM('OP Ratios'!AI5,'OP Ratios'!AI6,'OP Ratios'!AI7,'OP Ratios'!AI8,'OP Ratios'!AI11,'OP Ratios'!AI12)-MAX('OP Ratios'!AI5,'OP Ratios'!AI6,'OP Ratios'!AI7,'OP Ratios'!AI8,'OP Ratios'!AI11,'OP Ratios'!AI12)-MIN('OP Ratios'!AI5,'OP Ratios'!AI6,'OP Ratios'!AI7,'OP Ratios'!AI8,'OP Ratios'!AI11,'OP Ratios'!AI12))/(COUNT('OP Ratios'!AI5,'OP Ratios'!AI6,'OP Ratios'!AI7,'OP Ratios'!AI8,'OP Ratios'!AI11,'OP Ratios'!AI12)-2) | D35: =IF(ISNUMBER(C35),C35,B35) | E35: =1/PRODUCT(D35:D46) | F35: 2023-04, 2023-05, 2023-06, 2023-07, 2023-10, 2023-11
A36: 34 | B36: =(SUM('OP Ratios'!AJ4,'OP Ratios'!AJ5,'OP Ratios'!AJ6,'OP Ratios'!AJ7,'OP Ratios'!AJ10,'OP Ratios'!AJ11)-MAX('OP Ratios'!AJ4,'OP Ratios'!AJ5,'OP Ratios'!AJ6,'OP Ratios'!AJ7,'OP Ratios'!AJ10,'OP Ratios'!AJ11)-MIN('OP Ratios'!AJ4,'OP Ratios'!AJ5,'OP Ratios'!AJ6,'OP Ratios'!AJ7,'OP Ratios'!AJ10,'OP Ratios'!AJ11))/(COUNT('OP Ratios'!AJ4,'OP Ratios'!AJ5,'OP Ratios'!AJ6,'OP Ratios'!AJ7,'OP Ratios'!AJ10,'OP Ratios'!AJ11)-2) | D36: =IF(ISNUMBER(C36),C36,B36) | E36: =1/PRODUCT(D36:D46) | F36: 2023-03, 2023-04, 2023-05, 2023-06, 2023-09, 2023-10
A37: 35 | B37: =(SUM('OP Ratios'!AK3,'OP Ratios'!AK4,'OP Ratios'!AK5,'OP Ratios'!AK6,'OP Ratios'!AK9,'OP Ratios'!AK10)-MAX('OP Ratios'!AK3,'OP Ratios'!AK4,'OP Ratios'!AK5,'OP Ratios'!AK6,'OP Ratios'!AK9,'OP Ratios'!AK10)-MIN('OP Ratios'!AK3,'OP Ratios'!AK4,'OP Ratios'!AK5,'OP Ratios'!AK6,'OP Ratios'!AK9,'OP Ratios'!AK10))/(COUNT('OP Ratios'!AK3,'OP Ratios'!AK4,'OP Ratios'!AK5,'OP Ratios'!AK6,'OP Ratios'!AK9,'OP Ratios'!AK10)-2) | D37: =IF(ISNUMBER(C37),C37,B37) | E37: =1/PRODUCT(D37:D46) | F37: 2023-02, 2023-03, 2023-04, 2023-05, 2023-08, 2023-09
A38: 36 | B38: 1 | D38: =IF(ISNUMBER(C38),C38,B38) | E38: =1/PRODUCT(D38:D46) | F38: 2023-01, 2023-02, 2023-03, 2023-04, 2023-07, 2023-08
A39: 37 | B39: 1 | D39: =IF(ISNUMBER(C39),C39,B39) | E39: =1/PRODUCT(D39:D46) | F39: 2023-01, 2023-02, 2023-03, 2023-06, 2023-07
A40: 38 | B40: 1 | D40: =IF(ISNUMBER(C40),C40,B40) | E40: =1/PRODUCT(D40:D46) | F40: 2023-01, 2023-02, 2023-05, 2023-06
A41: 39 | B41: 1 | D41: =IF(ISNUMBER(C41),C41,B41) | E41: =1/PRODUCT(D41:D46) | F41: 2023-01, 2023-04, 2023-05
A42: 40 | B42: 1 | D42: =IF(ISNUMBER(C42),C42,B42) | E42: =1/PRODUCT(D42:D46) | F42: 2023-03, 2023-04
A43: 41 | B43: 1 | D43: =IF(ISNUMBER(C43),C43,B43) | E43: =1/PRODUCT(D43:D46) | F43: 2023-02, 2023-03
A44: 42 | B44: 1 | D44: =IF(ISNUMBER(C44),C44,B44) | E44: =1/PRODUCT(D44:D46) | F44: 2023-01, 2023-02
A45: 43 | B45: 1 | D45: =IF(ISNUMBER(C45),C45,B45) | E45: =1/PRODUCT(D45:D46) | F45: 2023-01
A46: 44 | B46: 1 | D46: =IF(ISNUMBER(C46),C46,B46) | E46: =1/PRODUCT(D46:D46) | F46: complete

Sheet OP Reserve
A1: Incurred | B1: Member months | C1: Age | D1: Paid to date | E1: Paid for estimation | F1: Completion factor | G1: CF ultimate | H1: Expected PMPM | I1: Expected claims | J1: B-F ultimate | K1: Selected ultimate | L1: IBNR | M1: Method
A2: 2023-01 | B2: 185202 | C2: 44 | D2: ='OP Triangle'!AT2 | E2: ='OP Triangle'!AS2+(D2-'OP Triangle'!AS2)/Assumptions!$B$7 | F2: =INDEX('OP Factors'!$E:$E,C2+2) | G2: =E2/F2 | H2: 135.50041 | I2: =H2*B2 | J2: =E2+(1-F2)*I2 | K2: =IF(C2>=Assumptions!$B$3,G2,J2) | L2: =K2-D2 | M2: =IF(C2>=Assumptions!$B$3,"Completion factor","PMPM / B-F")
A3: 2023-02 | B3: 185248 | C3: 43 | D3: ='OP Triangle'!AS3 | E3: ='OP Triangle'!AR3+(D3-'OP Triangle'!AR3)/Assumptions!$B$7 | F3: =INDEX('OP Factors'!$E:$E,C3+2) | G3: =E3/F3 | H3: 142.40858 | I3: =H3*B3 | J3: =E3+(1-F3)*I3 | K3: =IF(C3>=Assumptions!$B$3,G3,J3) | L3: =K3-D3 | M3: =IF(C3>=Assumptions!$B$3,"Completion factor","PMPM / B-F")
A4: 2023-03 | B4: 185435 | C4: 42 | D4: ='OP Triangle'!AR4 | E4: ='OP Triangle'!AQ4+(D4-'OP Triangle'!AQ4)/Assumptions!$B$7 | F4: =INDEX('OP Factors'!$E:$E,C4+2) | G4: =E4/F4 | H4: 147.71048 | I4: =H4*B4 | J4: =E4+(1-F4)*I4 | K4: =IF(C4>=Assumptions!$B$3,G4,J4) | L4: =K4-D4 | M4: =IF(C4>=Assumptions!$B$3,"Completion factor","PMPM / B-F")
A5: 2023-04 | B5: 185785 | C5: 41 | D5: ='OP Triangle'!AQ5 | E5: ='OP Triangle'!AP5+(D5-'OP Triangle'!AP5)/Assumptions!$B$7 | F5: =INDEX('OP Factors'!$E:$E,C5+2) | G5: =E5/F5 | H5: 144.37633 | I5: =H5*B5 | J5: =E5+(1-F5)*I5 | K5: =IF(C5>=Assumptions!$B$3,G5,J5) | L5: =K5-D5 | M5: =IF(C5>=Assumptions!$B$3,"Completion factor","PMPM / B-F")
A6: 2023-05 | B6: 185684 | C6: 40 | D6: ='OP Triangle'!AP6 | E6: ='OP Triangle'!AO6+(D6-'OP Triangle'!AO6)/Assumptions!$B$7 | F6: =INDEX('OP Factors'!$E:$E,C6+2) | G6: =E6/F6 | H6: 144.22848 | I6: =H6*B6 | J6: =E6+(1-F6)*I6 | K6: =IF(C6>=Assumptions!$B$3,G6,J6) | L6: =K6-D6 | M6: =IF(C6>=Assumptions!$B$3,"Completion factor","PMPM / B-F")
A7: 2023-06 | B7: 186376 | C7: 39 | D7: ='OP Triangle'!AO7 | E7: ='OP Triangle'!AN7+(D7-'OP Triangle'!AN7)/Assumptions!$B$7 | F7: =INDEX('OP Factors'!$E:$E,C7+2) | G7: =E7/F7 | H7: 147.09559 | I7: =H7*B7 | J7: =E7+(1-F7)*I7 | K7: =IF(C7>=Assumptions!$B$3,G7,J7) | L7: =K7-D7 | M7: =IF(C7>=Assumptions!$B$3,"Completion factor","PMPM / B-F")
A8: 2023-07 | B8: 186902 | C8: 38 | D8: ='OP Triangle'!AN8 | E8: ='OP Triangle'!AM8+(D8-'OP Triangle'!AM8)/Assumptions!$B$7 | F8: =INDEX('OP Factors'!$E:$E,C8+2) | G8: =E8/F8 | H8: 145.20081 | I8: =H8*B8 | J8: =E8+(1-F8)*I8 | K8: =IF(C8>=Assumptions!$B$3,G8,J8) | L8: =K8-D8 | M8: =IF(C8>=Assumptions!$B$3,"Completion factor","PMPM / B-F")
A9: 2023-08 | B9: 187226 | C9: 37 | D9: ='OP Triangle'!AM9 | E9: ='OP Triangle'!AL9+(D9-'OP Triangle'!AL9)/Assumptions!$B$7 | F9: =INDEX('OP Factors'!$E:$E,C9+2) | G9: =E9/F9 | H9: 158.16074 | I9: =H9*B9 | J9: =E9+(1-F9)*I9 | K9: =IF(C9>=Assumptions!$B$3,G9,J9) | L9: =K9-D9 | M9: =IF(C9>=Assumptions!$B$3,"Completion factor","PMPM / B-F")
A10: 2023-09 | B10: 187750 | C10: 36 | D10: ='OP Triangle'!AL10 | E10: ='OP Triangle'!AK10+(D10-'OP Triangle'!AK10)/Assumptions!$B$7 | F10: =INDEX('OP Factors'!$E:$E,C10+2) | G10: =E10/F10 | H10: 152.58783 | I10: =H10*B10 | J10: =E10+(1-F10)*I10 | K10: =IF(C10>=Assumptions!$B$3,G10,J10) | L10: =K10-D10 | M10: =IF(C10>=Assumptions!$B$3,"Completion factor","PMPM / B-F")
A11: 2023-10 | B11: 187725 | C11: 35 | D11: ='OP Triangle'!AK11 | E11: ='OP Triangle'!AJ11+(D11-'OP Triangle'!AJ11)/Assumptions!$B$7 | F11: =INDEX('OP Factors'!$E:$E,C11+2) | G11: =E11/F11 | H11: 163.44624 | I11: =H11*B11 | J11: =E11+(1-F11)*I11 | K11: =IF(C11>=Assumptions!$B$3,G11,J11) | L11: =K11-D11 | M11: =IF(C11>=Assumptions!$B$3,"Completion factor","PMPM / B-F")
A12: 2023-11 | B12: 187816 | C12: 34 | D12: ='OP Triangle'!AJ12 | E12: ='OP Triangle'!AI12+(D12-'OP Triangle'!AI12)/Assumptions!$B$7 | F12: =INDEX('OP Factors'!$E:$E,C12+2) | G12: =E12/F12 | H12: 160.48413 | I12: =H12*B12 | J12: =E12+(1-F12)*I12 | K12: =IF(C12>=Assumptions!$B$3,G12,J12) | L12: =K12-D12 | M12: =IF(C12>=Assumptions!$B$3,"Completion factor","PMPM / B-F")
A13: 2023-12 | B13: 188296 | C13: 33 | D13: ='OP Triangle'!AI13 | E13: ='OP Triangle'!AH13+(D13-'OP Triangle'!AH13)/Assumptions!$B$7 | F13: =INDEX('OP Factors'!$E:$E,C13+2) | G13: =E13/F13 | H13: 182.39446 | I13: =H13*B13 | J13: =E13+(1-F13)*I13 | K13: =IF(C13>=Assumptions!$B$3,G13,J13) | L13: =K13-D13 | M13: =IF(C13>=Assumptions!$B$3,"Completion factor","PMPM / B-F")
A14: 2024-01 | B14: 195186 | C14: 32 | D14: ='OP Triangle'!AH14 | E14: ='OP Triangle'!AG14+(D14-'OP Triangle'!AG14)/Assumptions!$B$7 | F14: =INDEX('OP Factors'!$E:$E,C14+2) | G14: =E14/F14 | H14: 147.75385 | I14: =H14*B14 | J14: =E14+(1-F14)*I14 | K14: =IF(C14>=Assumptions!$B$3,G14,J14) | L14: =K14-D14 | M14: =IF(C14>=Assumptions!$B$3,"Completion factor","PMPM / B-F")
A15: 2024-02 | B15: 195754 | C15: 31 | D15: ='OP Triangle'!AG15 | E15: ='OP Triangle'!AF15+(D15-'OP Triangle'!AF15)/Assumptions!$B$7 | F15: =INDEX('OP Factors'!$E:$E,C15+2) | G15: =E15/F15 | H15: 155.28673 | I15: =H15*B15 | J15: =E15+(1-F15)*I15 | K15: =IF(C15>=Assumptions!$B$3,G15,J15) | L15: =K15-D15 | M15: =IF(C15>=Assumptions!$B$3,"Completion factor","PMPM / B-F")
A16: 2024-03 | B16: 196371 | C16: 30 | D16: ='OP Triangle'!AF16 | E16: ='OP Triangle'!AE16+(D16-'OP Triangle'!AE16)/Assumptions!$B$7 | F16: =INDEX('OP Factors'!$E:$E,C16+2) | G16: =E16/F16 | H16: 161.06809 | I16: =H16*B16 | J16: =E16+(1-F16)*I16 | K16: =IF(C16>=Assumptions!$B$3,G16,J16) | L16: =K16-D16 | M16: =IF(C16>=Assumptions!$B$3,"Completion factor","PMPM / B-F")
A17: 2024-04 | B17: 196912 | C17: 29 | D17: ='OP Triangle'!AE17 | E17: ='OP Triangle'!AD17+(D17-'OP Triangle'!AD17)/Assumptions!$B$7 | F17: =INDEX('OP Factors'!$E:$E,C17+2) | G17: =E17/F17 | H17: 157.43243 | I17: =H17*B17 | J17: =E17+(1-F17)*I17 | K17: =IF(C17>=Assumptions!$B$3,G17,J17) | L17: =K17-D17 | M17: =IF(C17>=Assumptions!$B$3,"Completion factor","PMPM / B-F")
A18: 2024-05 | B18: 197352 | C18: 28 | D18: ='OP Triangle'!AD18 | E18: ='OP Triangle'!AC18+(D18-'OP Triangle'!AC18)/Assumptions!$B$7 | F18: =INDEX('OP Factors'!$E:$E,C18+2) | G18: =E18/F18 | H18: 157.2712 | I18: =H18*B18 | J18: =E18+(1-F18)*I18 | K18: =IF(C18>=Assumptions!$B$3,G18,J18) | L18: =K18-D18 | M18: =IF(C18>=Assumptions!$B$3,"Completion factor","PMPM / B-F")
A19: 2024-06 | B19: 198493 | C19: 27 | D19: ='OP Triangle'!AC19 | E19: ='OP Triangle'!AB19+(D19-'OP Triangle'!AB19)/Assumptions!$B$7 | F19: =INDEX('OP Factors'!$E:$E,C19+2) | G19: =E19/F19 | H19: 160.39759 | I19: =H19*B19 | J19: =E19+(1-F19)*I19 | K19: =IF(C19>=Assumptions!$B$3,G19,J19) | L19: =K19-D19 | M19: =IF(C19>=Assumptions!$B$3,"Completion factor","PMPM / B-F")
A20: 2024-07 | B20: 198829 | C20: 26 | D20: ='OP Triangle'!AB20 | E20: ='OP Triangle'!AA20+(D20-'OP Triangle'!AA20)/Assumptions!$B$7 | F20: =INDEX('OP Factors'!$E:$E,C20+2) | G20: =E20/F20 | H20: 158.33146 | I20: =H20*B20 | J20: =E20+(1-F20)*I20 | K20: =IF(C20>=Assumptions!$B$3,G20,J20) | L20: =K20-D20 | M20: =IF(C20>=Assumptions!$B$3,"Completion factor","PMPM / B-F")
A21: 2024-08 | B21: 199099 | C21: 25 | D21: ='OP Triangle'!AA21 | E21: ='OP Triangle'!Z21+(D21-'OP Triangle'!Z21)/Assumptions!$B$7 | F21: =INDEX('OP Factors'!$E:$E,C21+2) | G21: =E21/F21 | H21: 172.46338 | I21: =H21*B21 | J21: =E21+(1-F21)*I21 | K21: =IF(C21>=Assumptions!$B$3,G21,J21) | L21: =K21-D21 | M21: =IF(C21>=Assumptions!$B$3,"Completion factor","PMPM / B-F")
A22: 2024-09 | B22: 199429 | C22: 24 | D22: ='OP Triangle'!Z22 | E22: ='OP Triangle'!Y22+(D22-'OP Triangle'!Y22)/Assumptions!$B$7 | F22: =INDEX('OP Factors'!$E:$E,C22+2) | G22: =E22/F22 | H22: 166.3865 | I22: =H22*B22 | J22: =E22+(1-F22)*I22 | K22: =IF(C22>=Assumptions!$B$3,G22,J22) | L22: =K22-D22 | M22: =IF(C22>=Assumptions!$B$3,"Completion factor","PMPM / B-F")
A23: 2024-10 | B23: 199749 | C23: 23 | D23: ='OP Triangle'!Y23 | E23: ='OP Triangle'!X23+(D23-'OP Triangle'!X23)/Assumptions!$B$7 | F23: =INDEX('OP Factors'!$E:$E,C23+2) | G23: =E23/F23 | H23: 178.22684 | I23: =H23*B23 | J23: =E23+(1-F23)*I23 | K23: =IF(C23>=Assumptions!$B$3,G23,J23) | L23: =K23-D23 | M23: =IF(C23>=Assumptions!$B$3,"Completion factor","PMPM / B-F")
A24: 2024-11 | B24: 200252 | C24: 22 | D24: ='OP Triangle'!X24 | E24: ='OP Triangle'!W24+(D24-'OP Triangle'!W24)/Assumptions!$B$7 | F24: =INDEX('OP Factors'!$E:$E,C24+2) | G24: =E24/F24 | H24: 174.99687 | I24: =H24*B24 | J24: =E24+(1-F24)*I24 | K24: =IF(C24>=Assumptions!$B$3,G24,J24) | L24: =K24-D24 | M24: =IF(C24>=Assumptions!$B$3,"Completion factor","PMPM / B-F")
A25: 2024-12 | B25: 200297 | C25: 21 | D25: ='OP Triangle'!W25 | E25: ='OP Triangle'!V25+(D25-'OP Triangle'!V25)/Assumptions!$B$7 | F25: =INDEX('OP Factors'!$E:$E,C25+2) | G25: =E25/F25 | H25: 198.88858 | I25: =H25*B25 | J25: =E25+(1-F25)*I25 | K25: =IF(C25>=Assumptions!$B$3,G25,J25) | L25: =K25-D25 | M25: =IF(C25>=Assumptions!$B$3,"Completion factor","PMPM / B-F")
A26: 2025-01 | B26: 206379 | C26: 20 | D26: ='OP Triangle'!V26 | E26: ='OP Triangle'!U26+(D26-'OP Triangle'!U26)/Assumptions!$B$7 | F26: =INDEX('OP Factors'!$E:$E,C26+2) | G26: =E26/F26 | H26: 161.11538 | I26: =H26*B26 | J26: =E26+(1-F26)*I26 | K26: =IF(C26>=Assumptions!$B$3,G26,J26) | L26: =K26-D26 | M26: =IF(C26>=Assumptions!$B$3,"Completion factor","PMPM / B-F")
A27: 2025-02 | B27: 206414 | C27: 19 | D27: ='OP Triangle'!U27 | E27: ='OP Triangle'!T27+(D27-'OP Triangle'!T27)/Assumptions!$B$7 | F27: =INDEX('OP Factors'!$E:$E,C27+2) | G27: =E27/F27 | H27: 169.32946 | I27: =H27*B27 | J27: =E27+(1-F27)*I27 | K27: =IF(C27>=Assumptions!$B$3,G27,J27) | L27: =K27-D27 | M27: =IF(C27>=Assumptions!$B$3,"Completion factor","PMPM / B-F")
A28: 2025-03 | B28: 207034 | C28: 18 | D28: ='OP Triangle'!T28 | E28: ='OP Triangle'!S28+(D28-'OP Triangle'!S28)/Assumptions!$B$7 | F28: =INDEX('OP Factors'!$E:$E,C28+2) | G28: =E28/F28 | H28: 175.63363 | I28: =H28*B28 | J28: =E28+(1-F28)*I28 | K28: =IF(C28>=Assumptions!$B$3,G28,J28) | L28: =K28-D28 | M28: =IF(C28>=Assumptions!$B$3,"Completion factor","PMPM / B-F")
A29: 2025-04 | B29: 207074 | C29: 17 | D29: ='OP Triangle'!S29 | E29: ='OP Triangle'!R29+(D29-'OP Triangle'!R29)/Assumptions!$B$7 | F29: =INDEX('OP Factors'!$E:$E,C29+2) | G29: =E29/F29 | H29: 171.6692 | I29: =H29*B29 | J29: =E29+(1-F29)*I29 | K29: =IF(C29>=Assumptions!$B$3,G29,J29) | L29: =K29-D29 | M29: =IF(C29>=Assumptions!$B$3,"Completion factor","PMPM / B-F")
A30: 2025-05 | B30: 207656 | C30: 16 | D30: ='OP Triangle'!R30 | E30: ='OP Triangle'!Q30+(D30-'OP Triangle'!Q30)/Assumptions!$B$7 | F30: =INDEX('OP Factors'!$E:$E,C30+2) | G30: =E30/F30 | H30: 171.4934 | I30: =H30*B30 | J30: =E30+(1-F30)*I30 | K30: =IF(C30>=Assumptions!$B$3,G30,J30) | L30: =K30-D30 | M30: =IF(C30>=Assumptions!$B$3,"Completion factor","PMPM / B-F")
A31: 2025-06 | B31: 208551 | C31: 15 | D31: ='OP Triangle'!Q31 | E31: ='OP Triangle'!P31+(D31-'OP Triangle'!P31)/Assumptions!$B$7 | F31: =INDEX('OP Factors'!$E:$E,C31+2) | G31: =E31/F31 | H31: 174.90251 | I31: =H31*B31 | J31: =E31+(1-F31)*I31 | K31: =IF(C31>=Assumptions!$B$3,G31,J31) | L31: =K31-D31 | M31: =IF(C31>=Assumptions!$B$3,"Completion factor","PMPM / B-F")
A32: 2025-07 | B32: 208290 | C32: 14 | D32: ='OP Triangle'!P32 | E32: ='OP Triangle'!O32+(D32-'OP Triangle'!O32)/Assumptions!$B$7 | F32: =INDEX('OP Factors'!$E:$E,C32+2) | G32: =E32/F32 | H32: 172.64954 | I32: =H32*B32 | J32: =E32+(1-F32)*I32 | K32: =IF(C32>=Assumptions!$B$3,G32,J32) | L32: =K32-D32 | M32: =IF(C32>=Assumptions!$B$3,"Completion factor","PMPM / B-F")
A33: 2025-08 | B33: 209114 | C33: 13 | D33: ='OP Triangle'!O33 | E33: ='OP Triangle'!N33+(D33-'OP Triangle'!N33)/Assumptions!$B$7 | F33: =INDEX('OP Factors'!$E:$E,C33+2) | G33: =E33/F33 | H33: 188.05941 | I33: =H33*B33 | J33: =E33+(1-F33)*I33 | K33: =IF(C33>=Assumptions!$B$3,G33,J33) | L33: =K33-D33 | M33: =IF(C33>=Assumptions!$B$3,"Completion factor","PMPM / B-F")
A34: 2025-09 | B34: 209604 | C34: 12 | D34: ='OP Triangle'!N34 | E34: ='OP Triangle'!M34+(D34-'OP Triangle'!M34)/Assumptions!$B$7 | F34: =INDEX('OP Factors'!$E:$E,C34+2) | G34: =E34/F34 | H34: 181.433 | I34: =H34*B34 | J34: =E34+(1-F34)*I34 | K34: =IF(C34>=Assumptions!$B$3,G34,J34) | L34: =K34-D34 | M34: =IF(C34>=Assumptions!$B$3,"Completion factor","PMPM / B-F")
A35: 2025-10 | B35: 210074 | C35: 11 | D35: ='OP Triangle'!M35 | E35: ='OP Triangle'!L35+(D35-'OP Triangle'!L35)/Assumptions!$B$7 | F35: =INDEX('OP Factors'!$E:$E,C35+2) | G35: =E35/F35 | H35: 194.34408 | I35: =H35*B35 | J35: =E35+(1-F35)*I35 | K35: =IF(C35>=Assumptions!$B$3,G35,J35) | L35: =K35-D35 | M35: =IF(C35>=Assumptions!$B$3,"Completion factor","PMPM / B-F")
A36: 2025-11 | B36: 210375 | C36: 10 | D36: ='OP Triangle'!L36 | E36: ='OP Triangle'!K36+(D36-'OP Triangle'!K36)/Assumptions!$B$7 | F36: =INDEX('OP Factors'!$E:$E,C36+2) | G36: =E36/F36 | H36: 190.82201 | I36: =H36*B36 | J36: =E36+(1-F36)*I36 | K36: =IF(C36>=Assumptions!$B$3,G36,J36) | L36: =K36-D36 | M36: =IF(C36>=Assumptions!$B$3,"Completion factor","PMPM / B-F")
A37: 2025-12 | B37: 211296 | C37: 9 | D37: ='OP Triangle'!K37 | E37: ='OP Triangle'!J37+(D37-'OP Triangle'!J37)/Assumptions!$B$7 | F37: =INDEX('OP Factors'!$E:$E,C37+2) | G37: =E37/F37 | H37: 216.87427 | I37: =H37*B37 | J37: =E37+(1-F37)*I37 | K37: =IF(C37>=Assumptions!$B$3,G37,J37) | L37: =K37-D37 | M37: =IF(C37>=Assumptions!$B$3,"Completion factor","PMPM / B-F")
A38: 2026-01 | B38: 218809 | C38: 8 | D38: ='OP Triangle'!J38 | E38: ='OP Triangle'!I38+(D38-'OP Triangle'!I38)/Assumptions!$B$7 | F38: =INDEX('OP Factors'!$E:$E,C38+2) | G38: =E38/F38 | H38: 175.6852 | I38: =H38*B38 | J38: =E38+(1-F38)*I38 | K38: =IF(C38>=Assumptions!$B$3,G38,J38) | L38: =K38-D38 | M38: =IF(C38>=Assumptions!$B$3,"Completion factor","PMPM / B-F")
A39: 2026-02 | B39: 219372 | C39: 7 | D39: ='OP Triangle'!I39 | E39: ='OP Triangle'!H39+(D39-'OP Triangle'!H39)/Assumptions!$B$7 | F39: =INDEX('OP Factors'!$E:$E,C39+2) | G39: =E39/F39 | H39: 184.6421 | I39: =H39*B39 | J39: =E39+(1-F39)*I39 | K39: =IF(C39>=Assumptions!$B$3,G39,J39) | L39: =K39-D39 | M39: =IF(C39>=Assumptions!$B$3,"Completion factor","PMPM / B-F")
A40: 2026-03 | B40: 219455 | C40: 6 | D40: ='OP Triangle'!H40 | E40: ='OP Triangle'!G40+(D40-'OP Triangle'!G40)/Assumptions!$B$7 | F40: =INDEX('OP Factors'!$E:$E,C40+2) | G40: =E40/F40 | H40: 191.51636 | I40: =H40*B40 | J40: =E40+(1-F40)*I40 | K40: =IF(C40>=Assumptions!$B$3,G40,J40) | L40: =K40-D40 | M40: =IF(C40>=Assumptions!$B$3,"Completion factor","PMPM / B-F")
A41: 2026-04 | B41: 219206 | C41: 5 | D41: ='OP Triangle'!G41 | E41: ='OP Triangle'!F41+(D41-'OP Triangle'!F41)/Assumptions!$B$7 | F41: =INDEX('OP Factors'!$E:$E,C41+2) | G41: =E41/F41 | H41: 187.19342 | I41: =H41*B41 | J41: =E41+(1-F41)*I41 | K41: =IF(C41>=Assumptions!$B$3,G41,J41) | L41: =K41-D41 | M41: =IF(C41>=Assumptions!$B$3,"Completion factor","PMPM / B-F")
A42: 2026-05 | B42: 219383 | C42: 4 | D42: ='OP Triangle'!F42 | E42: ='OP Triangle'!E42+(D42-'OP Triangle'!E42)/Assumptions!$B$7 | F42: =INDEX('OP Factors'!$E:$E,C42+2) | G42: =E42/F42 | H42: 187.00172 | I42: =H42*B42 | J42: =E42+(1-F42)*I42 | K42: =IF(C42>=Assumptions!$B$3,G42,J42) | L42: =K42-D42 | M42: =IF(C42>=Assumptions!$B$3,"Completion factor","PMPM / B-F")
A43: 2026-06 | B43: 219891 | C43: 3 | D43: ='OP Triangle'!E43 | E43: ='OP Triangle'!D43+(D43-'OP Triangle'!D43)/Assumptions!$B$7 | F43: =INDEX('OP Factors'!$E:$E,C43+2) | G43: =E43/F43 | H43: 190.71912 | I43: =H43*B43 | J43: =E43+(1-F43)*I43 | K43: =IF(C43>=Assumptions!$B$3,G43,J43) | L43: =K43-D43 | M43: =IF(C43>=Assumptions!$B$3,"Completion factor","PMPM / B-F")
A44: 2026-07 | B44: 220771 | C44: 2 | D44: ='OP Triangle'!D44 | E44: ='OP Triangle'!C44+(D44-'OP Triangle'!C44)/Assumptions!$B$7 | F44: =INDEX('OP Factors'!$E:$E,C44+2) | G44: =E44/F44 | H44: 188.26241 | I44: =H44*B44 | J44: =E44+(1-F44)*I44 | K44: =IF(C44>=Assumptions!$B$3,G44,J44) | L44: =K44-D44 | M44: =IF(C44>=Assumptions!$B$3,"Completion factor","PMPM / B-F")
A45: 2026-08 | B45: 221871 | C45: 1 | D45: ='OP Triangle'!C45 | E45: ='OP Triangle'!B45+(D45-'OP Triangle'!B45)/Assumptions!$B$7 | F45: =INDEX('OP Factors'!$E:$E,C45+2) | G45: =E45/F45 | H45: 205.06581 | I45: =H45*B45 | J45: =E45+(1-F45)*I45 | K45: =IF(C45>=Assumptions!$B$3,G45,J45) | L45: =K45-D45 | M45: =IF(C45>=Assumptions!$B$3,"Completion factor","PMPM / B-F")
A46: 2026-09 | B46: 222253 | C46: 0 | D46: ='OP Triangle'!B46 | E46: =0+(D46-0)/Assumptions!$B$7 | F46: =INDEX('OP Factors'!$E:$E,C46+2) | G46: =E46/F46 | H46: 197.84017 | I46: =H46*B46 | J46: =E46+(1-F46)*I46 | K46: =IF(C46>=Assumptions!$B$3,G46,J46) | L46: =K46-D46 | M46: =IF(C46>=Assumptions!$B$3,"Completion factor","PMPM / B-F")
A47: Total | B47: =SUM(B2:B46) | D47: =SUM(D2:D46) | G47: =SUM(G2:G46) | I47: =SUM(I2:I46) | K47: =SUM(K2:K46) | L47: =SUM(L2:L46)

Sheet Prof Triangle
A1: Incurred | B1: Lag 0 | C1: Lag 1 | D1: Lag 2 | E1: Lag 3 | F1: Lag 4 | G1: Lag 5 | H1: Lag 6 | I1: Lag 7 | J1: Lag 8 | K1: Lag 9 | L1: Lag 10 | M1: Lag 11 | N1: Lag 12 | O1: Lag 13 | P1: Lag 14 | Q1: Lag 15 | R1: Lag 16 | S1: Lag 17 | T1: Lag 18 | U1: Lag 19 | V1: Lag 20 | W1: Lag 21 | X1: Lag 22 | Y1: Lag 23 | Z1: Lag 24 | AA1: Lag 25 | AB1: Lag 26 | AC1: Lag 27 | AD1: Lag 28 | AE1: Lag 29 | AF1: Lag 30 | AG1: Lag 31 | AH1: Lag 32 | AI1: Lag 33 | AJ1: Lag 34 | AK1: Lag 35 | AL1: Lag 36 | AM1: Lag 37 | AN1: Lag 38 | AO1: Lag 39 | AP1: Lag 40 | AQ1: Lag 41 | AR1: Lag 42 | AS1: Lag 43 | AT1: Lag 44
A2: 2023-01 | B2: 7856135.2 | C2: 21032556 | D2: 26598260 | E2: 28677784 | F2: 29383996 | G2: 29605696 | H2: 29679851 | I2: 29705681 | J2: 29713571 | K2: 29715952 | L2: 29716673 | M2: 29716899 | N2: 29716970 | O2: 29716992 | P2: 29716998 | Q2: 29717000 | R2: 29717000 | S2: 29717001 | T2: 29717001 | U2: 29717001 | V2: 29717001 | W2: 29717001 | X2: 29717001 | Y2: 29717001 | Z2: 29717001 | AA2: 29717001 | AB2: 29717001 | AC2: 29717001 | AD2: 29717001 | AE2: 29717001 | AF2: 29717001 | AG2: 29717001 | AH2: 29717001 | AI2: 29717001 | AJ2: 29717001 | AK2: 29717001 | AL2: 29717001 | AM2: 29717001 | AN2: 29717001 | AO2: 29717001 | AP2: 29717001 | AQ2: 29717001 | AR2: 29717001 | AS2: 29717001 | AT2: 29717001
A3: 2023-02 | B3: 8272479.3 | C3: 21432365 | D3: 26958875 | E3: 29161780 | F3: 29899749 | G3: 30141453 | H3: 30223127 | I3: 30247541 | J3: 30255217 | K3: 30257714 | L3: 30258498 | M3: 30258738 | N3: 30258808 | O3: 30258830 | P3: 30258837 | Q3: 30258839 | R3: 30258839 | S3: 30258840 | T3: 30258840 | U3: 30258840 | V3: 30258840 | W3: 30258840 | X3: 30258840 | Y3: 30258840 | Z3: 30258840 | AA3: 30258840 | AB3: 30258840 | AC3: 30258840 | AD3: 30258840 | AE3: 30258840 | AF3: 30258840 | AG3: 30258840 | AH3: 30258840 | AI3: 30258840 | AJ3: 30258840 | AK3: 30258840 | AL3: 30258840 | AM3: 30258840 | AN3: 30258840 | AO3: 30258840 | AP3: 30258840 | AQ3: 30258840 | AR3: 30258840 | AS3: 30258840
A4: 2023-03 | B4: 8532998.3 | C4: 22592770 | D4: 28944604 | E4: 31177346 | F4: 31985484 | G4: 32232583 | H4: 32314520 | I4: 32340540 | J4: 32348581 | K4: 32351208 | L4: 32351968 | M4: 32352211 | N4: 32352283 | O4: 32352304 | P4: 32352310 | Q4: 32352313 | R4: 32352313 | S4: 32352313 | T4: 32352313 | U4: 32352313 | V4: 32352313 | W4: 32352313 | X4: 32352313 | Y4: 32352313 | Z4: 32352313 | AA4: 32352313 | AB4: 32352313 | AC4: 32352313 | AD4: 32352313 | AE4: 32352313 | AF4: 32352313 | AG4: 32352313 | AH4: 32352313 | AI4: 32352313 | AJ4: 32352313 | AK4: 32352313 | AL4: 32352313 | AM4: 32352313 | AN4: 32352313 | AO4: 32352313 | AP4: 32352313 | AQ4: 32352313 | AR4: 32352313
A5: 2023-04 | B5: 8794888.2 | C5: 22912091 | D5: 29013651 | E5: 31301397 | F5: 32075179 | G5: 32312297 | H5: 32390139 | I5: 32415055 | J5: 32422812 | K5: 32425159 | L5: 32425909 | M5: 32426139 | N5: 32426208 | O5: 32426228 | P5: 32426234 | Q5: 32426236 | R5: 32426237 | S5: 32426237 | T5: 32426237 | U5: 32426237 | V5: 32426237 | W5: 32426237 | X5: 32426237 | Y5: 32426237 | Z5: 32426237 | AA5: 32426237 | AB5: 32426237 | AC5: 32426237 | AD5: 32426237 | AE5: 32426237 | AF5: 32426237 | AG5: 32426237 | AH5: 32426237 | AI5: 32426237 | AJ5: 32426237 | AK5: 32426237 | AL5: 32426237 | AM5: 32426237 | AN5: 32426237 | AO5: 32426237 | AP5: 32426237 | AQ5: 32426237
A6: 2023-05 | B6: 9557486.3 | C6: 22968891 | D6: 28896945 | E6: 31176959 | F6: 31955804 | G6: 32214670 | H6: 32295566 | I6: 32321744 | J6: 32329540 | K6: 32332072 | L6: 32332838 | M6: 32333072 | N6: 32333139 | O6: 32333160 | P6: 32333166 | Q6: 32333168 | R6: 32333169 | S6: 32333169 | T6: 32333169 | U6: 32333169 | V6: 32333169 | W6: 32333169 | X6: 32333169 | Y6: 32333169 | Z6: 32333169 | AA6: 32333169 | AB6: 32333169 | AC6: 32333169 | AD6: 32333169 | AE6: 32333169 | AF6: 32333169 | AG6: 32333169 | AH6: 32333169 | AI6: 32333169 | AJ6: 32333169 | AK6: 32333169 | AL6: 32333169 | AM6: 32333169 | AN6: 32333169 | AO6: 32333169 | AP6: 32333169
A7: 2023-06 | B7: 8768941.2 | C7: 22672049 | D7: 28490370 | E7: 30692026 | F7: 31432272 | G7: 31678976 | H7: 31758245 | I7: 31783843 | J7: 31791689 | K7: 31793946 | L7: 31794690 | M7: 31794906 | N7: 31794972 | O7: 31794991 | P7: 31794997 | Q7: 31794999 | R7: 31794999 | S7: 31794999 | T7: 31794999 | U7: 31794999 | V7: 31794999 | W7: 31794999 | X7: 31794999 | Y7: 31794999 | Z7: 31794999 | AA7: 31794999 | AB7: 31794999 | AC7: 31794999 | AD7: 31794999 | AE7: 31794999 | AF7: 31794999 | AG7: 31794999 | AH7: 31794999 | AI7: 31794999 | AJ7: 31794999 | AK7: 31794999 | AL7: 31794999 | AM7: 31794999 | AN7: 31794999 | AO7: 31794999
A8: 2023-07 | B8: 8673349.9 | C8: 21954163 | D8: 27990035 | E8: 30132522 | F8: 30852062 | G8: 31091605 | H8: 31168706 | I8: 31193160 | J8: 31200693 | K8: 31202967 | L8: 31203670 | M8: 31203883 | N8: 31203942 | O8: 31203961 | P8: 31203966 | Q8: 31203968 | R8: 31203968 | S8: 31203969 | T8: 31203969 | U8: 31203969 | V8: 31203969 | W8: 31203969 | X8: 31203969 | Y8: 31203969 | Z8: 31203969 | AA8: 31203969 | AB8: 31203969 | AC8: 31203969 | AD8: 31203969 | AE8: 31203969 | AF8: 31203969 | AG8: 31203969 | AH8: 31203969 | AI8: 31203969 | AJ8: 31203969 | AK8: 31203969 | AL8: 31203969 | AM8: 31203969 | AN8: 31203969
A9: 2023-08 | B9: 9726800 | C9: 23627624 | D9: 29947954 | E9: 32139271 | F9: 32876551 | G9: 33120398 | H9: 33195821 | I9: 33218570 | J9: 33225706 | K9: 33228008 | L9: 33228693 | M9: 33228887 | N9: 33228949 | O9: 33228968 | P9: 33228973 | Q9: 33228974 | R9: 33228975 | S9: 33228975 | T9: 33228975 | U9: 33228975 | V9: 33228975 | W9: 33228975 | X9: 33228975 | Y9: 33228975 | Z9: 33228975 | AA9: 33228975 | AB9: 33228975 | AC9: 33228975 | AD9: 33228975 | AE9: 33228975 | AF9: 33228975 | AG9: 33228975 | AH9: 33228975 | AI9: 33228975 | AJ9: 33228975 | AK9: 33228975 | AL9: 33228975 | AM9: 33228975
A10: 2023-09 | B10: 9383356.9 | C10: 23556984 | D10: 29753617 | E10: 31998852 | F10: 32758003 | G10: 33002552 | H10: 33083270 | I10: 33107365 | J10: 33114754 | K10: 33117030 | L10: 33117687 | M10: 33117880 | N10: 33117941 | O10: 33117959 | P10: 33117964 | Q10: 33117965 | R10: 33117966 | S10: 33117966 | T10: 33117966 | U10: 33117966 | V10: 33117966 | W10: 33117966 | X10: 33117966 | Y10: 33117966 | Z10: 33117966 | AA10: 33117966 | AB10: 33117966 | AC10: 33117966 | AD10: 33117966 | AE10: 33117966 | AF10: 33117966 | AG10: 33117966 | AH10: 33117966 | AI10: 33117966 | AJ10: 33117966 | AK10: 33117966 | AL10: 33117966
A11: 2023-10 | B11: 9427633.1 | C11: 23906394 | D11: 29996187 | E11: 32223328 | F11: 32995790 | G11: 33232878 | H11: 33306230 | I11: 33329858 | J11: 33336909 | K11: 33339072 | L11: 33339757 | M11: 33339950 | N11: 33340010 | O11: 33340028 | P11: 33340033 | Q11: 33340035 | R11: 33340035 | S11: 33340035 | T11: 33340035 | U11: 33340035 | V11: 33340035 | W11: 33340035 | X11: 33340035 | Y11: 33340035 | Z11: 33340035 | AA11: 33340035 | AB11: 33340035 | AC11: 33340035 | AD11: 33340035 | AE11: 33340035 | AF11: 33340035 | AG11: 33340035 | AH11: 33340035 | AI11: 33340035 | AJ11: 33340035 | AK11: 33340035
A12: 2023-11 | B12: 10267028 | C12: 25024940 | D12: 31409483 | E12: 33613101 | F12: 34361936 | G12: 34601673 | H12: 34681748 | I12: 34705438 | J12: 34712672 | K12: 34714763 | L12: 34715448 | M12: 34715637 | N12: 34715692 | O12: 34715708 | P12: 34715713 | Q12: 34715715 | R12: 34715715 | S12: 34715715 | T12: 34715715 | U12: 34715716 | V12: 34715716 | W12: 34715716 | X12: 34715716 | Y12: 34715716 | Z12: 34715716 | AA12: 34715716 | AB12: 34715716 | AC12: 34715716 | AD12: 34715716 | AE12: 34715716 | AF12: 34715716 | AG12: 34715716 | AH12: 34715716 | AI12: 34715716 | AJ12: 34715716
A13: 2023-12 | B13: 11142721 | C13: 27855192 | D13: 34658969 | E13: 37058198 | F13: 37850022 | G13: 38106052 | H13: 38186214 | I13: 38211120 | J13: 38218664 | K13: 38220899 | L13: 38221567 | M13: 38221770 | N13: 38221829 | O13: 38221846 | P13: 38221851 | Q13: 38221853 | R13: 38221853 | S13: 38221853 | T13: 38221853 | U13: 38221853 | V13: 38221853 | W13: 38221853 | X13: 38221853 | Y13: 38221853 | Z13: 38221853 | AA13: 38221853 | AB13: 38221853 | AC13: 38221853 | AD13: 38221853 | AE13: 38221853 | AF13: 38221853 | AG13: 38221853 | AH13: 38221853 | AI13: 38221853
A14: 2024-01 | B14: 9919660.5 | C14: 23714892 | D14: 29912265 | E14: 32000231 | F14: 32731530 | G14: 32972196 | H14: 33043828 | I14: 33066105 | J14: 33073232 | K14: 33075353 | L14: 33075966 | M14: 33076140 | N14: 33076191 | O14: 33076206 | P14: 33076211 | Q14: 33076212 | R14: 33076212 | S14: 33076212 | T14: 33076212 | U14: 33076212 | V14: 33076212 | W14: 33076212 | X14: 33076212 | Y14: 33076212 | Z14: 33076212 | AA14: 33076212 | AB14: 33076212 | AC14: 33076212 | AD14: 33076212 | AE14: 33076212 | AF14: 33076212 | AG14: 33076212 | AH14: 33076212
A15: 2024-02 | B15: 9457105.7 | C15: 23539141 | D15: 29515751 | E15: 31671749 | F15: 32371672 | G15: 32582428 | H15: 32648395 | I15: 32670138 | J15: 32676605 | K15: 32678394 | L15: 32678954 | M15: 32679113 | N15: 32679158 | O15: 32679172 | P15: 32679176 | Q15: 32679177 | R15: 32679177 | S15: 32679177 | T15: 32679178 | U15: 32679178 | V15: 32679178 | W15: 32679178 | X15: 32679178 | Y15: 32679178 | Z15: 32679178 | AA15: 32679178 | AB15: 32679178 | AC15: 32679178 | AD15: 32679178 | AE15: 32679178 | AF15: 32679178 | AG15: 32679178
A16: 2024-03 | B16: 10717325 | C16: 26542391 | D16: 33099217 | E16: 35476101 | F16: 36292967 | G16: 36551902 | H16: 36631710 | I16: 36655425 | J16: 36662913 | K16: 36665171 | L16: 36665793 | M16: 36665977 | N16: 36666032 | O16: 36666049 | P16: 36666053 | Q16: 36666055 | R16: 36666055 | S16: 36666055 | T16: 36666055 | U16: 36666055 | V16: 36666055 | W16: 36666055 | X16: 36666055 | Y16: 36666055 | Z16: 36666055 | AA16: 36666055 | AB16: 36666055 | AC16: 36666055 | AD16: 36666055 | AE16: 36666055 | AF16: 36666055
A17: 2024-04 | B17: 10689165 | C17: 26656325 | D17: 33067882 | E17: 35451129 | F17: 36243763 | G17: 36478549 | H17: 36551592 | I17: 36572376 | J17: 36578811 | K17: 36580714 | L17: 36581275 | M17: 36581442 | N17: 36581493 | O17: 36581507 | P17: 36581510 | Q17: 36581511 | R17: 36581512 | S17: 36581512 | T17: 36581512 | U17: 36581512 | V17: 36581512 | W17: 36581512 | X17: 36581512 | Y17: 36581512 | Z17: 36581512 | AA17: 36581512 | AB17: 36581512 | AC17: 36581512 | AD17: 36581512 | AE17: 36581512
A18: 2024-05 | B18: 10500557 | C18: 26718122 | D18: 33315875 | E18: 35604479 | F18: 36342408 | G18: 36563097 | H18: 36635363 | I18: 36657973 | J18: 36664514 | K18: 36666500 | L18: 36667033 | M18: 36667197 | N18: 36667241 | O18: 36667254 | P18: 36667259 | Q18: 36667260 | R18: 36667260 | S18: 36667260 | T18: 36667260 | U18: 36667260 | V18: 36667260 | W18: 36667260 | X18: 36667260 | Y18: 36667260 | Z18: 36667260 | AA18: 36667260 | AB18: 36667260 | AC18: 36667260 | AD18: 36667260
A19: 2024-06 | B19: 10640333 | C19: 26196735 | D19: 32575697 | E19: 34759599 | F19: 35466716 | G19: 35697120 | H19: 35767506 | I19: 35788969 | J19: 35795333 | K19: 35797161 | L19: 35797705 | M19: 35797863 | N19: 35797908 | O19: 35797922 | P19: 35797925 | Q19: 35797926 | R19: 35797927 | S19: 35797927 | T19: 35797927 | U19: 35797927 | V19: 35797927 | W19: 35797927 | X19: 35797927 | Y19: 35797927 | Z19: 35797927 | AA19: 35797927 | AB19: 35797927 | AC19: 35797927
A20: 2024-07 | B20: 10174092 | C20: 25839247 | D20: 32238947 | E20: 34481409 | F20: 35205632 | G20: 35432332 | H20: 35502673 | I20: 35522884 | J20: 35529164 | K20: 35530952 | L20: 35531478 | M20: 35531627 | N20: 35531668 | O20: 35531680 | P20: 35531684 | Q20: 35531685 | R20: 35531685 | S20: 35531685 | T20: 35531685 | U20: 35531685 | V20: 35531685 | W20: 35531685 | X20: 35531685 | Y20: 35531685 | Z20: 35531685 | AA20: 35531685 | AB20: 35531685
A21: 2024-08 | B21: 11073648 | C21: 26952203 | D21: 33605405 | E21: 35939508 | F21: 36739703 | G21: 36980061 | H21: 37051950 | I21: 37074160 | J21: 37080339 | K21: 37082188 | L21: 37082698 | M21: 37082857 | N21: 37082902 | O21: 37082914 | P21: 37082918 | Q21: 37082919 | R21: 37082919 | S21: 37082919 | T21: 37082919 | U21: 37082919 | V21: 37082919 | W21: 37082919 | X21: 37082919 | Y21: 37082919 | Z21: 37082919 | AA21: 37082919
A22: 2024-09 | B22: 10624714 | C22: 25618543 | D22: 32078609 | E22: 34193449 | F22: 34896601 | G22: 35114637 | H22: 35176540 | I22: 35195174 | J22: 35201080 | K22: 35202796 | L22: 35203260 | M22: 35203400 | N22: 35203439 | O22: 35203450 | P22: 35203454 | Q22: 35203454 | R22: 35203455 | S22: 35203455 | T22: 35203455 | U22: 35203455 | V22: 35203455 | W22: 35203455 | X22: 35203455 | Y22: 35203455 | Z22: 35203455
A23: 2024-10 | B23: 11864267 | C23: 28305861 | D23: 35478183 | E23: 37987208 | F23: 38780266 | G23: 39021827 | H23: 39099313 | I23: 39121154 | J23: 39127450 | K23: 39129239 | L23: 39129777 | M23: 39129923 | N23: 39129965 | O23: 39129977 | P23: 39129980 | Q23: 39129981 | R23: 39129982 | S23: 39129982 | T23: 39129982 | U23: 39129982 | V23: 39129982 | W23: 39129982 | X23: 39129982 | Y23: 39129982
A24: 2024-11 | B24: 10947125 | C24: 26998234 | D24: 33491594 | E24: 35778185 | F24: 36454260 | G24: 36689500 | H24: 36751525 | I24: 36770720 | J24: 36776732 | K24: 36778329 | L24: 36778819 | M24: 36778954 | N24: 36778993 | O24: 36779003 | P24: 36779006 | Q24: 36779007 | R24: 36779007 | S24: 36779008 | T24: 36779008 | U24: 36779008 | V24: 36779008 | W24: 36779008 | X24: 36779008
A25: 2024-12 | B25: 11777908 | C25: 29254183 | D25: 36100119 | E25: 38439883 | F25: 39223527 | G25: 39453943 | H25: 39525572 | I25: 39545938 | J25: 39551675 | K25: 39553331 | L25: 39553788 | M25: 39553926 | N25: 39553964 | O25: 39553975 | P25: 39553978 | Q25: 39553979 | R25: 39553979 | S25: 39553979 | T25: 39553979 | U25: 39553979 | V25: 39553979 | W25: 39553979
A26: 2025-01 | B26: 10980821 | C26: 27662514 | D26: 34047507 | E26: 36355168 | F26: 37004259 | G26: 37214460 | H26: 37278749 | I26: 37296825 | J26: 37302260 | K26: 37303807 | L26: 37304233 | M26: 37304353 | N26: 37304390 | O26: 37304400 | P26: 37304402 | Q26: 37304403 | R26: 37304403 | S26: 37304404 | T26: 37304404 | U26: 37304404 | V26: 37304404
A27: 2025-02 | B27: 11486967 | C27: 28081557 | D27: 34774359 | E27: 36992421 | F27: 37730158 | G27: 37945665 | H27: 38007866 | I27: 38027534 | J27: 38032662 | K27: 38034224 | L27: 38034677 | M27: 38034798 | N27: 38034833 | O27: 38034843 | P27: 38034846 | Q27: 38034846 | R27: 38034846 | S27: 38034847 | T27: 38034847 | U27: 38034847
A28: 2025-03 | B28: 12494844 | C28: 30711291 | D28: 38306808 | E28: 40807359 | F28: 41574585 | G28: 41812718 | H28: 41883476 | I28: 41904315 | J28: 41910200 | K28: 41911907 | L28: 41912377 | M28: 41912506 | N28: 41912542 | O28: 41912552 | P28: 41912555 | Q28: 41912555 | R28: 41912556 | S28: 41912556 | T28: 41912556
A29: 2025-04 | B29: 11730853 | C29: 28700639 | D29: 35357679 | E29: 37593993 | F29: 38329003 | G29: 38542755 | H29: 38605553 | I29: 38624067 | J29: 38629286 | K29: 38630757 | L29: 38631163 | M29: 38631281 | N29: 38631314 | O29: 38631323 | P29: 38631325 | Q29: 38631326 | R29: 38631326 | S29: 38631326
A30: 2025-05 | B30: 12274142 | C30: 29470723 | D30: 36240778 | E30: 38535862 | F30: 39283424 | G30: 39493352 | H30: 39556151 | I30: 39574212 | J30: 39579621 | K30: 39581101 | L30: 39581520 | M30: 39581636 | N30: 39581669 | O30: 39581676 | P30: 39581680 | Q30: 39581681 | R30: 39581681
A31: 2025-06 | B31: 11406593 | C31: 28540514 | D31: 35129492 | E31: 37297022 | F31: 37984143 | G31: 38194433 | H31: 38253220 | I31: 38269906 | J31: 38274860 | K31: 38276229 | L31: 38276615 | M31: 38276717 | N31: 38276744 | O31: 38276756 | P31: 38276758 | Q31: 38276759
A32: 2025-07 | B32: 11690589 | C32: 28204226 | D32: 34560127 | E32: 36779147 | F32: 37434728 | G32: 37626326 | H32: 37681382 | I32: 37696666 | J32: 37701221 | K32: 37702433 | L32: 37702770 | M32: 37702858 | N32: 37702897 | O32: 37702904 | P32: 37702906
A33: 2025-08 | B33: 12790088 | C33: 30184400 | D33: 36984770 | E33: 39339432 | F33: 40053588 | G33: 40286163 | H33: 40347558 | I33: 40365046 | J33: 40370192 | K33: 40371545 | L33: 40371883 | M33: 40372036 | N33: 40372066 | O33: 40372073
A34: 2025-09 | B34: 12898842 | C34: 30573592 | D34: 37335518 | E34: 39682469 | F34: 40415179 | G34: 40614745 | H34: 40675019 | I34: 40692799 | J34: 40697485 | K34: 40698684 | L34: 40699213 | M34: 40699317 | N34: 40699345
A35: 2025-10 | B35: 13192268 | C35: 30909864 | D35: 38446519 | E35: 40850121 | F35: 41570520 | G35: 41791770 | H35: 41854704 | I35: 41873468 | J35: 41877652 | K35: 41879571 | L35: 41879930 | M35: 41880029
A36: 2025-11 | B36: 12870133 | C36: 31286565 | D36: 38424393 | E36: 40731122 | F36: 41425907 | G36: 41631065 | H36: 41690707 | I36: 41705871 | J36: 41712563 | K36: 41713838 | L36: 41714189
A37: 2025-12 | B37: 14036201 | C37: 34214210 | D37: 41862542 | E37: 44477727 | F37: 45198691 | G37: 45417317 | H37: 45471223 | I37: 45495885 | J37: 45500878 | K37: 45502140
A38: 2026-01 | B38: 13568743 | C38: 31111617 | D38: 38323118 | E38: 40621321 | F38: 41323483 | G38: 41500031 | H38: 41581793 | I38: 41598046 | J38: 41602446
A39: 2026-02 | B39: 13097698 | C39: 31723438 | D39: 38470711 | E39: 40714634 | F39: 41314996 | G39: 41595644 | H39: 41647847 | I39: 41663359
A40: 2026-03 | B40: 13721024 | C40: 32505353 | D40: 39568428 | E40: 41532908 | F40: 42506105 | G40: 42729015 | H40: 42782524
A41: 2026-04 | B41: 14789334 | C41: 33789949 | D41: 40525295 | E41: 43814991 | F41: 44531305 | G41: 44745681
A42: 2026-05 | B42: 13863018 | C42: 30995970 | D42: 40939799 | E42: 43357639 | F42: 44043127
A43: 2026-06 | B43: 12217962 | C43: 32684019 | D43: 39687885 | E43: 41964304
A44: 2026-07 | B44: 14048239 | C44: 32695920 | D44: 39926812
A45: 2026-08 | B45: 15164993 | C45: 35564967
A46: 2026-09 | B46: 14239496

Sheet Prof Ratios
A1: Incurred | B1: 0-1 | C1: 1-2 | D1: 2-3 | E1: 3-4 | F1: 4-5 | G1: 5-6 | H1: 6-7 | I1: 7-8 | J1: 8-9 | K1: 9-10 | L1: 10-11 | M1: 11-12 | N1: 12-13 | O1: 13-14 | P1: 14-15 | Q1: 15-16 | R1: 16-17 | S1: 17-18 | T1: 18-19 | U1: 19-20 | V1: 20-21 | W1: 21-22 | X1: 22-23 | Y1: 23-24 | Z1: 24-25 | AA1: 25-26 | AB1: 26-27 | AC1: 27-28 | AD1: 28-29 | AE1: 29-30 | AF1: 30-31 | AG1: 31-32 | AH1: 32-33 | AI1: 33-34 | AJ1: 34-35 | AK1: 35-36 | AL1: 36-37 | AM1: 37-38 | AN1: 38-39 | AO1: 39-40 | AP1: 40-41 | AQ1: 41-42 | AR1: 42-43 | AS1: 43-44
A2: 2023-01 | B2: =IF('Prof Triangle'!B2>0,'Prof Triangle'!C2/'Prof Triangle'!B2,"") | C2: =IF('Prof Triangle'!C2>0,'Prof Triangle'!D2/'Prof Triangle'!C2,"") | D2: =IF('Prof Triangle'!D2>0,'Prof Triangle'!E2/'Prof Triangle'!D2,"") | E2: =IF('Prof Triangle'!E2>0,'Prof Triangle'!F2/'Prof Triangle'!E2,"") | F2: =IF('Prof Triangle'!F2>0,'Prof Triangle'!G2/'Prof Triangle'!F2,"") | G2: =IF('Prof Triangle'!G2>0,'Prof Triangle'!H2/'Prof Triangle'!G2,"") | H2: =IF('Prof Triangle'!H2>0,'Prof Triangle'!I2/'Prof Triangle'!H2,"") | I2: =IF('Prof Triangle'!I2>0,'Prof Triangle'!J2/'Prof Triangle'!I2,"") | ... AS2: =IF('Prof Triangle'!AS2>0,'Prof Triangle'!AT2/'Prof Triangle'!AS2,"")
A3: 2023-02 | B3: =IF('Prof Triangle'!B3>0,'Prof Triangle'!C3/'Prof Triangle'!B3,"") | C3: =IF('Prof Triangle'!C3>0,'Prof Triangle'!D3/'Prof Triangle'!C3,"") | D3: =IF('Prof Triangle'!D3>0,'Prof Triangle'!E3/'Prof Triangle'!D3,"") | E3: =IF('Prof Triangle'!E3>0,'Prof Triangle'!F3/'Prof Triangle'!E3,"") | F3: =IF('Prof Triangle'!F3>0,'Prof Triangle'!G3/'Prof Triangle'!F3,"") | G3: =IF('Prof Triangle'!G3>0,'Prof Triangle'!H3/'Prof Triangle'!G3,"") | H3: =IF('Prof Triangle'!H3>0,'Prof Triangle'!I3/'Prof Triangle'!H3,"") | I3: =IF('Prof Triangle'!I3>0,'Prof Triangle'!J3/'Prof Triangle'!I3,"") | ... AR3: =IF('Prof Triangle'!AR3>0,'Prof Triangle'!AS3/'Prof Triangle'!AR3,"")
A4: 2023-03 | B4: =IF('Prof Triangle'!B4>0,'Prof Triangle'!C4/'Prof Triangle'!B4,"") | C4: =IF('Prof Triangle'!C4>0,'Prof Triangle'!D4/'Prof Triangle'!C4,"") | D4: =IF('Prof Triangle'!D4>0,'Prof Triangle'!E4/'Prof Triangle'!D4,"") | E4: =IF('Prof Triangle'!E4>0,'Prof Triangle'!F4/'Prof Triangle'!E4,"") | F4: =IF('Prof Triangle'!F4>0,'Prof Triangle'!G4/'Prof Triangle'!F4,"") | G4: =IF('Prof Triangle'!G4>0,'Prof Triangle'!H4/'Prof Triangle'!G4,"") | H4: =IF('Prof Triangle'!H4>0,'Prof Triangle'!I4/'Prof Triangle'!H4,"") | I4: =IF('Prof Triangle'!I4>0,'Prof Triangle'!J4/'Prof Triangle'!I4,"") | ... AQ4: =IF('Prof Triangle'!AQ4>0,'Prof Triangle'!AR4/'Prof Triangle'!AQ4,"")
A5: 2023-04 | B5: =IF('Prof Triangle'!B5>0,'Prof Triangle'!C5/'Prof Triangle'!B5,"") | C5: =IF('Prof Triangle'!C5>0,'Prof Triangle'!D5/'Prof Triangle'!C5,"") | D5: =IF('Prof Triangle'!D5>0,'Prof Triangle'!E5/'Prof Triangle'!D5,"") | E5: =IF('Prof Triangle'!E5>0,'Prof Triangle'!F5/'Prof Triangle'!E5,"") | F5: =IF('Prof Triangle'!F5>0,'Prof Triangle'!G5/'Prof Triangle'!F5,"") | G5: =IF('Prof Triangle'!G5>0,'Prof Triangle'!H5/'Prof Triangle'!G5,"") | H5: =IF('Prof Triangle'!H5>0,'Prof Triangle'!I5/'Prof Triangle'!H5,"") | I5: =IF('Prof Triangle'!I5>0,'Prof Triangle'!J5/'Prof Triangle'!I5,"") | ... AP5: =IF('Prof Triangle'!AP5>0,'Prof Triangle'!AQ5/'Prof Triangle'!AP5,"")
A6: 2023-05 | B6: =IF('Prof Triangle'!B6>0,'Prof Triangle'!C6/'Prof Triangle'!B6,"") | C6: =IF('Prof Triangle'!C6>0,'Prof Triangle'!D6/'Prof Triangle'!C6,"") | D6: =IF('Prof Triangle'!D6>0,'Prof Triangle'!E6/'Prof Triangle'!D6,"") | E6: =IF('Prof Triangle'!E6>0,'Prof Triangle'!F6/'Prof Triangle'!E6,"") | F6: =IF('Prof Triangle'!F6>0,'Prof Triangle'!G6/'Prof Triangle'!F6,"") | G6: =IF('Prof Triangle'!G6>0,'Prof Triangle'!H6/'Prof Triangle'!G6,"") | H6: =IF('Prof Triangle'!H6>0,'Prof Triangle'!I6/'Prof Triangle'!H6,"") | I6: =IF('Prof Triangle'!I6>0,'Prof Triangle'!J6/'Prof Triangle'!I6,"") | ... AO6: =IF('Prof Triangle'!AO6>0,'Prof Triangle'!AP6/'Prof Triangle'!AO6,"")
A7: 2023-06 | B7: =IF('Prof Triangle'!B7>0,'Prof Triangle'!C7/'Prof Triangle'!B7,"") | C7: =IF('Prof Triangle'!C7>0,'Prof Triangle'!D7/'Prof Triangle'!C7,"") | D7: =IF('Prof Triangle'!D7>0,'Prof Triangle'!E7/'Prof Triangle'!D7,"") | E7: =IF('Prof Triangle'!E7>0,'Prof Triangle'!F7/'Prof Triangle'!E7,"") | F7: =IF('Prof Triangle'!F7>0,'Prof Triangle'!G7/'Prof Triangle'!F7,"") | G7: =IF('Prof Triangle'!G7>0,'Prof Triangle'!H7/'Prof Triangle'!G7,"") | H7: =IF('Prof Triangle'!H7>0,'Prof Triangle'!I7/'Prof Triangle'!H7,"") | I7: =IF('Prof Triangle'!I7>0,'Prof Triangle'!J7/'Prof Triangle'!I7,"") | ... AN7: =IF('Prof Triangle'!AN7>0,'Prof Triangle'!AO7/'Prof Triangle'!AN7,"")
A8: 2023-07 | B8: =IF('Prof Triangle'!B8>0,'Prof Triangle'!C8/'Prof Triangle'!B8,"") | C8: =IF('Prof Triangle'!C8>0,'Prof Triangle'!D8/'Prof Triangle'!C8,"") | D8: =IF('Prof Triangle'!D8>0,'Prof Triangle'!E8/'Prof Triangle'!D8,"") | E8: =IF('Prof Triangle'!E8>0,'Prof Triangle'!F8/'Prof Triangle'!E8,"") | F8: =IF('Prof Triangle'!F8>0,'Prof Triangle'!G8/'Prof Triangle'!F8,"") | G8: =IF('Prof Triangle'!G8>0,'Prof Triangle'!H8/'Prof Triangle'!G8,"") | H8: =IF('Prof Triangle'!H8>0,'Prof Triangle'!I8/'Prof Triangle'!H8,"") | I8: =IF('Prof Triangle'!I8>0,'Prof Triangle'!J8/'Prof Triangle'!I8,"") | ... AM8: =IF('Prof Triangle'!AM8>0,'Prof Triangle'!AN8/'Prof Triangle'!AM8,"")
A9: 2023-08 | B9: =IF('Prof Triangle'!B9>0,'Prof Triangle'!C9/'Prof Triangle'!B9,"") | C9: =IF('Prof Triangle'!C9>0,'Prof Triangle'!D9/'Prof Triangle'!C9,"") | D9: =IF('Prof Triangle'!D9>0,'Prof Triangle'!E9/'Prof Triangle'!D9,"") | E9: =IF('Prof Triangle'!E9>0,'Prof Triangle'!F9/'Prof Triangle'!E9,"") | F9: =IF('Prof Triangle'!F9>0,'Prof Triangle'!G9/'Prof Triangle'!F9,"") | G9: =IF('Prof Triangle'!G9>0,'Prof Triangle'!H9/'Prof Triangle'!G9,"") | H9: =IF('Prof Triangle'!H9>0,'Prof Triangle'!I9/'Prof Triangle'!H9,"") | I9: =IF('Prof Triangle'!I9>0,'Prof Triangle'!J9/'Prof Triangle'!I9,"") | ... AL9: =IF('Prof Triangle'!AL9>0,'Prof Triangle'!AM9/'Prof Triangle'!AL9,"")
A10: 2023-09 | B10: =IF('Prof Triangle'!B10>0,'Prof Triangle'!C10/'Prof Triangle'!B10,"") | C10: =IF('Prof Triangle'!C10>0,'Prof Triangle'!D10/'Prof Triangle'!C10,"") | D10: =IF('Prof Triangle'!D10>0,'Prof Triangle'!E10/'Prof Triangle'!D10,"") | E10: =IF('Prof Triangle'!E10>0,'Prof Triangle'!F10/'Prof Triangle'!E10,"") | F10: =IF('Prof Triangle'!F10>0,'Prof Triangle'!G10/'Prof Triangle'!F10,"") | G10: =IF('Prof Triangle'!G10>0,'Prof Triangle'!H10/'Prof Triangle'!G10,"") | H10: =IF('Prof Triangle'!H10>0,'Prof Triangle'!I10/'Prof Triangle'!H10,"") | I10: =IF('Prof Triangle'!I10>0,'Prof Triangle'!J10/'Prof Triangle'!I10,"") | ... AK10: =IF('Prof Triangle'!AK10>0,'Prof Triangle'!AL10/'Prof Triangle'!AK10,"")
A11: 2023-10 | B11: =IF('Prof Triangle'!B11>0,'Prof Triangle'!C11/'Prof Triangle'!B11,"") | C11: =IF('Prof Triangle'!C11>0,'Prof Triangle'!D11/'Prof Triangle'!C11,"") | D11: =IF('Prof Triangle'!D11>0,'Prof Triangle'!E11/'Prof Triangle'!D11,"") | E11: =IF('Prof Triangle'!E11>0,'Prof Triangle'!F11/'Prof Triangle'!E11,"") | F11: =IF('Prof Triangle'!F11>0,'Prof Triangle'!G11/'Prof Triangle'!F11,"") | G11: =IF('Prof Triangle'!G11>0,'Prof Triangle'!H11/'Prof Triangle'!G11,"") | H11: =IF('Prof Triangle'!H11>0,'Prof Triangle'!I11/'Prof Triangle'!H11,"") | I11: =IF('Prof Triangle'!I11>0,'Prof Triangle'!J11/'Prof Triangle'!I11,"") | ... AJ11: =IF('Prof Triangle'!AJ11>0,'Prof Triangle'!AK11/'Prof Triangle'!AJ11,"")
A12: 2023-11 | B12: =IF('Prof Triangle'!B12>0,'Prof Triangle'!C12/'Prof Triangle'!B12,"") | C12: =IF('Prof Triangle'!C12>0,'Prof Triangle'!D12/'Prof Triangle'!C12,"") | D12: =IF('Prof Triangle'!D12>0,'Prof Triangle'!E12/'Prof Triangle'!D12,"") | E12: =IF('Prof Triangle'!E12>0,'Prof Triangle'!F12/'Prof Triangle'!E12,"") | F12: =IF('Prof Triangle'!F12>0,'Prof Triangle'!G12/'Prof Triangle'!F12,"") | G12: =IF('Prof Triangle'!G12>0,'Prof Triangle'!H12/'Prof Triangle'!G12,"") | H12: =IF('Prof Triangle'!H12>0,'Prof Triangle'!I12/'Prof Triangle'!H12,"") | I12: =IF('Prof Triangle'!I12>0,'Prof Triangle'!J12/'Prof Triangle'!I12,"") | ... AI12: =IF('Prof Triangle'!AI12>0,'Prof Triangle'!AJ12/'Prof Triangle'!AI12,"")
A13: 2023-12 | B13: =IF('Prof Triangle'!B13>0,'Prof Triangle'!C13/'Prof Triangle'!B13,"") | C13: =IF('Prof Triangle'!C13>0,'Prof Triangle'!D13/'Prof Triangle'!C13,"") | D13: =IF('Prof Triangle'!D13>0,'Prof Triangle'!E13/'Prof Triangle'!D13,"") | E13: =IF('Prof Triangle'!E13>0,'Prof Triangle'!F13/'Prof Triangle'!E13,"") | F13: =IF('Prof Triangle'!F13>0,'Prof Triangle'!G13/'Prof Triangle'!F13,"") | G13: =IF('Prof Triangle'!G13>0,'Prof Triangle'!H13/'Prof Triangle'!G13,"") | H13: =IF('Prof Triangle'!H13>0,'Prof Triangle'!I13/'Prof Triangle'!H13,"") | I13: =IF('Prof Triangle'!I13>0,'Prof Triangle'!J13/'Prof Triangle'!I13,"") | ... AH13: =IF('Prof Triangle'!AH13>0,'Prof Triangle'!AI13/'Prof Triangle'!AH13,"")
A14: 2024-01 | B14: =IF('Prof Triangle'!B14>0,'Prof Triangle'!C14/'Prof Triangle'!B14,"") | C14: =IF('Prof Triangle'!C14>0,'Prof Triangle'!D14/'Prof Triangle'!C14,"") | D14: =IF('Prof Triangle'!D14>0,'Prof Triangle'!E14/'Prof Triangle'!D14,"") | E14: =IF('Prof Triangle'!E14>0,'Prof Triangle'!F14/'Prof Triangle'!E14,"") | F14: =IF('Prof Triangle'!F14>0,'Prof Triangle'!G14/'Prof Triangle'!F14,"") | G14: =IF('Prof Triangle'!G14>0,'Prof Triangle'!H14/'Prof Triangle'!G14,"") | H14: =IF('Prof Triangle'!H14>0,'Prof Triangle'!I14/'Prof Triangle'!H14,"") | I14: =IF('Prof Triangle'!I14>0,'Prof Triangle'!J14/'Prof Triangle'!I14,"") | ... AG14: =IF('Prof Triangle'!AG14>0,'Prof Triangle'!AH14/'Prof Triangle'!AG14,"")
A15: 2024-02 | B15: =IF('Prof Triangle'!B15>0,'Prof Triangle'!C15/'Prof Triangle'!B15,"") | C15: =IF('Prof Triangle'!C15>0,'Prof Triangle'!D15/'Prof Triangle'!C15,"") | D15: =IF('Prof Triangle'!D15>0,'Prof Triangle'!E15/'Prof Triangle'!D15,"") | E15: =IF('Prof Triangle'!E15>0,'Prof Triangle'!F15/'Prof Triangle'!E15,"") | F15: =IF('Prof Triangle'!F15>0,'Prof Triangle'!G15/'Prof Triangle'!F15,"") | G15: =IF('Prof Triangle'!G15>0,'Prof Triangle'!H15/'Prof Triangle'!G15,"") | H15: =IF('Prof Triangle'!H15>0,'Prof Triangle'!I15/'Prof Triangle'!H15,"") | I15: =IF('Prof Triangle'!I15>0,'Prof Triangle'!J15/'Prof Triangle'!I15,"") | ... AF15: =IF('Prof Triangle'!AF15>0,'Prof Triangle'!AG15/'Prof Triangle'!AF15,"")
A16: 2024-03 | B16: =IF('Prof Triangle'!B16>0,'Prof Triangle'!C16/'Prof Triangle'!B16,"") | C16: =IF('Prof Triangle'!C16>0,'Prof Triangle'!D16/'Prof Triangle'!C16,"") | D16: =IF('Prof Triangle'!D16>0,'Prof Triangle'!E16/'Prof Triangle'!D16,"") | E16: =IF('Prof Triangle'!E16>0,'Prof Triangle'!F16/'Prof Triangle'!E16,"") | F16: =IF('Prof Triangle'!F16>0,'Prof Triangle'!G16/'Prof Triangle'!F16,"") | G16: =IF('Prof Triangle'!G16>0,'Prof Triangle'!H16/'Prof Triangle'!G16,"") | H16: =IF('Prof Triangle'!H16>0,'Prof Triangle'!I16/'Prof Triangle'!H16,"") | I16: =IF('Prof Triangle'!I16>0,'Prof Triangle'!J16/'Prof Triangle'!I16,"") | ... AE16: =IF('Prof Triangle'!AE16>0,'Prof Triangle'!AF16/'Prof Triangle'!AE16,"")
A17: 2024-04 | B17: =IF('Prof Triangle'!B17>0,'Prof Triangle'!C17/'Prof Triangle'!B17,"") | C17: =IF('Prof Triangle'!C17>0,'Prof Triangle'!D17/'Prof Triangle'!C17,"") | D17: =IF('Prof Triangle'!D17>0,'Prof Triangle'!E17/'Prof Triangle'!D17,"") | E17: =IF('Prof Triangle'!E17>0,'Prof Triangle'!F17/'Prof Triangle'!E17,"") | F17: =IF('Prof Triangle'!F17>0,'Prof Triangle'!G17/'Prof Triangle'!F17,"") | G17: =IF('Prof Triangle'!G17>0,'Prof Triangle'!H17/'Prof Triangle'!G17,"") | H17: =IF('Prof Triangle'!H17>0,'Prof Triangle'!I17/'Prof Triangle'!H17,"") | I17: =IF('Prof Triangle'!I17>0,'Prof Triangle'!J17/'Prof Triangle'!I17,"") | ... AD17: =IF('Prof Triangle'!AD17>0,'Prof Triangle'!AE17/'Prof Triangle'!AD17,"")
A18: 2024-05 | B18: =IF('Prof Triangle'!B18>0,'Prof Triangle'!C18/'Prof Triangle'!B18,"") | C18: =IF('Prof Triangle'!C18>0,'Prof Triangle'!D18/'Prof Triangle'!C18,"") | D18: =IF('Prof Triangle'!D18>0,'Prof Triangle'!E18/'Prof Triangle'!D18,"") | E18: =IF('Prof Triangle'!E18>0,'Prof Triangle'!F18/'Prof Triangle'!E18,"") | F18: =IF('Prof Triangle'!F18>0,'Prof Triangle'!G18/'Prof Triangle'!F18,"") | G18: =IF('Prof Triangle'!G18>0,'Prof Triangle'!H18/'Prof Triangle'!G18,"") | H18: =IF('Prof Triangle'!H18>0,'Prof Triangle'!I18/'Prof Triangle'!H18,"") | I18: =IF('Prof Triangle'!I18>0,'Prof Triangle'!J18/'Prof Triangle'!I18,"") | ... AC18: =IF('Prof Triangle'!AC18>0,'Prof Triangle'!AD18/'Prof Triangle'!AC18,"")
A19: 2024-06 | B19: =IF('Prof Triangle'!B19>0,'Prof Triangle'!C19/'Prof Triangle'!B19,"") | C19: =IF('Prof Triangle'!C19>0,'Prof Triangle'!D19/'Prof Triangle'!C19,"") | D19: =IF('Prof Triangle'!D19>0,'Prof Triangle'!E19/'Prof Triangle'!D19,"") | E19: =IF('Prof Triangle'!E19>0,'Prof Triangle'!F19/'Prof Triangle'!E19,"") | F19: =IF('Prof Triangle'!F19>0,'Prof Triangle'!G19/'Prof Triangle'!F19,"") | G19: =IF('Prof Triangle'!G19>0,'Prof Triangle'!H19/'Prof Triangle'!G19,"") | H19: =IF('Prof Triangle'!H19>0,'Prof Triangle'!I19/'Prof Triangle'!H19,"") | I19: =IF('Prof Triangle'!I19>0,'Prof Triangle'!J19/'Prof Triangle'!I19,"") | ... AB19: =IF('Prof Triangle'!AB19>0,'Prof Triangle'!AC19/'Prof Triangle'!AB19,"")
A20: 2024-07 | B20: =IF('Prof Triangle'!B20>0,'Prof Triangle'!C20/'Prof Triangle'!B20,"") | C20: =IF('Prof Triangle'!C20>0,'Prof Triangle'!D20/'Prof Triangle'!C20,"") | D20: =IF('Prof Triangle'!D20>0,'Prof Triangle'!E20/'Prof Triangle'!D20,"") | E20: =IF('Prof Triangle'!E20>0,'Prof Triangle'!F20/'Prof Triangle'!E20,"") | F20: =IF('Prof Triangle'!F20>0,'Prof Triangle'!G20/'Prof Triangle'!F20,"") | G20: =IF('Prof Triangle'!G20>0,'Prof Triangle'!H20/'Prof Triangle'!G20,"") | H20: =IF('Prof Triangle'!H20>0,'Prof Triangle'!I20/'Prof Triangle'!H20,"") | I20: =IF('Prof Triangle'!I20>0,'Prof Triangle'!J20/'Prof Triangle'!I20,"") | ... AA20: =IF('Prof Triangle'!AA20>0,'Prof Triangle'!AB20/'Prof Triangle'!AA20,"")
A21: 2024-08 | B21: =IF('Prof Triangle'!B21>0,'Prof Triangle'!C21/'Prof Triangle'!B21,"") | C21: =IF('Prof Triangle'!C21>0,'Prof Triangle'!D21/'Prof Triangle'!C21,"") | D21: =IF('Prof Triangle'!D21>0,'Prof Triangle'!E21/'Prof Triangle'!D21,"") | E21: =IF('Prof Triangle'!E21>0,'Prof Triangle'!F21/'Prof Triangle'!E21,"") | F21: =IF('Prof Triangle'!F21>0,'Prof Triangle'!G21/'Prof Triangle'!F21,"") | G21: =IF('Prof Triangle'!G21>0,'Prof Triangle'!H21/'Prof Triangle'!G21,"") | H21: =IF('Prof Triangle'!H21>0,'Prof Triangle'!I21/'Prof Triangle'!H21,"") | I21: =IF('Prof Triangle'!I21>0,'Prof Triangle'!J21/'Prof Triangle'!I21,"") | ... Z21: =IF('Prof Triangle'!Z21>0,'Prof Triangle'!AA21/'Prof Triangle'!Z21,"")
A22: 2024-09 | B22: =IF('Prof Triangle'!B22>0,'Prof Triangle'!C22/'Prof Triangle'!B22,"") | C22: =IF('Prof Triangle'!C22>0,'Prof Triangle'!D22/'Prof Triangle'!C22,"") | D22: =IF('Prof Triangle'!D22>0,'Prof Triangle'!E22/'Prof Triangle'!D22,"") | E22: =IF('Prof Triangle'!E22>0,'Prof Triangle'!F22/'Prof Triangle'!E22,"") | F22: =IF('Prof Triangle'!F22>0,'Prof Triangle'!G22/'Prof Triangle'!F22,"") | G22: =IF('Prof Triangle'!G22>0,'Prof Triangle'!H22/'Prof Triangle'!G22,"") | H22: =IF('Prof Triangle'!H22>0,'Prof Triangle'!I22/'Prof Triangle'!H22,"") | I22: =IF('Prof Triangle'!I22>0,'Prof Triangle'!J22/'Prof Triangle'!I22,"") | ... Y22: =IF('Prof Triangle'!Y22>0,'Prof Triangle'!Z22/'Prof Triangle'!Y22,"")
